Workbook

Sheet Valuation Summary
B2: Valuation Summary
B3: Company Analysis
B4: Valuation Date | C4: =Assumptions!C19 -> 45591 | D4: Company Name | E4: =Assumptions!C30 -> Tyson Foods | F4: 52 Week High | G4: =_xlfn.XLOOKUP(F4,Assumptions!$B$33:$B$35,Assumptions!$C$33:$C$35,0) -> 66.88
B5: Team Name | C5: =Assumptions!C25 -> Market Mavericks | D5: Company Ticker | E5: =Assumptions!C31 -> TSN | F5: 52 Week Low | G5: =_xlfn.XLOOKUP(F5,Assumptions!$B$33:$B$35,Assumptions!$C$33:$C$35,0) -> 45.13
B6: Analyst Name | C6: Yash Agrawal | D6: Sector | E6: =Assumptions!C32 -> Consumer Staples | F6: Current Stock Price | G6: =_xlfn.XLOOKUP(F6,Assumptions!$B$33:$B$35,Assumptions!$C$33:$C$35,0) -> 58.67
B8: Valuation Scenarios
B9: Model | C9: Base | D9: Bear | E9: Spread | F9: Bull | G9: Weights | I9: Enter Weights | K9: Y-Values for Secondary Axis
B10: 52 Week Low / High | C10: =_xlfn.XLOOKUP(C9,Assumptions!$D$33:$D$35,Assumptions!$C$33:$C$35,0) -> 58.67 | D10: =_xlfn.XLOOKUP(D9,Assumptions!$D$33:$D$35,Assumptions!$C$33:$C$35,0) -> 45.13 | E10: =F10-D10 -> 21.75 | F10: =_xlfn.XLOOKUP(F9,Assumptions!$D$33:$D$35,Assumptions!$C$33:$C$35,0) -> 66.88 | K10: 1000 | L10: 0 | M10: 0
B11: Perpetuity DCF | C11: =_xlfn.XLOOKUP(C9,'Discounted Cash Flow'!$A$59:$A$61,'Discounted Cash Flow'!$C$59:$C$61,0) -> 92.240402 | D11: =_xlfn.XLOOKUP(D9,'Discounted Cash Flow'!$A$59:$A$61,'Discounted Cash Flow'!$C$59:$C$61,0) -> 90.044447 | E11: =F11-D11 -> 0.26891962 | F11: =_xlfn.XLOOKUP(F9,'Discounted Cash Flow'!$A$59:$A$61,'Discounted Cash Flow'!$C$59:$C$61,0) -> 90.313367 | G11: =I11 -> 0.05 | I11: 0.05 | K11: 1000 | L11: 0 | M11: 0
B12: EBITDA DCF | C12: =_xlfn.XLOOKUP(C9,'Discounted Cash Flow'!$A$59:$A$61,'Discounted Cash Flow'!$F$59:$F$61,0) -> 204.53676 | D12: =_xlfn.XLOOKUP(D9,'Discounted Cash Flow'!$A$59:$A$61,'Discounted Cash Flow'!$F$59:$F$61,0) -> 183.21167 | E12: =F12-D12 -> 40.379345 | F12: =_xlfn.XLOOKUP(F9,'Discounted Cash Flow'!$A$59:$A$61,'Discounted Cash Flow'!$F$59:$F$61,0) -> 223.59102 | G12: =I12 -> 0.15 | I12: 0.15
B13: Comparable Peers | C13: =_xlfn.XLOOKUP(C9,'Comparable Peer'!$A$32:$A$34,'Comparable Peer'!$C$32:$C$34,0) -> 22.52766 | D13: =_xlfn.XLOOKUP(D9,'Comparable Peer'!$A$32:$A$34,'Comparable Peer'!$C$32:$C$34,0) -> -33.107068 | E13: =F13-D13 -> 77.436547 | F13: =_xlfn.XLOOKUP(F9,'Comparable Peer'!$A$32:$A$34,'Comparable Peer'!$C$32:$C$34,0) -> 44.329479 | G13: =I13 -> 0.2 | I13: 0.2
B14: Internal Rate of Return | C14: =_xlfn.XLOOKUP(C9,'Internal Rate of Return'!$A$59:$A$61,'Internal Rate of Return'!$C$59:$C$61,0) -> 84.657 | D14: =_xlfn.XLOOKUP(D9,'Internal Rate of Return'!$A$59:$A$61,'Internal Rate of Return'!$C$59:$C$61,0) -> 82.59764 | E14: =F14-D14 -> -0.0023609774 | F14: =_xlfn.XLOOKUP(F9,'Internal Rate of Return'!$A$59:$A$61,'Internal Rate of Return'!$C$59:$C$61,0) -> 82.595279 | G14: =I14 -> 0.2 | I14: 0.2
B15: Dividend Discount | C15: =_xlfn.XLOOKUP(C9,'Dividend Discount'!$A$53:$A$55,'Dividend Discount'!$C$53:$C$55,0) -> 39.1153 | D15: =_xlfn.XLOOKUP(D9,'Dividend Discount'!$A$53:$A$55,'Dividend Discount'!$C$53:$C$55,0) -> 37.45197 | E15: =F15-D15 -> 3.3881178 | F15: =_xlfn.XLOOKUP(F9,'Dividend Discount'!$A$53:$A$55,'Dividend Discount'!$C$53:$C$55,0) -> 40.840088 | G15: =G16-SUM(G11:G14) -> 0.4
B16: Target Price | C16: =SUMPRODUCT(C11:C15,$G$11:$G$15) -> 72.375586 | D16: =SUMPRODUCT(D11:D15,$G$11:$G$15) -> 56.862876 | E16: =F16-D16 -> 22.912432 | F16: =SUMPRODUCT(F11:F15,$G$11:$G$15) -> 79.775308 | G16: 1 | I16: =+SUM(I11:I15)+G15 -> 1
B18: Current Stock Price versus Scenarios
C19: Current | D19: Bear | E19: Base | F19: Bull
B20: Stock Price | C20: =+$G$6 -> 58.67 | D20: =_xlfn.XLOOKUP(D19,$C$9:$F$9,$C$16:$F$16,0) -> 56.862876 | E20: =_xlfn.XLOOKUP(E19,$C$9:$F$9,$C$16:$F$16,0) -> 72.375586 | F20: =_xlfn.XLOOKUP(F19,$C$9:$F$9,$C$16:$F$16,0) -> 79.775308
B21: Upside (Downside) | D21: =D$20-$C20 -> -1.8071242 | E21: =E$20-$C20 -> 13.705586 | F21: =F$20-$C20 -> 21.105308
B22: Upside (Downside) % | D22: =D$20/$C$20-1 -> -0.030801503 | E22: =E$20/$C$20-1 -> 0.23360468 | F22: =F$20/$C$20-1 -> 0.35972913
B25: Current Stock Price | C25: =$G$6 -> 58.67 | D25: =$G$6 -> 58.67 | E25: =$G$6 -> 58.67 | F25: =$G$6 -> 58.67
B26: Target Price | C26: =$C$16 -> 72.375586 | D26: =$C$16 -> 72.375586 | E26: =$C$16 -> 72.375586 | F26: =$C$16 -> 72.375586

Sheet Assumptions
A2: B | B2: Bloomberg Functions used for this Analysis
B3: Function Description | C3: Function | D3: Template
B4: Financial Analysis | C4: FA
B5: Relative Valuation | C5: RV
B6: Security Description | C6: DES
B7: Company Financials | C7: MODL
B8: Weighted Average Cost of Capital | C8: WACC
B9: Comparable Relative Valuation | C9: EQRV
B11: Excel Template Library | C11: XLTP
B12: =$C$11&" Financial Analysis" -> XLTP Financial Analysis | C12: XFA
B13: =$C$11&" Discounted Cash Flow" -> XLTP Discounted Cash Flow | C13: XDCF
B14: =$C$11&" Bloomberg Comparable Valuation Analysis" -> XLTP Bloomberg Comparable Valuation Analysis | C14: XCVA
A16: A | B16: Assumptions
D17: {=_xlfn.SEQUENCE(1,5+$C$20,(YEAR($C$19)-5))} -> 2019 | E17: 2020 | F17: 2021 | G17: 2022 | H17: 2023 | I17: 2024 | J17: 2025 | K17: 2026 | L17: 2027 | M17: 2028
B18: Valuation Assumptions
B19: Valuation Date | C19: 45591
B20: Number of Forecasted Years | C20: 5 | D20: 3 | E20: 5 | F20: 7 | G20: 10
B21: Exit EV / EBITDA Multiple | C21: 15.97
B24: MSIF Analyst Team | H24: =D64/F64 -> 10.287483
B25: Team Name | C25: Market Mavericks
B26: Analyst Name | C26: Stephen Fredrick
B29: Company Specific Information
B30: Company Name | C30: Tyson Foods
B31: Company Ticker | C31: TSN
B32: Sector | C32: Consumer Staples
B33: 52 Week High | C33: 66.88 | D33: Bull
B34: 52 Week Low | C34: 45.13 | D34: Bear
B35: Current Stock Price | C35: 58.67 | D35: Base
B36: Shares Outstanding | C36: 285.8
B37: Year Ending | C37: 09/31/2024
B38: Currency | C38: USD
B39: ="In "&C38&" " -> In USD | C39: Millions
B42: Dividend Discount Model Assumptions
D43: 1 | E43: 2 | F43: 3 | G43: 4 | H43: 5
D44: {=_xlfn.SEQUENCE(1,5,(YEAR($C$19)-5))} -> 2019 | E44: 2020 | F44: 2021 | G44: 2022 | H44: 2023
B45: Annual Dividend | D45: =(0.42+3*0.375) -> 1.545 | E45: =(0.445+3*0.42) -> 1.705 | F45: =0.46+3*0.445 -> 1.795 | G45: =0.48+3*0.46 -> 1.86 | H45: =0.48+0.48+0.48+0.49 -> 1.93
B46: Compound Annual Growth Rate (CAGR) | C46: =((H45/D45)^(1/H43)-1) -> 0.04550416
B47: Bear | C47: =C46-D47 -> 0.03550416 | D47: 0.01
B48: Bull | C48: =C46+D48 -> 0.05550416 | D48: 0.01
B50: Custom Dividend Growth Rate | C50: 0.04
B51: Bear | C51: =C50-D51 -> 0.03 | D51: 0.01
B52: Bull | C52: =C50+D52 -> 0.05 | D52: 0.01
B54: Set Dividend Growth Rate = CAGR or Custom? | C54: CAGR | D54: CAGR | E54: Custom
B56: ="Annual Dividends Per Share - Last Paid "&H44 -> Annual Dividends Per Share - Last Paid 2023 | C56: =H45 -> 1.93
B57: Cost of Equity - From WACC | C57: =C121 -> 0.068229
B60: Comparable Peer Analysis Assumptions
C62: P / E | D62: EV | E62: LTM Sales | F62: LTM EBITDA
B63: Target Company
B64: =Assumptions!$C$30 -> Tyson Foods | C64: 24.6 | D64: 30327.5 | E64: 53092 | F64: 2948
B65: Comparable Peer Companies
B66: Pilgrim's Pride | C66: 12.1 | D66: 13208.2 | E66: 17809.7 | F66: 1678.3
B67: Hormel Foods Corp | C67: 18.4 | D67: 19340.2 | E67: 11980.8 | F67: 1307.8
B68: Maple Leaf | C68: 16.5 | D68: 4577 | E68: 4851.9 | F68: 499.7
A78: WACC | B78: Weighted Average Cost of Capital - Bloomberg
B79: ="Capital Structure, "&Assumptions!$B$39&Assumptions!$C$39 -> Capital Structure, In USD Millions
B80: Market Cap | C80: 20876.5
B81: % of Total Capital | C81: =C80/$C$92 -> 0.67536354
B83: Short Term Debt | C83: 2048
B84: % of Total Capital | C84: =C83/$C$92 -> 0.06625366
B85: Long Term Debt | C85: 7987
B86: % of Total Capital | C86: =C85/$C$92 -> 0.2583828
B87: Total Debt | C87: =C83+C85 -> 10035
B88: % of Total Capital | C88: =C87/$C$92 -> 0.32463646
B90: Preferred Equity | C90: 0
B91: % of Total Capital | C91: =C90/$C$92 -> 0
B92: Total Capital | C92: =SUM(C80,C87,C90) -> 30911.5
B94: ="Cost of Debt, "&Assumptions!$B$39&Assumptions!$C$39 -> Cost of Debt, In USD Millions
B95: Effective Tax Rate
B96: 1 - Effective Tax Rate | C96: =1-C95 -> 1
B98: Note Rate | C98: 0.0413
B99: Short Term Debt as % of Total Debt | C99: =C83/C87 -> 0.2040857
B100: Note Rate x Short Term Debt as % of Total Debt | C100: =C99*C98 -> 0.0084287394
B101: Bond Rate | C101: 0.0427
B102: Long Term Debt as % of Total Debt | C102: =C85/C87 -> 0.7959143
B103: Bond Rate x Long Term Debt as % of Total Debt | C103: =C101*C102 -> 0.033985541
B104: Total Pre-Tax Cost of Debt | C104: =C103+C100 -> 0.04241428
B106: Debt Adjustment Factor (Proprietary to Bloomberg) | C106: 1.43
B107: Total Cost of Debt | C107: =C106*C104*C96 -> 0.06065242
B109: ="Cost of Equity, "&Assumptions!$B$39&Assumptions!$C$39 -> Cost of Equity, In USD Millions
B110: Risk Free Rate | C110: 0.0427
B111: + Equity Risk Premium | C111: 0.0258
B112: Beta | C112: 0.49
B113: x Country / Region Premium | C113: =+C114-C115 -> 0.0521
B114: Expected Market Return | C114: 0.0948
B115: - Risk Free Rate | C115: =+C110 -> 0.0427
B116: Total Cost of Common Equity | C116: =C110+C112*C113 -> 0.068229
B117: Cost of Preferred Equity
B118: Preferred Dividend | C118: 0
B119: / Preferred Equity | C119: 0
B120: Total Cost of Preferred Equity | C120: =IFERROR(C118/C119,0) -> 0
B121: Total Cost of Equity | C121: =C116+C120 -> 0.068229
B123: Weighted Average Cost of Capital | C123: =C81*C116+C88*C107+C91*C120 -> 0.065769366
A131: IS | B131: Income Statement
B132: ="Year Ending "&TEXT($C$37,"mmmm d")&", "&$B$39&$C$39 -> Year Ending 09/31/2024, In USD Millions | C132: =D132-1 -> 2018 | D132: {=_xlfn.SEQUENCE(1,5+$C$20,(YEAR($C$19)-5))} -> 2019 | E132: 2020 | F132: 2021 | G132: 2022 | H132: 2023 | I132: 2024 | J132: 2025 | K132: 2026 | L132: 2027 | M132: 2028
B133: Perpetuity Growth Rate: | C133: 0.01
B134: Growth Rate Selected: | C134: Perpetual | D134: Perpetual | E134: 5 Year Average | F134: CAGR | G134: Custom
B136: Revenue | C136: 40052 | D136: 42405 | E136: 43185 | F136: 47049 | G136: 53282 | H136: 52881 | I136: 0.04 | J136: 0.04 | K136: 0.045 | L136: 0.05 | M136: 0.05 | N136: 0.05 | O136: 0.05 | P136: 0.05 | Q136: 0.05 | R136: 0.05
B137: Base | D137: =D136/C136-1 -> 0.058748627 | E137: =E136/D136-1 -> 0.018394057 | F137: =F136/E136-1 -> 0.089475512 | G137: =G136/F136-1 -> 0.1324789 | H137: =H136/G136-1 -> -0.0075259938 | I137: =IF(I132="",0, IF($C$134="Perpetual",$C$133, IF($C$134="Custom",I136, IF($C$134="CAGR",(($H$137/$D$137)^(1/COUNTA($D$136:$H$136))-1), AVERAGE($D$137:$H$137))))) -> 0.01 | J137: =IF(J132="",0, IF($C$134="Perpetual",$C$133, IF($C$134="Custom",J136, IF($C$134="CAGR",(($H$137/$D$137)^(1/COUNTA($D$136:$H$136))-1), AVERAGE($D$137:$H$137))))) -> 0.01 | K137: =IF(K132="",0, IF($C$134="Perpetual",$C$133, IF($C$134="Custom",K136, IF($C$134="CAGR",(($H$137/$D$137)^(1/COUNTA($D$136:$H$136))-1), AVERAGE($D$137:$H$137))))) -> 0.01 | L137: =IF(L132="",0, IF($C$134="Perpetual",$C$133, IF($C$134="Custom",L136, IF($C$134="CAGR",(($H$137/$D$137)^(1/COUNTA($D$136:$H$136))-1), AVERAGE($D$137:$H$137))))) -> 0.01 | M137: =IF(M132="",0, IF($C$134="Perpetual",$C$133, IF($C$134="Custom",M136, IF($C$134="CAGR",(($H$137/$D$137)^(1/COUNTA($D$136:$H$136))-1), AVERAGE($D$137:$H$137))))) -> 0.01 | N137: =IF(N132="",0, IF($C$134="Perpetual",$C$133, IF($C$134="Custom",N136, IF($C$134="CAGR",(($H$137/$D$137)^(1/COUNTA($D$136:$H$136))-1), AVERAGE($D$137:$H$137))))) -> 0 | O137: =IF(O132="",0, IF($C$134="Perpetual",$C$133, IF($C$134="Custom",O136, IF($C$134="CAGR",(($H$137/$D$137)^(1/COUNTA($D$136:$H$136))-1), AVERAGE($D$137:$H$137))))) -> 0 | P137: =IF(P132="",0, IF($C$134="Perpetual",$C$133, IF($C$134="Custom",P136, IF($C$134="CAGR",(($H$137/$D$137)^(1/COUNTA($D$136:$H$136))-1), AVERAGE($D$137:$H$137))))) -> 0 | ... R137: =IF(R132="",0, IF($C$134="Perpetual",$C$133, IF($C$134="Custom",R136, IF($C$134="CAGR",(($H$137/$D$137)^(1/COUNTA($D$136:$H$136))-1), AVERAGE($D$137:$H$137))))) -> 0
B138: Bear | C138: 0.02 | I138: =IF(I132="",0,I137-$C138) -> -0.01 | J138: =IF(J132="",0,J137-$C138) -> -0.01 | K138: =IF(K132="",0,K137-$C138) -> -0.01 | L138: =IF(L132="",0,L137-$C138) -> -0.01 | M138: =IF(M132="",0,M137-$C138) -> -0.01 | N138: =IF(N132="",0,N137-$C138) -> 0 | O138: =IF(O132="",0,O137-$C138) -> 0 | P138: =IF(P132="",0,P137-$C138) -> 0 | ... R138: =IF(R132="",0,R137-$C138) -> 0
B139: Bull | C139: 0.02 | I139: =IF(I132="",0,I137+$C139) -> 0.03 | J139: =IF(J132="",0,J137+$C139) -> 0.03 | K139: =IF(K132="",0,K137+$C139) -> 0.03 | L139: =IF(L132="",0,L137+$C139) -> 0.03 | M139: =IF(M132="",0,M137+$C139) -> 0.03 | N139: =IF(N132="",0,N137+$C139) -> 0 | O139: =IF(O132="",0,O137+$C139) -> 0 | P139: =IF(P132="",0,P137+$C139) -> 0 | ... R139: =IF(R132="",0,R137+$C139) -> 0
...

Sheet Discounted Cash Flow
B2: Perpetuity Growth Method - Value Per Share | E2: EBITDA Multiple Method - Value Per Share | H2: Discounted Cash Flow
A3: Base | B3: =_xlfn.TEXTBEFORE(B$2," - ")&" - "&$A3 -> Perpetuity Growth Method - Base | E3: =_xlfn.TEXTBEFORE(E$2," - ")&" - "&$A3 -> EBITDA Multiple Method - Base | H3: =Assumptions!$B$132 -> Year Ending 09/31/2024, In USD Millions | I3: {=_xlfn.SEQUENCE(1,Assumptions!$C$20,(YEAR(Assumptions!$C$19)))} -> 2024 | J3: 2025 | K3: 2026 | L3: 2027 | M3: 2028
B4: ="Free Cash Flow at Year "&COUNTA($I3:$R3) -> Free Cash Flow at Year 5 | C4: {=LOOKUP(2,1/($I15:$R15<>""),$I15:$R15)} -> 2060.8523 | E4: ="Terminal EBITDA at Year "&COUNTA($I3:$R3) -> Terminal EBITDA at Year 5 | F4: {=LOOKUP(2,1/($I4:$R4<>""),$I4:$R4)} -> 5100.4187 | H4: EBITDA | I4: =IF(I3="","",'Income Statement'!H$53) -> 4901.4021 | J4: =IF(J3="","",'Income Statement'!I$53) -> 4950.4161 | K4: =IF(K3="","",'Income Statement'!J$53) -> 4999.9203 | L4: =IF(L3="","",'Income Statement'!K$53) -> 5049.9195 | M4: =IF(M3="","",'Income Statement'!L$53) -> 5100.4187 | N4: =IF(N3="","",'Income Statement'!M$53) | O4: =IF(O3="","",'Income Statement'!N$53) | P4: =IF(P3="","",'Income Statement'!O$53) | ... R4: =IF(R3="","",'Income Statement'!Q$53)
B5: Weighted Average Cost of Capital | C5: =Assumptions!$C$123 -> 0.065769366 | E5: Weighted Average Cost of Capital | F5: =Assumptions!$C$123 -> 0.065769366
B6: Perpetuity Growth Rate | C6: =Assumptions!$C$133 -> 0.01 | E6: Exit EV / EBITDA Multiple | F6: =Assumptions!$C$21 -> 15.97 | H6: NOPAT | I6: =IF(I3="","",'Income Statement'!H$59) -> 2882.3235 | J6: =IF(J3="","",'Income Statement'!I$59) -> 2906.9493 | K6: =IF(K3="","",'Income Statement'!J$59) -> 2935.4675 | L6: =IF(L3="","",'Income Statement'!K$59) -> 2966.6102 | M6: =IF(M3="","",'Income Statement'!L$59) -> 2996.9328 | N6: =IF(N3="","",'Income Statement'!M$59) | O6: =IF(O3="","",'Income Statement'!N$59) | P6: =IF(P3="","",'Income Statement'!O$59) | ... R6: =IF(R3="","",'Income Statement'!Q$59)
B7: =+"Perpetuity Value at Year "&COUNTA($I3:$R3)&" ~ Terminal Value" -> Perpetuity Value at Year 5 ~ Terminal Value | C7: =(C4*(1+C6))/(C5-C6) -> 37322.656 | E7: =+"Perpetuity Value at Year "&COUNTA($I3:$R3)&" ~ Terminal Value" -> Perpetuity Value at Year 5 ~ Terminal Value | F7: =+F4*F6 -> 81453.687
H8: Depreciation and Amortization | I8: =IF(I3="","",'Income Statement'!H$47) -> 1392.2121 | J8: =IF(J3="","",'Income Statement'!I$47) -> 1406.1342 | K8: =IF(K3="","",'Income Statement'!J$47) -> 1420.1956 | L8: =IF(L3="","",'Income Statement'!K$47) -> 1434.3975 | M8: =IF(M3="","",'Income Statement'!L$47) -> 1448.7415 | N8: =IF(N3="","",'Income Statement'!M$47) | O8: =IF(O3="","",'Income Statement'!N$47) | P8: =IF(P3="","",'Income Statement'!O$47) | ... R8: =IF(R3="","",'Income Statement'!Q$47)
B9: Discounted Terminal Value | C9: =C7/(1+C5)^COUNTA($I3:$R3) -> 27142.908 | E9: Discounted Terminal Value | F9: =F7/(1+F5)^COUNTA($I3:$R3) -> 59237.208
B10: Present Value of Free Cash Flows | C10: =SUM($I18:$R18) -> 8803.3986 | E10: Present Value of Free Cash Flows | F10: =SUM($I18:$R18) -> 8803.3986 | H10: Capital Expenditures | I10: =IF(I3="","",'Income Statement'!H$44) -> 1658.1968 | J10: =IF(J3="","",'Income Statement'!I$44) -> 1674.7787 | K10: =IF(K3="","",'Income Statement'!J$44) -> 1691.5265 | L10: =IF(L3="","",'Income Statement'!K$44) -> 1708.4418 | M10: =IF(M3="","",'Income Statement'!L$44) -> 1725.5262 | N10: =IF(N3="","",'Income Statement'!M$44) | O10: =IF(O3="","",'Income Statement'!N$44) | P10: =IF(P3="","",'Income Statement'!O$44) | ... R10: =IF(R3="","",'Income Statement'!Q$44)
B11: Enterprise Value | C11: =C9+C10 -> 35946.307 | E11: Enterprise Value | F11: =F9+F10 -> 68040.607
H12: Net Working Capital Change | I12: =IF(I3="","",'Balance Sheet'!H$47-'Balance Sheet'!G$47) -> 1258.6371 | J12: =IF(J3="","",'Balance Sheet'!I$47-'Balance Sheet'!H$47) -> 1500.5313 | K12: =IF(K3="","",'Balance Sheet'!J$47-'Balance Sheet'!I$47) -> 1176.9184 | L12: =IF(L3="","",'Balance Sheet'!K$47-'Balance Sheet'!J$47) -> 607.51441 | M12: =IF(M3="","",'Balance Sheet'!L$47-'Balance Sheet'!K$47) -> 1314.0402 | N12: =IF(N3="","",'Balance Sheet'!M$47-'Balance Sheet'!L$47) | O12: =IF(O3="","",'Balance Sheet'!N$47-'Balance Sheet'!M$47) | P12: =IF(P3="","",'Balance Sheet'!O$47-'Balance Sheet'!N$47) | ... R12: =IF(R3="","",'Balance Sheet'!Q$47-'Balance Sheet'!P$47)
B13: Net Debt | C13: =+'Balance Sheet'!$G$48 -> 9462 | E13: Net Debt | F13: =+'Balance Sheet'!$G$48 -> 9462
B14: Minority Interest | C14: =+'Balance Sheet'!$G$37 -> 122 | E14: Minority Interest | F14: =+'Balance Sheet'!$G$37 -> 122 | H14: Taxes | I14: =IF(I3="","",'Income Statement'!H$31) -> 626.86646 | J14: =IF(J3="","",'Income Statement'!I$31) -> 637.33259 | K14: =IF(K3="","",'Income Statement'!J$31) -> 644.25721 | L14: =IF(L3="","",'Income Statement'!K$31) -> 648.91174 | M14: =IF(M3="","",'Income Statement'!L$31) -> 654.74439 | N14: =IF(N3="","",'Income Statement'!M$31) | O14: =IF(O3="","",'Income Statement'!N$31) | P14: =IF(P3="","",'Income Statement'!O$31) | ... R14: =IF(R3="","",'Income Statement'!Q$31)
B15: Equity Value | C15: =+C11-C13-C14 -> 26362.307 | E15: Equity Value | F15: =+F11-F13-F14 -> 58456.607 | H15: Free Cash Flow | I15: =IF(I3="","",I6+I8-I10-I12+I14) -> 1984.5683 | J15: =IF(J3="","",J6+J8-J10-J12+J14) -> 1775.1061 | K15: =IF(K3="","",K6+K8-K10-K12+K14) -> 2131.4753 | L15: =IF(L3="","",L6+L8-L10-L12+L14) -> 2733.9633 | M15: =IF(M3="","",M6+M8-M10-M12+M14) -> 2060.8523 | N15: =IF(N3="","",N6+N8-N10-N12+N14) | O15: =IF(O3="","",O6+O8-O10-O12+O14) | P15: =IF(P3="","",P6+P8-P10-P12+P14) | ... R15: =IF(R3="","",R6+R8-R10-R12+R14)
B17: Shares Outstanding | C17: =+Assumptions!$C$36 -> 285.8 | E17: Shares Outstanding | F17: =+Assumptions!$C$36 -> 285.8 | H17: Discount Factor | I17: =IF(I3="","",1/((1+$C5)^COUNTA($I3:I3))) -> 0.93828931 | J17: =IF(J3="","",1/((1+$C5)^COUNTA($I3:J3))) -> 0.88038682 | K17: =IF(K3="","",1/((1+$C5)^COUNTA($I3:K3))) -> 0.82605754 | L17: =IF(L3="","",1/((1+$C5)^COUNTA($I3:L3))) -> 0.77508096 | M17: =IF(M3="","",1/((1+$C5)^COUNTA($I3:M3))) -> 0.72725018 | N17: =IF(N3="","",1/((1+$C5)^COUNTA($I3:N3))) | O17: =IF(O3="","",1/((1+$C5)^COUNTA($I3:O3))) | P17: =IF(P3="","",1/((1+$C5)^COUNTA($I3:P3))) | ... R17: =IF(R3="","",1/((1+$C5)^COUNTA($I3:R3)))
B18: Value Per Share | C18: =+C15/C17 -> 92.240402 | E18: Value Per Share | F18: =+F15/F17 -> 204.53676 | H18: Discounted Free Cash Flow | I18: =IF(I3="","",I15*I17) -> 1862.0992 | J18: =IF(J3="","",J15*J17) -> 1562.78 | K18: =IF(K3="","",K15*K17) -> 1760.7213 | L18: =IF(L3="","",L15*L17) -> 2119.0429 | M18: =IF(M3="","",M15*M17) -> 1498.7552 | N18: =IF(N3="","",N15*N17) | O18: =IF(O3="","",O15*O17) | P18: =IF(P3="","",P15*P17) | ... R18: =IF(R3="","",R15*R17)
A21: Bear | B21: =_xlfn.TEXTBEFORE(B$2," - ")&" - "&$A21 -> Perpetuity Growth Method - Bear | E21: =_xlfn.TEXTBEFORE(E$2," - ")&" - "&$A21 -> EBITDA Multiple Method - Bear | H21: =Assumptions!$B$132 -> Year Ending 09/31/2024, In USD Millions | I21: {=_xlfn.SEQUENCE(1,Assumptions!$C$20,(YEAR(Assumptions!$C$19)))} -> 2024 | J21: 2025 | K21: 2026 | L21: 2027 | M21: 2028
B22: ="Free Cash Flow at Year "&COUNTA($I21:$R21) -> Free Cash Flow at Year 5 | C22: {=LOOKUP(2,1/(I33:R33<>""),I33:R33)} -> 2047.9268 | E22: ="Terminal EBITDA at Year "&COUNTA($I21:$R21) -> Terminal EBITDA at Year 5 | F22: {=LOOKUP(2,1/($I22:$R22<>""),$I22:$R22)} -> 4615.0343 | H22: EBITDA | I22: =IF(I21="","",'IS Bear'!H$53) -> 4804.3446 | J22: =IF(J21="","",'IS Bear'!I$53) -> 4756.3012 | K22: =IF(K21="","",'IS Bear'!J$53) -> 4708.7382 | L22: =IF(L21="","",'IS Bear'!K$53) -> 4661.6508 | M22: =IF(M21="","",'IS Bear'!L$53) -> 4615.0343 | N22: =IF(N21="","",'IS Bear'!M$53) | O22: =IF(O21="","",'IS Bear'!N$53) | P22: =IF(P21="","",'IS Bear'!O$53) | ... R22: =IF(R21="","",'IS Bear'!Q$53)
B23: Weighted Average Cost of Capital | C23: =Assumptions!$C$123 -> 0.065769366 | E23: Weighted Average Cost of Capital | F23: =Assumptions!$C$123 -> 0.065769366
B24: Perpetuity Growth Rate | C24: =Assumptions!$C$133 -> 0.01 | E24: Exit EV / EBITDA Multiple | F24: =Assumptions!$C$21 -> 15.97 | H24: NOPAT | I24: =IF(I21="","",'IS Bear'!H$59) -> 2826.7466 | J24: =IF(J21="","",'IS Bear'!I$59) -> 2795.7954 | K24: =IF(K21="","",'IS Bear'!J$59) -> 2768.7312 | L24: =IF(L21="","",'IS Bear'!K$59) -> 2744.2803 | M24: =IF(M21="","",'IS Bear'!L$59) -> 2718.9926 | N24: =IF(N21="","",'IS Bear'!M$59) | O24: =IF(O21="","",'IS Bear'!N$59) | P24: =IF(P21="","",'IS Bear'!O$59) | ... R24: =IF(R21="","",'IS Bear'!Q$59)
B25: =+"Perpetuity Value at Year "&COUNTA($I21:$R21)&" ~ Terminal Value" -> Perpetuity Value at Year 5 ~ Terminal Value | C25: =(C22*(1+C24))/(C23-C24) -> 37088.571 | E25: =+"Perpetuity Value at Year "&COUNTA($I21:$R21)&" ~ Terminal Value" -> Perpetuity Value at Year 5 ~ Terminal Value | F25: =+F22*F24 -> 73702.098
H26: Depreciation and Amortization | I26: =IF(I21="","",'IS Bear'!H$47) -> 1364.6436 | J26: =IF(J21="","",'IS Bear'!I$47) -> 1350.9971 | K26: =IF(K21="","",'IS Bear'!J$47) -> 1337.4872 | L26: =IF(L21="","",'IS Bear'!K$47) -> 1324.1123 | M26: =IF(M21="","",'IS Bear'!L$47) -> 1310.8712 | N26: =IF(N21="","",'IS Bear'!M$47) | O26: =IF(O21="","",'IS Bear'!N$47) | P26: =IF(P21="","",'IS Bear'!O$47) | ... R26: =IF(R21="","",'IS Bear'!Q$47)
B27: Discounted Terminal Value | C27: =C25/(1+C23)^COUNTA($I21:$R21) -> 26972.67 | E27: Discounted Terminal Value | F27: =F25/(1+F23)^COUNTA($I21:$R21) -> 53599.864
B28: Present Value of Free Cash Flows | C28: =SUM($I36:$R36) -> 8346.0329 | E28: Present Value of Free Cash Flows | F28: =SUM($I36:$R36) -> 8346.0329 | H28: Capital Expenditures | I28: =IF(I21="","",'IS Bear'!H$44) -> 1625.3612 | J28: =IF(J21="","",'IS Bear'!I$44) -> 1609.1076 | K28: =IF(K21="","",'IS Bear'!J$44) -> 1593.0165 | L28: =IF(L21="","",'IS Bear'!K$44) -> 1577.0863 | M28: =IF(M21="","",'IS Bear'!L$44) -> 1561.3155 | N28: =IF(N21="","",'IS Bear'!M$44) | O28: =IF(O21="","",'IS Bear'!N$44) | P28: =IF(P21="","",'IS Bear'!O$44) | ... R28: =IF(R21="","",'IS Bear'!Q$44)
B29: Enterprise Value | C29: =C27+C28 -> 35318.703 | E29: Enterprise Value | F29: =F27+F28 -> 61945.897
H30: Net Working Capital Change | I30: =IF(I21="","",'BS Bear'!H$47-'BS Bear'!G$47) -> 1727.6726 | J30: =IF(J21="","",'BS Bear'!I$47-'BS Bear'!H$47) -> 1335.0183 | K30: =IF(K21="","",'BS Bear'!J$47-'BS Bear'!I$47) -> 963.84522 | L30: =IF(L21="","",'BS Bear'!K$47-'BS Bear'!J$47) -> 346.86436 | M30: =IF(M21="","",'BS Bear'!L$47-'BS Bear'!K$47) -> 1005.792 | N30: =IF(N21="","",'BS Bear'!M$47-'BS Bear'!L$47) | O30: =IF(O21="","",'BS Bear'!N$47-'BS Bear'!M$47) | P30: =IF(P21="","",'BS Bear'!O$47-'BS Bear'!N$47) | ... R30: =IF(R21="","",'BS Bear'!Q$47-'BS Bear'!P$47)
B31: Net Debt | C31: =+'Balance Sheet'!$G$48 -> 9462 | E31: Net Debt | F31: =+'Balance Sheet'!$G$48 -> 9462
B32: Minority Interest | C32: =+'Balance Sheet'!$G$37 -> 122 | E32: Minority Interest | F32: =+'Balance Sheet'!$G$37 -> 122 | H32: Taxes | I32: =IF(I21="","",'IS Bear'!H$31) -> 612.95448 | J32: =IF(J21="","",'IS Bear'!I$31) -> 609.50862 | K32: =IF(K21="","",'IS Bear'!J$31) -> 602.51986 | L32: =IF(L21="","",'IS Bear'!K$31) -> 593.25824 | M32: =IF(M21="","",'IS Bear'!L$31) -> 585.17056 | N32: =IF(N21="","",'IS Bear'!M$31) | O32: =IF(O21="","",'IS Bear'!N$31) | P32: =IF(P21="","",'IS Bear'!O$31) | ... R32: =IF(R21="","",'IS Bear'!Q$31)
B33: Equity Value | C33: =+C29-C31-C32 -> 25734.703 | E33: Equity Value | F33: =+F29-F31-F32 -> 52361.897 | H33: Free Cash Flow | I33: =IF(I21="","",I24+I26-I28-I30+I32) -> 1451.3109 | J33: =IF(J21="","",J24+J26-J28-J30+J32) -> 1812.1753 | K33: =IF(K21="","",K24+K26-K28-K30+K32) -> 2151.8765 | L33: =IF(L21="","",L24+L26-L28-L30+L32) -> 2737.7001 | M33: =IF(M21="","",M24+M26-M28-M30+M32) -> 2047.9268 | N33: =IF(N21="","",N24+N26-N28-N30+N32) | O33: =IF(O21="","",O24+O26-O28-O30+O32) | P33: =IF(P21="","",P24+P26-P28-P30+P32) | ... R33: =IF(R21="","",R24+R26-R28-R30+R32)
B35: Shares Outstanding | C35: =+Assumptions!$C$36 -> 285.8 | E35: Shares Outstanding | F35: =+Assumptions!$C$36 -> 285.8 | H35: Discount Factor | I35: =IF(I21="","",1/((1+$C23)^COUNTA($I21:I21))) -> 0.93828931 | J35: =IF(J21="","",1/((1+$C23)^COUNTA($I21:J21))) -> 0.88038682 | K35: =IF(K21="","",1/((1+$C23)^COUNTA($I21:K21))) -> 0.82605754 | L35: =IF(L21="","",1/((1+$C23)^COUNTA($I21:L21))) -> 0.77508096 | M35: =IF(M21="","",1/((1+$C23)^COUNTA($I21:M21))) -> 0.72725018 | N35: =IF(N21="","",1/((1+$C23)^COUNTA($I21:N21))) | O35: =IF(O21="","",1/((1+$C23)^COUNTA($I21:O21))) | P35: =IF(P21="","",1/((1+$C23)^COUNTA($I21:P21))) | ... R35: =IF(R21="","",1/((1+$C23)^COUNTA($I21:R21)))
B36: Value Per Share | C36: =+C33/C35 -> 90.044447 | E36: Value Per Share | F36: =+F33/F35 -> 183.21167 | H36: Discounted Free Cash Flow | I36: =IF(I21="","",I33*I35) -> 1361.7495 | J36: =IF(J21="","",J33*J35) -> 1595.4153 | K36: =IF(K21="","",K33*K35) -> 1777.5738 | L36: =IF(L21="","",L33*L35) -> 2121.9392 | M36: =IF(M21="","",M33*M35) -> 1489.3552 | N36: =IF(N21="","",N33*N35) | O36: =IF(O21="","",O33*O35) | P36: =IF(P21="","",P33*P35) | ... R36: =IF(R21="","",R33*R35)
A39: Bull | B39: =_xlfn.TEXTBEFORE(B$2," - ")&" - "&$A39 -> Perpetuity Growth Method - Bull | E39: =_xlfn.TEXTBEFORE(E$2," - ")&" - "&$A39 -> EBITDA Multiple Method - Bull | H39: =Assumptions!$B$132 -> Year Ending 09/31/2024, In USD Millions | I39: {=_xlfn.SEQUENCE(1,Assumptions!$C$20,(YEAR(Assumptions!$C$19)))} -> 2024 | J39: 2025 | K39: 2026 | L39: 2027 | M39: 2028
B40: ="Free Cash Flow at Year "&COUNTA($I39:$R39) -> Free Cash Flow at Year 5 | C40: {=LOOKUP(2,1/(I51:R51<>""),I51:R51)} -> 2068.8657 | E40: ="Terminal EBITDA at Year "&COUNTA($I39:$R39) -> Terminal EBITDA at Year 5 | F40: {=LOOKUP(2,1/($I40:$R40<>""),$I40:$R40)} -> 5625.8103 | H40: EBITDA | I40: =IF(I39="","",'IS Bull'!H$53) -> 4998.4596 | J40: =IF(J39="","",'IS Bull'!I$53) -> 5148.4134 | K40: =IF(K39="","",'IS Bull'!J$53) -> 5302.8658 | L40: =IF(L39="","",'IS Bull'!K$53) -> 5461.9517 | M40: =IF(M39="","",'IS Bull'!L$53) -> 5625.8103 | N40: =IF(N39="","",'IS Bull'!M$53) | O40: =IF(O39="","",'IS Bull'!N$53) | P40: =IF(P39="","",'IS Bull'!O$53) | ... R40: =IF(R39="","",'IS Bull'!Q$53)
B41: Weighted Average Cost of Capital | C41: =Assumptions!$C$123 -> 0.065769366 | E41: Weighted Average Cost of Capital | F41: =Assumptions!$C$123 -> 0.065769366
B42: Perpetuity Growth Rate | C42: =Assumptions!$C$133 -> 0.01 | E42: Exit EV / EBITDA Multiple | F42: =Assumptions!$C$21 -> 15.97 | H42: NOPAT | I42: =IF(I39="","",'IS Bull'!H$59) -> 2937.9004 | J42: =IF(J39="","",'IS Bull'!I$59) -> 3020.3262 | K42: =IF(K39="","",'IS Bull'!J$59) -> 3108.9398 | L42: =IF(L39="","",'IS Bull'!K$59) -> 3202.5476 | M42: =IF(M39="","",'IS Bull'!L$59) -> 3297.7819 | N42: =IF(N39="","",'IS Bull'!M$59) | O42: =IF(O39="","",'IS Bull'!N$59) | P42: =IF(P39="","",'IS Bull'!O$59) | ... R42: =IF(R39="","",'IS Bull'!Q$59)
B43: =+"Perpetuity Value at Year "&COUNTA($I39:$R39)&" ~ Terminal Value" -> Perpetuity Value at Year 5 ~ Terminal Value | C43: =(C40*(1+C42))/(C41-C42) -> 37467.781 | E43: =+"Perpetuity Value at Year "&COUNTA($I39:$R39)&" ~ Terminal Value" -> Perpetuity Value at Year 5 ~ Terminal Value | F43: =+F40*F42 -> 89844.19
H44: Depreciation and Amortization | I44: =IF(I39="","",'IS Bull'!H$47) -> 1419.7807 | J44: =IF(J39="","",'IS Bull'!I$47) -> 1462.3741 | K44: =IF(K39="","",'IS Bull'!J$47) -> 1506.2453 | L44: =IF(L39="","",'IS Bull'!K$47) -> 1551.4327 | M44: =IF(M39="","",'IS Bull'!L$47) -> 1597.9757 | N44: =IF(N39="","",'IS Bull'!M$47) | O44: =IF(O39="","",'IS Bull'!N$47) | P44: =IF(P39="","",'IS Bull'!O$47) | ... R44: =IF(R39="","",'IS Bull'!Q$47)
B45: Discounted Terminal Value | C45: =C43/(1+C41)^COUNTA($I39:$R39) -> 27248.45 | E45: Discounted Terminal Value | F45: =F43/(1+F41)^COUNTA($I39:$R39) -> 65339.203
B46: Present Value of Free Cash Flows | C46: =SUM($I54:$R54) -> 8147.11 | E46: Present Value of Free Cash Flows | F46: =SUM($I54:$R54) -> 8147.11 | H46: Capital Expenditures | I46: =IF(I39="","",'IS Bull'!H$44) -> 1691.0323 | J46: =IF(J39="","",'IS Bull'!I$44) -> 1741.7633 | K46: =IF(K39="","",'IS Bull'!J$44) -> 1794.0162 | L46: =IF(L39="","",'IS Bull'!K$44) -> 1847.8367 | M46: =IF(M39="","",'IS Bull'!L$44) -> 1903.2718 | N46: =IF(N39="","",'IS Bull'!M$44) | O46: =IF(O39="","",'IS Bull'!N$44) | P46: =IF(P39="","",'IS Bull'!O$44) | ... R46: =IF(R39="","",'IS Bull'!Q$44)
B47: Enterprise Value | C47: =C45+C46 -> 35395.56 | E47: Enterprise Value | F47: =F45+F46 -> 73486.313
H48: Net Working Capital Change | I48: =IF(I39="","",'BS Bull'!H$47-'BS Bull'!G$47) -> 1963.6016 | J48: =IF(J39="","",'BS Bull'!I$47-'BS Bull'!H$47) -> 1670.7628 | K48: =IF(K39="","",'BS Bull'!J$47-'BS Bull'!I$47) -> 1401.4723 | L48: =IF(L39="","",'BS Bull'!K$47-'BS Bull'!J$47) -> 888.51246 | M48: =IF(M39="","",'BS Bull'!L$47-'BS Bull'!K$47) -> 1653.6728 | N48: =IF(N39="","",'BS Bull'!M$47-'BS Bull'!L$47) | O48: =IF(O39="","",'BS Bull'!N$47-'BS Bull'!M$47) | P48: =IF(P39="","",'BS Bull'!O$47-'BS Bull'!N$47) | ... R48: =IF(R39="","",'BS Bull'!Q$47-'BS Bull'!P$47)
B49: Net Debt | C49: =+'Balance Sheet'!$G$48 -> 9462 | E49: Net Debt | F49: =+'Balance Sheet'!$G$48 -> 9462
B50: Minority Interest | C50: =+'Balance Sheet'!$G$37 -> 122 | E50: Minority Interest | F50: =+'Balance Sheet'!$G$37 -> 122 | H50: Taxes | I50: =IF(I39="","",'IS Bull'!H$31) -> 640.77845 | J50: =IF(J39="","",'IS Bull'!I$31) -> 665.71304 | K50: =IF(K39="","",'IS Bull'!J$31) -> 687.68068 | L50: =IF(L39="","",'IS Bull'!K$31) -> 707.97146 | M50: =IF(M39="","",'IS Bull'!L$31) -> 730.05276 | N50: =IF(N39="","",'IS Bull'!M$31) | O50: =IF(O39="","",'IS Bull'!N$31) | P50: =IF(P39="","",'IS Bull'!O$31) | ... R50: =IF(R39="","",'IS Bull'!Q$31)
B51: Equity Value | C51: =+C47-C49-C50 -> 25811.56 | E51: Equity Value | F51: =+F47-F49-F50 -> 63902.313 | H51: Free Cash Flow | I51: =IF(I39="","",I42+I44-I46-I48+I50) -> 1343.8257 | J51: =IF(J39="","",J42+J44-J46-J48+J50) -> 1735.8872 | K51: =IF(K39="","",K42+K44-K46-K48+K50) -> 2107.3772 | L51: =IF(L39="","",L42+L44-L46-L48+L50) -> 2725.6026 | M51: =IF(M39="","",M42+M44-M46-M48+M50) -> 2068.8657 | N51: =IF(N39="","",N42+N44-N46-N48+N50) | O51: =IF(O39="","",O42+O44-O46-O48+O50) | P51: =IF(P39="","",P42+P44-P46-P48+P50) | ... R51: =IF(R39="","",R42+R44-R46-R48+R50)
B53: Shares Outstanding | C53: =+Assumptions!$C$36 -> 285.8 | E53: Shares Outstanding | F53: =+Assumptions!$C$36 -> 285.8 | H53: Discount Factor | I53: =IF(I39="","",1/((1+$C41)^COUNTA($I39:I39))) -> 0.93828931 | J53: =IF(J39="","",1/((1+$C41)^COUNTA($I39:J39))) -> 0.88038682 | K53: =IF(K39="","",1/((1+$C41)^COUNTA($I39:K39))) -> 0.82605754 | L53: =IF(L39="","",1/((1+$C41)^COUNTA($I39:L39))) -> 0.77508096 | M53: =IF(M39="","",1/((1+$C41)^COUNTA($I39:M39))) -> 0.72725018 | N53: =IF(N39="","",1/((1+$C41)^COUNTA($I39:N39))) | O53: =IF(O39="","",1/((1+$C41)^COUNTA($I39:O39))) | P53: =IF(P39="","",1/((1+$C41)^COUNTA($I39:P39))) | ... R53: =IF(R39="","",1/((1+$C41)^COUNTA($I39:R39)))
B54: Value Per Share | C54: =+C51/C53 -> 90.313367 | E54: Value Per Share | F54: =+F51/F53 -> 223.59102 | H54: Discounted Free Cash Flow | I54: =IF(I39="","",I51*I53) -> 1260.8972 | J54: =IF(J39="","",J51*J53) -> 1528.2522 | K54: =IF(K39="","",K51*K53) -> 1740.8149 | L54: =IF(L39="","",L51*L53) -> 2112.5627 | M54: =IF(M39="","",M51*M53) -> 1504.583 | N54: =IF(N39="","",N51*N53) | O54: =IF(O39="","",O51*O53) | P54: =IF(P39="","",P51*P53) | ... R54: =IF(R39="","",R51*R53)
B57: Perpetuity Growth Method DCF Summary | E57: EBITDA Multiple Method DCF Summary
B58: Scenarios | E58: Scenarios
A59: Base | B59: =B3 -> Perpetuity Growth Method - Base | C59: =C18 -> 92.240402 | E59: =E3 -> EBITDA Multiple Method - Base | F59: =F18 -> 204.53676
A60: Bear | B60: =B21 -> Perpetuity Growth Method - Bear | C60: =C36 -> 90.044447 | E60: =E21 -> EBITDA Multiple Method - Bear | F60: =F36 -> 183.21167
A61: Bull | B61: =B39 -> Perpetuity Growth Method - Bull | C61: =C54 -> 90.313367 | E61: =E39 -> EBITDA Multiple Method - Bull | F61: =F54 -> 223.59102

Sheet Comparable Peer
B2: Comparable Peer Companies
B3: Market and Financial Data - In Millions USD
B4: Company Name | C4: Enterprise Value | D4: LTM Sales | E4: LTM EBITDA | F4: Earnings | G4: EV / Sales | H4: EV / EBITDA | I4: P / E
B5: Target Company
B6: =Assumptions!$C$30 -> Tyson Foods | C6: =Assumptions!D64 -> 30327.5 | D6: =Assumptions!E64 -> 53092 | E6: =Assumptions!F64 -> 2948 | F6: =+'Income Statement'!$G$37 -> -648 | G6: =IFERROR(C6/D6,0) -> 0.57122542 | H6: =IFERROR(C6/E6,0) -> 10.287483 | I6: =Assumptions!C64 -> 24.6
B7: Comparable Peer Companies
B8: =Assumptions!B66 -> Pilgrim's Pride | C8: =Assumptions!D66 -> 13208.2 | D8: =Assumptions!E66 -> 17809.7 | E8: =Assumptions!F66 -> 1678.3 | G8: =IFERROR(C8/D8,0) -> 0.74162956 | H8: =IFERROR(C8/E8,0) -> 7.8699875 | I8: =Assumptions!C66 -> 12.1
B9: =Assumptions!B67 -> Hormel Foods Corp | C9: =Assumptions!D67 -> 19340.2 | D9: =Assumptions!E67 -> 11980.8 | E9: =Assumptions!F67 -> 1307.8 | G9: =IFERROR(C9/D9,0) -> 1.6142662 | H9: =IFERROR(C9/E9,0) -> 14.788347 | I9: =Assumptions!C67 -> 18.4
B10: =Assumptions!B68 -> Maple Leaf | C10: =Assumptions!D68 -> 4577 | D10: =Assumptions!E68 -> 4851.9 | E10: =Assumptions!F68 -> 499.7 | G10: =IFERROR(C10/D10,0) -> 0.94334178 | H10: =IFERROR(C10/E10,0) -> 9.1594957 | I10: =Assumptions!C68 -> 16.5
B11: =Assumptions!B69 -> 0 | C11: =Assumptions!D69 -> 0 | D11: =Assumptions!E69 -> 0 | E11: =Assumptions!F69 -> 0 | G11: =IFERROR(C11/D11,0) -> 0 | H11: =IFERROR(C11/E11,0) -> 0 | I11: =Assumptions!C69 -> 0
B12: =Assumptions!B70 -> 0 | C12: =Assumptions!D70 -> 0 | D12: =Assumptions!E70 -> 0 | E12: =Assumptions!F70 -> 0 | G12: =IFERROR(C12/D12,0) -> 0 | H12: =IFERROR(C12/E12,0) -> 0 | I12: =Assumptions!C70 -> 0
B15: SUMMARY
B16: Metrics | C16: Comps | D16: Implied EV | E16: Net Debt | F16: Equity Value | G16: Shares | H16: Share Price
B17: EV / Sales
B18: Mean | C18: =AVERAGE(G$8:G$12) -> 0.6598475 | D18: =+$D$6*C18 -> 35032.624 | E18: ='Balance Sheet'!$G$48 -> 9462 | F18: =+D18-E18 -> 25570.624 | G18: =Assumptions!$C$36 -> 285.8 | H18: =+F18/G18 -> 89.470341
B19: 25 Percentile | C19: =PERCENTILE(G$8:G$12,0.25) -> 0 | D19: =+$D$6*C19 -> 0 | E19: ='Balance Sheet'!$G$48 -> 9462 | F19: =+D19-E19 -> -9462 | G19: =Assumptions!$C$36 -> 285.8 | H19: =+F19/G19 -> -33.107068
B20: 75 Percentile | C20: =PERCENTILE(G$8:G$12,0.75) -> 0.94334178 | D20: =+$D$6*C20 -> 50083.902 | E20: ='Balance Sheet'!$G$48 -> 9462 | F20: =+D20-E20 -> 40621.902 | G20: =Assumptions!$C$36 -> 285.8 | H20: =+F20/G20 -> 142.13402
B21: EV / EBITDA
B22: Mean | C22: =AVERAGE(H$8:H$12) -> 6.363566 | D22: =+$E$6*C22 -> 18759.793 | E22: ='Balance Sheet'!$G$48 -> 9462 | F22: =+D22-E22 -> 9297.7926 | G22: =Assumptions!$C$36 -> 285.8 | H22: =+F22/G22 -> 32.532514
B23: 25 Percentile | C23: =PERCENTILE(H$8:H$12,0.25) -> 0 | D23: =+$E$6*C23 -> 0 | E23: ='Balance Sheet'!$G$48 -> 9462 | F23: =+D23-E23 -> -9462 | G23: =Assumptions!$C$36 -> 285.8 | H23: =+F23/G23 -> -33.107068
B24: 75 Percentile | C24: =PERCENTILE(H$8:H$12,0.75) -> 9.1594957 | D24: =+$E$6*C24 -> 27002.193 | E24: ='Balance Sheet'!$G$48 -> 9462 | F24: =+D24-E24 -> 17540.193 | G24: =Assumptions!$C$36 -> 285.8 | H24: =+F24/G24 -> 61.372265
B25: P / E
B26: Mean | C26: =AVERAGE(I$8:I$12) -> 9.4 | D26: =+$F$6*C26 -> -6091.2 | E26: ='Balance Sheet'!$G$48 -> 9462 | F26: =+D26-E26 -> -15553.2 | G26: =Assumptions!$C$36 -> 285.8 | H26: =+F26/G26 -> -54.419874
B27: 25 Percentile | C27: =PERCENTILE(I$8:I$12,0.25) -> 0 | D27: =+$F$6*C27 -> 0 | E27: ='Balance Sheet'!$G$48 -> 9462 | F27: =+D27-E27 -> -9462 | G27: =Assumptions!$C$36 -> 285.8 | H27: =+F27/G27 -> -33.107068
B28: 75 Percentile | C28: =PERCENTILE(I$8:I$12,0.75) -> 16.5 | D28: =+$F$6*C28 -> -10692 | E28: ='Balance Sheet'!$G$48 -> 9462 | F28: =+D28-E28 -> -20154 | G28: =Assumptions!$C$36 -> 285.8 | H28: =+F28/G28 -> -70.517845
B31: Value Per Share
A32: Base | B32: Mean | C32: =+AVERAGE(H18,H22,H26) -> 22.52766
A33: Bear | B33: 25 Percentile | C33: =+AVERAGE(H19,H23,H27) -> -33.107068
A34: Bull | B34: 75 Percentile | C34: =+AVERAGE(H20,H24,H28) -> 44.329479

Sheet Internal Rate of Return
B2: Internal Rate of Return | E2: Discounted Free Cash Flow to Equity
A3: Base | B3: ="IRR - "&A3 -> IRR - Base | E3: =Assumptions!$B$132 -> Year Ending 09/31/2024, In USD Millions | F3: {=_xlfn.SEQUENCE(1,Assumptions!$C$20,(YEAR(Assumptions!$C$19)))} -> 2024 | G3: 2025 | H3: 2026 | I3: 2027 | J3: 2028
B4: ="Free Cash Flow to Equity at Year "&COUNTA(F3:O3) -> Free Cash Flow to Equity at Year 5 | C4: {=LOOKUP(2,1/($F4:$O4<>""),$F4:$O4)} -> 2060.8523 | E4: Free Cash Flow | F4: =IF(F3="","",'Discounted Cash Flow'!I15) -> 1984.5683 | G4: =IF(G3="","",'Discounted Cash Flow'!J15) -> 1775.1061 | H4: =IF(H3="","",'Discounted Cash Flow'!K15) -> 2131.4753 | I4: =IF(I3="","",'Discounted Cash Flow'!L15) -> 2733.9633 | J4: =IF(J3="","",'Discounted Cash Flow'!M15) -> 2060.8523 | K4: =IF(K3="","",'Discounted Cash Flow'!N15) | L4: =IF(L3="","",'Discounted Cash Flow'!O15) | M4: =IF(M3="","",'Discounted Cash Flow'!P15) | ... O4: =IF(O3="","",'Discounted Cash Flow'!R15)
B5: Cost of Equity | C5: =Assumptions!$C$121 -> 0.068229
B6: Perpetuity Growth Rate | C6: =Assumptions!$C$133 -> 0.01 | E6: Non-Operating (Income) Loss | F6: =IF(F3="","",'Income Statement'!H$25) -> 524.11159 | G6: =IF(G3="","",'Income Statement'!I$25) -> 509.36479 | H6: =IF(H3="","",'Income Statement'!J$25) -> 511.83324 | I6: =IF(I3="","",'Income Statement'!K$25) -> 525.46603 | J6: =IF(J3="","",'Income Statement'!L$25) -> 533.84674 | K6: =IF(K3="","",'Income Statement'!M$25) | L6: =IF(L3="","",'Income Statement'!N$25) | M6: =IF(M3="","",'Income Statement'!O$25) | ... O6: =IF(O3="","",'Income Statement'!Q$25)
B7: ="Terminal value at Year "&COUNTA(F3:O3) -> Terminal value at Year 5 | C7: =(C4*(1+C5))/(C5-C6) -> 37806.973
E8: Free Cash Flow to Equity | F8: =IF(F3="","",F4-F6) -> 1460.4567 | G8: =IF(G3="","",G4-G6) -> 1265.7413 | H8: =IF(H3="","",H4-H6) -> 1619.6421 | I8: =IF(I3="","",I4-I6) -> 2208.4973 | J8: =IF(J3="","",J4-J6) -> 1527.0056 | K8: =IF(K3="","",K4-K6) | L8: =IF(L3="","",L4-L6) | M8: =IF(M3="","",M4-M6) | ... O8: =IF(O3="","",O4-O6)
B9: Discounted Terminal Value | C9: =C7/(1+C5)^COUNTA($F3:$O3) -> 27180.04
B10: PV of Free Cash Flow to Equity | C10: =SUM(F12:O12) -> 6598.9308 | E10: Discount Factor | F10: =IF(F3="","",1/((1+$C5)^COUNTA($F3:F3))) -> 0.93612886 | G10: =IF(G3="","",1/((1+$C5)^COUNTA($F3:G3))) -> 0.87633725 | H10: =IF(H3="","",1/((1+$C5)^COUNTA($F3:H3))) -> 0.82036459 | I10: =IF(I3="","",1/((1+$C5)^COUNTA($F3:I3))) -> 0.76796697 | J10: =IF(J3="","",1/((1+$C5)^COUNTA($F3:J3))) -> 0.71891605 | K10: =IF(K3="","",1/((1+$C5)^COUNTA($F3:K3))) | L10: =IF(L3="","",1/((1+$C5)^COUNTA($F3:L3))) | M10: =IF(M3="","",1/((1+$C5)^COUNTA($F3:M3))) | ... O10: =IF(O3="","",1/((1+$C5)^COUNTA($F3:O3)))
B11: Equity Value | C11: =C9+C10 -> 33778.971
E12: Discounted Free Cash Flow to Equity | F12: =IF(F3="","",F8*F10) -> 1367.1756 | G12: =IF(G3="","",G8*G10) -> 1109.2163 | H12: =IF(H3="","",H8*H10) -> 1328.697 | I12: =IF(I3="","",I8*I10) -> 1696.053 | J12: =IF(J3="","",J8*J10) -> 1097.7888 | K12: =IF(K3="","",K8*K10) | L12: =IF(L3="","",L8*L10) | M12: =IF(M3="","",M8*M10) | ... O12: =IF(O3="","",O8*O10)
B13: Net Debt | C13: =+'Balance Sheet'!$G$48 -> 9462
B14: Minority Interest | C14: =+'Balance Sheet'!$G$37 -> 122
B15: Enterprise Value | C15: =C11-C13-C14 -> 24194.971
B17: Shares Outstanding | C17: =+Assumptions!$C$36 -> 285.8
B18: Value Per Share | C18: =C15/C17 -> 84.657
A21: Bear | B21: ="IRR - "&A21 -> IRR - Bear | E21: =Assumptions!$B$132 -> Year Ending 09/31/2024, In USD Millions | F21: {=_xlfn.SEQUENCE(1,Assumptions!$C$20,(YEAR(Assumptions!$C$19)))} -> 2024 | G21: 2025 | H21: 2026 | I21: 2027 | J21: 2028
B22: ="Free Cash Flow to Equity at Year "&COUNTA(F21:O21) -> Free Cash Flow to Equity at Year 5 | C22: {=LOOKUP(2,1/($F22:$O22<>""),$F22:$O22)} -> 2047.9268 | E22: Free Cash Flow | F22: =IF(F21="","",'Discounted Cash Flow'!I33) -> 1451.3109 | G22: =IF(G21="","",'Discounted Cash Flow'!J33) -> 1812.1753 | H22: =IF(H21="","",'Discounted Cash Flow'!K33) -> 2151.8765 | I22: =IF(I21="","",'Discounted Cash Flow'!L33) -> 2737.7001 | J22: =IF(J21="","",'Discounted Cash Flow'!M33) -> 2047.9268 | K22: =IF(K21="","",'Discounted Cash Flow'!N33) | L22: =IF(L21="","",'Discounted Cash Flow'!O33) | M22: =IF(M21="","",'Discounted Cash Flow'!P33) | ... O22: =IF(O21="","",'Discounted Cash Flow'!R33)
B23: Cost of Equity | C23: =Assumptions!$C$121 -> 0.068229
B24: Perpetuity Growth Rate | C24: =Assumptions!$C$133 -> 0.01 | E24: Non-Operating (Income) Loss | F24: =IF(F21="","",'IS Bear'!H$25) -> 520.87022 | G24: =IF(G21="","",'IS Bear'!I$25) -> 502.88206 | H24: =IF(H21="","",'IS Bear'!J$25) -> 502.10882 | I24: =IF(I21="","",'IS Bear'!K$25) -> 512.49927 | J24: =IF(J21="","",'IS Bear'!L$25) -> 517.63667 | K24: =IF(K21="","",'Income Statement'!M$25) | L24: =IF(L21="","",'Income Statement'!N$25) | M24: =IF(M21="","",'Income Statement'!O$25) | N24: =IF(N21="","",'Income Statement'!P$25) | O24: =IF(O21="","",'Income Statement'!Q$25)
B25: ="Terminal value at Year "&COUNTA(F21:O21) -> Terminal value at Year 5 | C25: =(C22*(1+C23))/(C23-C24) -> 37569.851
E26: Free Cash Flow to Equity | F26: =IF(F21="","",F22-F24) -> 930.44065 | G26: =IF(G21="","",G22-G24) -> 1309.2932 | H26: =IF(H21="","",H22-H24) -> 1649.7677 | I26: =IF(I21="","",I22-I24) -> 2225.2009 | J26: =IF(J21="","",J22-J24) -> 1530.2902 | K26: =IF(K21="","",K22-K24) | L26: =IF(L21="","",L22-L24) | M26: =IF(M21="","",M22-M24) | ... O26: =IF(O21="","",O22-O24)
B27: Discounted Terminal Value | C27: =C25/(1+C23)^COUNTA($F21:$O21) -> 27009.569
B28: PV of Free Cash Flow to Equity | C28: =SUM(F30:O30) -> 6180.8367 | E28: Discount Factor | F28: =IF(F21="","",1/((1+$C23)^COUNTA($F21:F21))) -> 0.93612886 | G28: =IF(G21="","",1/((1+$C23)^COUNTA($F21:G21))) -> 0.87633725 | H28: =IF(H21="","",1/((1+$C23)^COUNTA($F21:H21))) -> 0.82036459 | I28: =IF(I21="","",1/((1+$C23)^COUNTA($F21:I21))) -> 0.76796697 | J28: =IF(J21="","",1/((1+$C23)^COUNTA($F21:J21))) -> 0.71891605 | K28: =IF(K21="","",1/((1+$C23)^COUNTA($F21:K21))) | L28: =IF(L21="","",1/((1+$C23)^COUNTA($F21:L21))) | M28: =IF(M21="","",1/((1+$C23)^COUNTA($F21:M21))) | ... O28: =IF(O21="","",1/((1+$C23)^COUNTA($F21:O21)))
B29: Equity Value | C29: =C27+C28 -> 33190.406
E30: Discounted Free Cash Flow to Equity | F30: =IF(F21="","",F26*F28) -> 871.01235 | G30: =IF(G21="","",G26*G28) -> 1147.3824 | H30: =IF(H21="","",H26*H28) -> 1353.411 | I30: =IF(I21="","",I26*I28) -> 1708.8808 | J30: =IF(J21="","",J26*J28) -> 1100.1502 | K30: =IF(K21="","",K26*K28) | L30: =IF(L21="","",L26*L28) | M30: =IF(M21="","",M26*M28) | ... O30: =IF(O21="","",O26*O28)
B31: Net Debt | C31: =+'Balance Sheet'!$G$48 -> 9462
B32: Minority Interest | C32: =+'Balance Sheet'!$G$37 -> 122
B33: Enterprise Value | C33: =C29-C31-C32 -> 23606.406
B35: Shares Outstanding | C35: =+Assumptions!$C$36 -> 285.8
B36: Value Per Share | C36: =C33/C35 -> 82.59764
A39: Bull | B39: ="IRR - "&A39 -> IRR - Bull | E39: =Assumptions!$B$132 -> Year Ending 09/31/2024, In USD Millions | F39: {=_xlfn.SEQUENCE(1,Assumptions!$C$20,(YEAR(Assumptions!$C$19)))} -> 2024 | G39: 2025 | H39: 2026 | I39: 2027 | J39: 2028
B40: ="Free Cash Flow to Equity at Year "&COUNTA(F39:O39) -> Free Cash Flow to Equity at Year 5 | C40: {=LOOKUP(2,1/($F40:$O40<>""),$F40:$O40)} -> 2068.8657 | E40: Free Cash Flow | F40: =IF(F39="","",'Discounted Cash Flow'!I51) -> 1343.8257 | G40: =IF(G39="","",'Discounted Cash Flow'!J51) -> 1735.8872 | H40: =IF(H39="","",'Discounted Cash Flow'!K51) -> 2107.3772 | I40: =IF(I39="","",'Discounted Cash Flow'!L51) -> 2725.6026 | J40: =IF(J39="","",'Discounted Cash Flow'!M51) -> 2068.8657 | K40: =IF(K39="","",'Discounted Cash Flow'!N51) | L40: =IF(L39="","",'Discounted Cash Flow'!O51) | M40: =IF(M39="","",'Discounted Cash Flow'!P51) | ... O40: =IF(O39="","",'Discounted Cash Flow'!R51)
B41: Cost of Equity | C41: =Assumptions!$C$121 -> 0.068229
B42: Perpetuity Growth Rate | C42: =Assumptions!$C$133 -> 0.01 | E42: Non-Operating (Income) Loss | F42: =IF(F39="","",'IS Bull'!H$25) -> 527.35296 | G42: =IF(G39="","",'IS Bull'!I$25) -> 515.97718 | H42: =IF(H39="","",'IS Bull'!J$25) -> 521.95052 | I42: =IF(I39="","",'IS Bull'!K$25) -> 539.22641 | J42: =IF(J39="","",'IS Bull'!L$25) -> 551.39291 | K42: =IF(K39="","",'IS Bull'!M$25) | L42: =IF(L39="","",'IS Bull'!N$25) | M42: =IF(M39="","",'IS Bull'!O$25) | ... O42: =IF(O39="","",'IS Bull'!Q$25)
B43: ="Terminal value at Year "&COUNTA(F39:O39) -> Terminal value at Year 5 | C43: =(C40*(1+C41))/(C41-C42) -> 37953.981
E44: Free Cash Flow to Equity | F44: =IF(F39="","",F40-F42) -> 816.4727 | G44: =IF(G39="","",G40-G42) -> 1219.91 | H44: =IF(H39="","",H40-H42) -> 1585.4267 | I44: =IF(I39="","",I40-I42) -> 2186.3762 | J44: =IF(J39="","",J40-J42) -> 1517.4728 | K44: =IF(K39="","",K40-K42) | L44: =IF(L39="","",L40-L42) | M44: =IF(M39="","",M40-M42) | ... O44: =IF(O39="","",O40-O42)
B45: Discounted Terminal Value | C45: =C43/(1+C41)^COUNTA($F39:$O39) -> 27285.726
B46: PV of Free Cash Flow to Equity | C46: =SUM(F48:O48) -> 5904.0045 | E46: Discount Factor | F46: =IF(F39="","",1/((1+$C41)^COUNTA($F39:F39))) -> 0.93612886 | G46: =IF(G39="","",1/((1+$C41)^COUNTA($F39:G39))) -> 0.87633725 | H46: =IF(H39="","",1/((1+$C41)^COUNTA($F39:H39))) -> 0.82036459 | I46: =IF(I39="","",1/((1+$C41)^COUNTA($F39:I39))) -> 0.76796697 | J46: =IF(J39="","",1/((1+$C41)^COUNTA($F39:J39))) -> 0.71891605 | K46: =IF(K39="","",1/((1+$C41)^COUNTA($F39:K39))) | L46: =IF(L39="","",1/((1+$C41)^COUNTA($F39:L39))) | M46: =IF(M39="","",1/((1+$C41)^COUNTA($F39:M39))) | ... O46: =IF(O39="","",1/((1+$C41)^COUNTA($F39:O39)))
B47: Equity Value | C47: =C45+C46 -> 33189.731
E48: Discounted Free Cash Flow to Equity | F48: =IF(F39="","",F44*F46) -> 764.32366 | G48: =IF(G39="","",G44*G46) -> 1069.0526 | H48: =IF(H39="","",H44*H46) -> 1300.6279 | I48: =IF(I39="","",I44*I46) -> 1679.0647 | J48: =IF(J39="","",J44*J46) -> 1090.9356 | K48: =IF(K39="","",K44*K46) | L48: =IF(L39="","",L44*L46) | M48: =IF(M39="","",M44*M46) | ... O48: =IF(O39="","",O44*O46)
B49: Net Debt | C49: =+'Balance Sheet'!$G$48 -> 9462
B50: Minority Interest | C50: =+'Balance Sheet'!$G$37 -> 122
B51: Enterprise Value | C51: =C47-C49-C50 -> 23605.731
B53: Shares Outstanding | C53: =+Assumptions!$C$36 -> 285.8
B54: Value Per Share | C54: =C51/C53 -> 82.595279
B57: Internal Rate of Return Summary
B58: Scenarios
A59: Base | B59: =B3 -> IRR - Base | C59: =C18 -> 84.657
A60: Bear | B60: =B21 -> IRR - Bear | C60: =C36 -> 82.59764
A61: Bull | B61: =B39 -> IRR - Bull | C61: =C54 -> 82.595279

Sheet Dividend Discount
B2: Dividend Discount Model - 2 Stage
A3: Base | B3: ="DDM - "&A3&" - "&Assumptions!$C$54 -> DDM - Base - CAGR | C3: {=_xlfn.SEQUENCE(1,6,(YEAR(Assumptions!$C$19)-1))} -> 2023 | D3: 2024 | E3: 2025 | F3: 2026 | G3: 2027 | H3: 2028
C4: 0 | D4: 1 | E4: 2 | F4: 3 | G4: 4 | H4: 5
B5: Annual Dividends Per Share | C5: =Assumptions!$C$56 -> 1.93 | D5: =C5*(1+$C9) -> 2.017823 | E5: =D5*(1+$C9) -> 2.1096424 | F5: =E5*(1+$C9) -> 2.2056399 | G5: =F5*(1+$C9) -> 2.3060057 | H5: =G5*(1+$C9) -> 2.4109385
B6: Cost of Equity | C6: =Assumptions!$C$57 -> 0.068229
B7: Present Value of Dividend | C7: =C5/(1+$C6)^C4 -> 1.93 | D7: =D5/(1+$C6)^D4 -> 1.8889424 | E7: =E5/(1+$C6)^E4 -> 1.8487582 | F7: =F5/(1+$C6)^F4 -> 1.8094289 | G7: =G5/(1+$C6)^G4 -> 1.7709362 | H7: =H5/(1+$C6)^H4 -> 1.7332624
B9: Dividend Growth Rate Stage 1 | C9: =IF(Assumptions!$C$54="CAGR",Assumptions!$C$46,Assumptions!$C$50) -> 0.04550416
B10: Dividend Growth Rate Stage 2 | C10: =Assumptions!$C$133 -> 0.01
B12: Sum of Stage 1 Dividends | C12: =SUM(D7:H7) -> 9.051328
B13: Year 5 Dividend * (1 + Stage 2 Growth Rate) | C13: =H5*(1+$C10) -> 2.4350479
B14: Stage 2 Terminal Value | C14: =C13/(C6-C10) -> 41.818474
B15: PV of Stage 2 Terminal Value | C15: =C14/(1+C6)^H4 -> 30.063972
B16: Value Per Share | C16: =SUM(C12,C15) -> 39.1153
A19: Bear | B19: ="DDM - "&A19&" - "&Assumptions!$C$54 -> DDM - Bear - CAGR | C19: {=_xlfn.SEQUENCE(1,6,(YEAR(Assumptions!$C$19)-1))} -> 2023 | D19: 2024 | E19: 2025 | F19: 2026 | G19: 2027 | H19: 2028
C20: 0 | D20: 1 | E20: 2 | F20: 3 | G20: 4 | H20: 5
B21: Annual Dividends Per Share | C21: =Assumptions!$C$56 -> 1.93 | D21: =C21*(1+$C25) -> 1.998523 | E21: =D21*(1+$C25) -> 2.0694789 | F21: =E21*(1+$C25) -> 2.142954 | G21: =F21*(1+$C25) -> 2.2190378 | H21: =G21*(1+$C25) -> 2.2978229
B22: Cost of Equity | C22: =Assumptions!$C$57 -> 0.068229 | D22: =C22 -> 0.068229 | E22: =D22 -> 0.068229 | F22: =E22 -> 0.068229 | G22: =F22 -> 0.068229 | H22: =G22 -> 0.068229
B23: Present Value of Dividend | C23: =C21/(1+C22)^C20 -> 1.93 | D23: =D21/(1+D22)^D20 -> 1.8708751 | E23: =E21/(1+E22)^E20 -> 1.8135615 | F23: =F21/(1+F22)^F20 -> 1.7580036 | G23: =G21/(1+G22)^G20 -> 1.7041477 | H23: =H21/(1+H22)^H20 -> 1.6519417
B25: Dividend Growth Rate Stage 1 | C25: =IF(Assumptions!$C$54="CAGR",Assumptions!$C$47,Assumptions!$C$51) -> 0.03550416
B26: Dividend Growth Rate Stage 2 | C26: =Assumptions!$C$133 -> 0.01
B28: Sum of Stage 1 Dividends | C28: =SUM(D23:H23) -> 8.7985296
B29: Year 5 Dividend * (1 + Stage 2 Growth Rate) | C29: =H21*(1+$C26) -> 2.3208011
B30: Stage 2 Terminal Value | C30: =C29/(C22-C26) -> 39.856448
B31: PV of Stage 2 Terminal Value | C31: =C30/(1+C22)^H20 -> 28.65344
B32: Value Per Share | C32: =SUM(C28,C31) -> 37.45197
A35: Bull | B35: ="DDM - "&A35&" - "&Assumptions!$C$54 -> DDM - Bull - CAGR | C35: {=_xlfn.SEQUENCE(1,6,(YEAR(Assumptions!$C$19)-1))} -> 2023 | D35: 2024 | E35: 2025 | F35: 2026 | G35: 2027 | H35: 2028
C36: 0 | D36: 1 | E36: 2 | F36: 3 | G36: 4 | H36: 5
B37: Annual Dividends Per Share | C37: =Assumptions!$C$56 -> 1.93 | D37: =C37*(1+$C41) -> 2.037123 | E37: =D37*(1+$C41) -> 2.1501918 | F37: =E37*(1+$C41) -> 2.2695364 | G37: =F37*(1+$C41) -> 2.3955051 | H37: =G37*(1+$C41) -> 2.5284656
B38: Cost of Equity | C38: =Assumptions!$C$57 -> 0.068229 | D38: =C38 -> 0.068229 | E38: =D38 -> 0.068229 | F38: =E38 -> 0.068229 | G38: =F38 -> 0.068229 | H38: =G38 -> 0.068229
B39: Present Value of Dividend | C39: =C37/(1+C38)^C36 -> 1.93 | D39: =D37/(1+D38)^D36 -> 1.9070097 | E39: =E37/(1+E38)^E36 -> 1.8842932 | F39: =F37/(1+F38)^F36 -> 1.8618473 | G39: =G37/(1+G38)^G36 -> 1.8396688 | H39: =H37/(1+H38)^H36 -> 1.8177545
B41: Dividend Growth Rate Stage 1 | C41: =IF(Assumptions!$C$54="CAGR",Assumptions!$C$48,Assumptions!$C$52) -> 0.05550416
B42: Dividend Growth Rate Stage 2 | C42: =Assumptions!$C$133 -> 0.01
B44: Sum of Stage 1 Dividends | C44: =SUM(D39:H39) -> 9.3105735
B45: Year 5 Dividend * (1 + Stage 2 Growth Rate) | C45: =H37*(1+$C42) -> 2.5537503
B46: Stage 2 Terminal Value | C46: =C45/(C38-C42) -> 43.857018
B47: PV of Stage 2 Terminal Value | C47: =C46/(1+C38)^H36 -> 31.529514
B48: Value Per Share | C48: =SUM(C44,C47) -> 40.840088
B51: Dividend Discount Model Summary
B52: Scenarios
A53: Base | B53: =B3 -> DDM - Base - CAGR | C53: =C16 -> 39.1153
A54: Bear | B54: =B19 -> DDM - Bear - CAGR | C54: =C32 -> 37.45197
A55: Bull | B55: =B35 -> DDM - Bull - CAGR | C55: =C48 -> 40.840088

Sheet Income Statement
B2: Income Statement - Base
B3: =Assumptions!$B$132 -> Year Ending 09/31/2024, In USD Millions | C3: {=_xlfn.SEQUENCE(1,5+Assumptions!$C$20,(YEAR('Valuation Summary'!$C$4)-5))} -> 2019 | D3: 2020 | E3: 2021 | F3: 2022 | G3: 2023 | H3: 2024 | I3: 2025 | J3: 2026 | K3: 2027 | L3: 2028
B4: =Assumptions!B136 -> Revenue | C4: =Assumptions!D136 -> 42405 | D4: =Assumptions!E136 -> 43185 | E4: =Assumptions!F136 -> 47049 | F4: =Assumptions!G136 -> 53282 | G4: =Assumptions!H136 -> 52881 | H4: =IF(H3="",0,G4*(1+H6)) -> 53409.81 | I4: =IF(I3="",0,H4*(1+I6)) -> 53943.908 | J4: =IF(J3="",0,I4*(1+J6)) -> 54483.347 | K4: =IF(K3="",0,J4*(1+K6)) -> 55028.181 | L4: =IF(L3="",0,K4*(1+L6)) -> 55578.462 | M4: =IF(M3="",0,L4*(1+M6)) -> 0 | N4: =IF(N3="",0,M4*(1+N6)) -> 0 | O4: =IF(O3="",0,N4*(1+O6)) -> 0 | ... Q4: =IF(Q3="",0,P4*(1+Q6)) -> 0
B5: ="% of "&$B$4 -> % of Revenue | C5: =IFERROR(C4/C$4,0) -> 1 | D5: =D4/D$4 -> 1 | E5: =E4/E$4 -> 1 | F5: =F4/F$4 -> 1 | G5: =G4/G$4 -> 1 | H5: =IFERROR(H4/H$4,0) -> 1 | I5: =IFERROR(I4/I$4,0) -> 1 | J5: =IFERROR(J4/J$4,0) -> 1 | K5: =IFERROR(K4/K$4,0) -> 1 | L5: =IFERROR(L4/L$4,0) -> 1 | M5: =IFERROR(M4/M$4,0) -> 0 | N5: =IFERROR(N4/N$4,0) -> 0 | O5: =IFERROR(O4/O$4,0) -> 0 | ... Q5: =IFERROR(Q4/Q$4,0) -> 0
B6: Year over Year Growth % | D6: =D4/C4-1 -> 0.018394057 | E6: =E4/D4-1 -> 0.089475512 | F6: =F4/E4-1 -> 0.1324789 | G6: =G4/F4-1 -> -0.0075259938 | H6: =Assumptions!I$137 -> 0.01 | I6: =Assumptions!J$137 -> 0.01 | J6: =Assumptions!K$137 -> 0.01 | K6: =Assumptions!L$137 -> 0.01 | L6: =Assumptions!M$137 -> 0.01 | M6: =Assumptions!N$137 -> 0 | N6: =Assumptions!O$137 -> 0 | O6: =Assumptions!P$137 -> 0 | ... Q6: =Assumptions!R$137 -> 0
B8: =Assumptions!B142 -> Cost of Revenue ~ Cost of Goods Sold | C8: =Assumptions!D142 -> 37383 | D8: =Assumptions!E142 -> 37801 | E8: =Assumptions!F142 -> 40523 | F8: =Assumptions!G142 -> 46614 | G8: =Assumptions!H142 -> 50250 | H8: =H$4*H9 -> 47463.082 | I8: =I$4*I9 -> 47937.713 | J8: =J$4*J9 -> 48417.09 | K8: =K$4*K9 -> 48901.261 | L8: =L$4*L9 -> 49390.273 | M8: =M$4*M9 -> 0 | N8: =N$4*N9 -> 0 | O8: =O$4*O9 -> 0 | ... Q8: =Q$4*Q9 -> 0
B9: ="% of "&$B$4 -> % of Revenue | C9: =IFERROR(C8/C$4,0) -> 0.88157057 | D9: =D8/D$4 -> 0.87532708 | E9: =E8/E$4 -> 0.86129355 | F9: =F8/F$4 -> 0.87485455 | G9: =G8/G$4 -> 0.95024678 | H9: =Assumptions!I$143 -> 0.8886585 | I9: =Assumptions!J$143 -> 0.8886585 | J9: =Assumptions!K$143 -> 0.8886585 | K9: =Assumptions!L$143 -> 0.8886585 | L9: =Assumptions!M$143 -> 0.8886585 | M9: =Assumptions!N$143 -> 0 | N9: =Assumptions!O$143 -> 0 | O9: =Assumptions!P$143 -> 0 | ... Q9: =Assumptions!R$143 -> 0
B10: Year over Year Growth % | D10: =D8/C8-1 -> 0.011181553 | E10: =E8/D8-1 -> 0.072008677 | F10: =F8/E8-1 -> 0.1503097 | G10: =G8/F8-1 -> 0.078002317 | H10: =IF(H$3="",0,H8/G8-1) -> -0.055461057 | I10: =IF(I$3="",0,I8/H8-1) -> 0.01 | J10: =IF(J$3="",0,J8/I8-1) -> 0.01 | K10: =IF(K$3="",0,K8/J8-1) -> 0.01 | L10: =IF(L$3="",0,L8/K8-1) -> 0.01 | M10: =IF(M$3="",0,M8/L8-1) -> 0 | N10: =IF(N$3="",0,N8/M8-1) -> 0 | O10: =IF(O$3="",0,O8/N8-1) -> 0 | ... Q10: =IF(Q$3="",0,Q8/P8-1) -> 0
B12: Gross Profit | C12: =C4-C8 -> 5022 | D12: =D4-D8 -> 5384 | E12: =E4-E8 -> 6526 | F12: =F4-F8 -> 6668 | G12: =G4-G8 -> 2631 | H12: =H4-H8 -> 5946.7281 | I12: =I4-I8 -> 6006.1954 | J12: =J4-J8 -> 6066.2573 | ... Q12: =Q4-Q8 -> 0
B13: ="% of "&$B$4 -> % of Revenue | C13: =IFERROR(C12/C$4,0) -> 0.11842943 | D13: =D12/D$4 -> 0.12467292 | E13: =E12/E$4 -> 0.13870645 | F13: =F12/F$4 -> 0.12514545 | G13: =G12/G$4 -> 0.049753219 | H13: =IFERROR(H12/H$4,0) -> 0.1113415 | I13: =IFERROR(I12/I$4,0) -> 0.1113415 | J13: =IFERROR(J12/J$4,0) -> 0.1113415 | K13: =IFERROR(K12/K$4,0) -> 0.1113415 | L13: =IFERROR(L12/L$4,0) -> 0.1113415 | M13: =IFERROR(M12/M$4,0) -> 0 | N13: =IFERROR(N12/N$4,0) -> 0 | O13: =IFERROR(O12/O$4,0) -> 0 | ... Q13: =IFERROR(Q12/Q$4,0) -> 0
B14: Year over Year Growth % | D14: =D12/C12-1 -> 0.072082836 | E14: =E12/D12-1 -> 0.21210996 | F14: =F12/E12-1 -> 0.021759117 | G14: =G12/F12-1 -> -0.60542891 | H14: =IF(H3="",0,H12/G12-1) -> 1.2602539 | I14: =IF(I3="",0,I12/H12-1) -> 0.01 | J14: =IF(J3="",0,J12/I12-1) -> 0.01 | K14: =IF(K3="",0,K12/J12-1) -> 0.01 | L14: =IF(L3="",0,L12/K12-1) -> 0.01 | M14: =IF(M3="",0,M12/L12-1) -> 0 | N14: =IF(N3="",0,N12/M12-1) -> 0 | O14: =IF(O3="",0,O12/N12-1) -> 0 | ... Q14: =IF(Q3="",0,Q12/P12-1) -> 0
B16: =Assumptions!B146 -> Other Operating Income | C16: =Assumptions!D146 -> 0 | D16: =Assumptions!E146 -> 0 | E16: =Assumptions!F146 -> 0 | F16: =Assumptions!G146 -> 0 | G16: =Assumptions!H146 -> 0 | H16: =H$4*H17 -> 0 | I16: =I$4*I17 -> 0 | J16: =J$4*J17 -> 0 | K16: =K$4*K17 -> 0 | L16: =L$4*L17 -> 0 | M16: =M$4*M17 -> 0 | N16: =N$4*N17 -> 0 | O16: =O$4*O17 -> 0 | ... Q16: =Q$4*Q17 -> 0
B17: ="% of "&$B$4 -> % of Revenue | C17: =IFERROR(C16/C$4,0) -> 0 | D17: =D16/D$4 -> 0 | E17: =E16/E$4 -> 0 | F17: =F16/F$4 -> 0 | G17: =G16/G$4 -> 0 | H17: =Assumptions!I$147 -> 0 | I17: =Assumptions!J$147 -> 0 | J17: =Assumptions!K$147 -> 0 | K17: =Assumptions!L$147 -> 0 | L17: =Assumptions!M$147 -> 0 | M17: =Assumptions!N$147 -> 0 | N17: =Assumptions!O$147 -> 0 | O17: =Assumptions!P$147 -> 0 | ... Q17: =Assumptions!R$147 -> 0
B19: =Assumptions!B150 -> Operating Expenses | C19: =Assumptions!D150 -> 1959 | D19: =Assumptions!E150 -> 2481 | E19: =Assumptions!F150 -> 2278 | F19: =Assumptions!G150 -> 2306 | G19: =Assumptions!H150 -> 1737 | H19: =H$4*H20 -> 2437.5381 | I19: =I$4*I20 -> 2461.9135 | J19: =J$4*J20 -> 2486.5326 | K19: =K$4*K20 -> 2511.398 | L19: =L$4*L20 -> 2536.5119 | M19: =M$4*M20 -> 0 | N19: =N$4*N20 -> 0 | O19: =O$4*O20 -> 0 | ... Q19: =Q$4*Q20 -> 0
B20: ="% of "&$B$4 -> % of Revenue | C20: =IFERROR(C19/C$4,0) -> 0.046197382 | D20: =D19/D$4 -> 0.057450504 | E20: =E19/E$4 -> 0.048417607 | F20: =F19/F$4 -> 0.043279156 | G20: =G19/G$4 -> 0.032847336 | H20: =Assumptions!I$151 -> 0.045638397 | I20: =Assumptions!J$151 -> 0.045638397 | J20: =Assumptions!K$151 -> 0.045638397 | K20: =Assumptions!L$151 -> 0.045638397 | L20: =Assumptions!M$151 -> 0.045638397 | M20: =Assumptions!N$151 -> 0 | N20: =Assumptions!O$151 -> 0 | O20: =Assumptions!P$151 -> 0 | ... Q20: =Assumptions!R$151 -> 0
B22: Operating Income (Loss) ~ EBIT | C22: =C12+C16-C19 -> 3063 | D22: =D12+D16-D19 -> 2903 | E22: =E12+E16-E19 -> 4248 | F22: =F12+F16-F19 -> 4362 | G22: =G12+G16-G19 -> 894 | H22: =H12+H16-H19 -> 3509.19 | I22: =I12+I16-I19 -> 3544.2819 | J22: =J12+J16-J19 -> 3579.7247 | ... Q22: =Q12+Q16-Q19 -> 0
B23: ="% of "&$B$4 -> % of Revenue | C23: =IFERROR(C22/C$4,0) -> 0.072232048 | D23: =D22/D$4 -> 0.067222415 | E23: =E22/E$4 -> 0.090288848 | F23: =F22/F$4 -> 0.081866296 | G23: =G22/G$4 -> 0.016905883 | H23: =IFERROR(H22/H$4,0) -> 0.065703098 | I23: =IFERROR(I22/I$4,0) -> 0.065703098 | J23: =IFERROR(J22/J$4,0) -> 0.065703098 | K23: =IFERROR(K22/K$4,0) -> 0.065703098 | L23: =IFERROR(L22/L$4,0) -> 0.065703098 | M23: =IFERROR(M22/M$4,0) -> 0 | N23: =IFERROR(N22/N$4,0) -> 0 | O23: =IFERROR(O22/O$4,0) -> 0 | ... Q23: =IFERROR(Q22/Q$4,0) -> 0
B25: =Assumptions!B154 -> Non-Operating (Income) Loss | C25: =Assumptions!D154 -> 632 | D25: =Assumptions!E154 -> 239 | E25: =Assumptions!F154 -> 207 | F25: =Assumptions!G154 -> 213 | G25: =Assumptions!H154 -> 1572 | H25: =+Assumptions!I$154+H4*Assumptions!$I$167+H4*Assumptions!I$169 -> 524.11159 | I25: =+Assumptions!J$154+I4*Assumptions!$I$167+I4*Assumptions!J$169 -> 509.36479 | J25: =+Assumptions!K$154+J4*Assumptions!$I$167+J4*Assumptions!K$169 -> 511.83324 | K25: =+Assumptions!L$154+K4*Assumptions!$I$167+K4*Assumptions!L$169 -> 525.46603 | L25: =+Assumptions!M$154+L4*Assumptions!$I$167+L4*Assumptions!M$169 -> 533.84674 | M25: =+Assumptions!N$154+M4*Assumptions!$I$167+M4*Assumptions!N$169 -> 0 | N25: =+Assumptions!O$154+N4*Assumptions!$I$167+N4*Assumptions!O$169 -> 0 | O25: =+Assumptions!P$154+O4*Assumptions!$I$167+O4*Assumptions!P$169 -> 0 | ... Q25: =+Assumptions!R$154+Q4*Assumptions!$I$167+Q4*Assumptions!R$169 -> 0
B26: ="% of "&$B$4 -> % of Revenue | C26: =IFERROR(C25/C$4,0) -> 0.014903903 | D26: =D25/D$4 -> 0.005534329 | E26: =E25/E$4 -> 0.0043996684 | F26: =F25/F$4 -> 0.0039975977 | G26: =G25/G$4 -> 0.029727123 | H26: =IFERROR(H25/H$4,0) -> 0.0098130211 | I26: =IFERROR(I25/I$4,0) -> 0.0094424896 | J26: =IFERROR(J25/J$4,0) -> 0.0093943061 | K26: =IFERROR(K25/K$4,0) -> 0.0095490352 | L26: =IFERROR(L25/L$4,0) -> 0.0096052809 | M26: =IFERROR(M25/M$4,0) -> 0 | N26: =IFERROR(N25/N$4,0) -> 0 | O26: =IFERROR(O25/O$4,0) -> 0 | ... Q26: =IFERROR(Q25/Q$4,0) -> 0
B28: Pretax Income (Loss), GAAP ~ EBT | C28: =C22-C25 -> 2431 | D28: =D22-D25 -> 2664 | E28: =E22-E25 -> 4041 | F28: =F22-F25 -> 4149 | G28: =G22-G25 -> -678 | H28: =H22-H25 -> 2985.0784 | I28: =I22-I25 -> 3034.9171 | J28: =J22-J25 -> 3067.8915 | ... Q28: =Q22-Q25 -> 0
B29: ="% of "&$B$4 -> % of Revenue | C29: =IFERROR(C28/C$4,0) -> 0.057328145 | D29: =D28/D$4 -> 0.061688086 | E29: =E28/E$4 -> 0.085889179 | F29: =F28/F$4 -> 0.077868699 | G29: =G28/G$4 -> -0.01282124 | H29: =IFERROR(H28/H$4,0) -> 0.055890077 | I29: =IFERROR(I28/I$4,0) -> 0.056260608 | J29: =IFERROR(J28/J$4,0) -> 0.056308792 | K29: =IFERROR(K28/K$4,0) -> 0.056154063 | L29: =IFERROR(L28/L$4,0) -> 0.056097817 | M29: =IFERROR(M28/M$4,0) -> 0 | N29: =IFERROR(N28/N$4,0) -> 0 | O29: =IFERROR(O28/O$4,0) -> 0 | ... Q29: =IFERROR(Q28/Q$4,0) -> 0
B31: =Assumptions!B172 -> Income Tax Expense (Benefit) | C31: =Assumptions!D172 -> 396 | D31: =Assumptions!E172 -> 593 | E31: =Assumptions!F172 -> 981 | F31: =Assumptions!G172 -> 900 | G31: =Assumptions!H172 -> -29 | H31: =H28*Assumptions!I174 -> 626.86646 | I31: =I28*Assumptions!J174 -> 637.33259 | J31: =J28*Assumptions!K174 -> 644.25721 | K31: =K28*Assumptions!L174 -> 648.91174 | L31: =L28*Assumptions!M174 -> 654.74439 | M31: =M28*Assumptions!N174 -> 0 | N31: =N28*Assumptions!O174 -> 0 | O31: =O28*Assumptions!P174 -> 0 | ... Q31: =Q28*Assumptions!R174 -> 0
B32: ="% of "&$B$4 -> % of Revenue | C32: =IFERROR(C31/C$4,0) -> 0.0093385214 | D32: =D31/D$4 -> 0.01373162 | E32: =E31/E$4 -> 0.020850603 | F32: =F31/F$4 -> 0.016891258 | G32: =G31/G$4 -> -0.00054840113 | H32: =IFERROR(H31/H$4,0) -> 0.011736916 | I32: =IFERROR(I31/I$4,0) -> 0.011814728 | J32: =IFERROR(J31/J$4,0) -> 0.011824846 | K32: =IFERROR(K31/K$4,0) -> 0.011792353 | L32: =IFERROR(L31/L$4,0) -> 0.011780542 | M32: =IFERROR(M31/M$4,0) -> 0 | N32: =IFERROR(N31/N$4,0) -> 0 | O32: =IFERROR(O31/O$4,0) -> 0 | ... XFD32: =IFERROR(XFD31/XFD$4,0) -> 0
B34: =Assumptions!B177 -> Miscellaneous After Tax Expenditures | C34: =Assumptions!D177 -> 13 | D34: =Assumptions!E177 -> 10 | E34: =Assumptions!F177 -> 13 | F34: =Assumptions!G177 -> 11 | G34: =Assumptions!H177 -> -1 | H34: =H$4*H35 -> 10.703064 | I34: =I$4*I35 -> 10.810095 | J34: =J$4*J35 -> 10.918196 | K34: =K$4*K35 -> 11.027378 | L34: =L$4*L35 -> 11.137652 | M34: =M$4*M35 -> 0 | N34: =N$4*N35 -> 0 | O34: =O$4*O35 -> 0 | ... Q34: =Q$4*Q35 -> 0
B35: ="% of "&$B$4 -> % of Revenue | C35: =IFERROR(C34/C$4,0) -> 0.00030656762 | D35: =D34/D$4 -> 0.00023156188 | E35: =E34/E$4 -> 0.00027630768 | F35: =F34/F$4 -> 0.00020644871 | G35: =G34/G$4 -> -1.8910384e-05 | H35: =Assumptions!I178 -> 0.0002003951 | I35: =Assumptions!J178 -> 0.0002003951 | J35: =Assumptions!K178 -> 0.0002003951 | K35: =Assumptions!L178 -> 0.0002003951 | L35: =Assumptions!M178 -> 0.0002003951 | M35: =Assumptions!N178 -> 0 | N35: =Assumptions!O178 -> 0 | O35: =Assumptions!P178 -> 0 | ... Q35: =Assumptions!R178 -> 0
B37: Net Income (Loss), GAAP | C37: =C28-C31-C34 -> 2022 | D37: =D28-D31-D34 -> 2061 | E37: =E28-E31-E34 -> 3047 | F37: =F28-F31-F34 -> 3238 | G37: =G28-G31-G34 -> -648 | H37: =H28-H31-H34 -> 2347.5089 | I37: =I28-I31-I34 -> 2386.7744 | J37: =J28-J31-J34 -> 2412.7161 | ... Q37: =Q28-Q31-Q34 -> 0
B38: ="% of "&$B$4 -> % of Revenue | C38: =IFERROR(C37/C$4,0) -> 0.047683056 | D38: =D37/D$4 -> 0.047724904 | E38: =E37/E$4 -> 0.064762269 | F38: =F37/F$4 -> 0.060770992 | G38: =G37/G$4 -> -0.012253929 | H38: =IFERROR(H37/H$4,0) -> 0.043952766 | I38: =IFERROR(I37/I$4,0) -> 0.044245486 | J38: =IFERROR(J37/J$4,0) -> 0.044283551 | K38: =IFERROR(K37/K$4,0) -> 0.044161315 | L38: =IFERROR(L37/L$4,0) -> 0.04411688 | M38: =IFERROR(M37/M$4,0) -> 0 | N38: =IFERROR(N37/N$4,0) -> 0 | O38: =IFERROR(O37/O$4,0) -> 0 | ... Q38: =IFERROR(Q37/Q$4,0) -> 0
B39: Year over Year Growth % | D39: =D37/C37-1 -> 0.019287834 | E39: =E37/D37-1 -> 0.47840854 | F39: =F37/E37-1 -> 0.062684608 | G39: =G37/F37-1 -> -1.2001235 | H39: =IF(H$3="",0,H37/G37-1) -> -4.6226989 | I39: =IF(I$3="",0,I37/H37-1) -> 0.016726471 | J39: =IF(J$3="",0,J37/I37-1) -> 0.010868916 | K39: =IF(K$3="",0,K37/J37-1) -> 0.0072120954 | L39: =IF(L$3="",0,L37/K37-1) -> 0.0089837612 | M39: =IF(M$3="",0,M37/L37-1) -> 0 | N39: =IF(N$3="",0,N37/M37-1) -> 0 | O39: =IF(O$3="",0,O37/N37-1) -> 0 | ... Q39: =IF(Q$3="",0,Q37/P37-1) -> 0
B42: EBITDA Calculation
B43: =B$22 -> Operating Income (Loss) ~ EBIT | C43: =C$22 -> 3063 | D43: =D$22 -> 2903 | E43: =E$22 -> 4248 | F43: =F$22 -> 4362 | G43: =G$22 -> 894 | H43: =H$22 -> 3509.19 | I43: =I$22 -> 3544.2819 | ... Q43: =Q$22 -> 0
B44: =Assumptions!B187 -> Capital Expenditures | C44: =Assumptions!D187 -> 1259 | D44: =Assumptions!E187 -> 1199 | E44: =Assumptions!F187 -> 1209 | F44: =Assumptions!G187 -> 1887 | G44: =Assumptions!H187 -> 1939 | H44: =H4*H45 -> 1658.1968 | I44: =I4*I45 -> 1674.7787 | J44: =J4*J45 -> 1691.5265 | K44: =K4*K45 -> 1708.4418 | L44: =L4*L45 -> 1725.5262 | M44: =M4*M45 -> 0 | N44: =N4*N45 -> 0 | O44: =O4*O45 -> 0 | ... Q44: =Q4*Q45 -> 0
B45: ="% of "&$B$4 -> % of Revenue | C45: =IFERROR(C44/C$4,0) -> 0.029689895 | D45: =D44/D$4 -> 0.02776427 | E45: =E44/E$4 -> 0.025696614 | F45: =F44/F$4 -> 0.035415337 | G45: =G44/G$4 -> 0.036667234 | H45: =Assumptions!I$188 -> 0.03104667 | I45: =Assumptions!J188 -> 0.03104667 | J45: =Assumptions!K188 -> 0.03104667 | K45: =Assumptions!L188 -> 0.03104667 | L45: =Assumptions!M188 -> 0.03104667 | M45: =Assumptions!N188 -> 0 | N45: =Assumptions!O188 -> 0 | O45: =Assumptions!P188 -> 0 | P45: =Assumptions!Q188 -> 0 | Q45: =Assumptions!R188 -> 0
B47: =Assumptions!B191 -> Depreciation and Amortization | C47: =Assumptions!D191 -> 1098 | D47: =Assumptions!E191 -> 1192 | E47: =Assumptions!F191 -> 1214 | F47: =Assumptions!G191 -> 1202 | G47: =Assumptions!H191 -> 1339 | H47: =H44*H49 -> 1392.2121 | I47: =I44*I49 -> 1406.1342 | J47: =J44*J49 -> 1420.1956 | K47: =K44*K49 -> 1434.3975 | L47: =L44*L49 -> 1448.7415 | M47: =M44*M49 -> 0 | N47: =N44*N49 -> 0 | O47: =O44*O49 -> 0 | ... Q47: =Q44*Q49 -> 0
B48: ="% of "&$B$4 -> % of Revenue | C48: =IFERROR(C47/C$4,0) -> 0.025893173 | D48: =D47/D$4 -> 0.027602177 | E48: =E47/E$4 -> 0.025802886 | F48: =F47/F$4 -> 0.022559213 | G48: =G47/G$4 -> 0.025321004 | H48: =IFERROR(H47/H$4,0) -> 0.0260666 | I48: =IFERROR(I47/I$4,0) -> 0.0260666 | J48: =IFERROR(J47/J$4,0) -> 0.0260666 | K48: =IFERROR(K47/K$4,0) -> 0.0260666 | L48: =IFERROR(L47/L$4,0) -> 0.0260666 | M48: =IFERROR(M47/M$4,0) -> 0 | N48: =IFERROR(N47/N$4,0) -> 0 | O48: =IFERROR(O47/O$4,0) -> 0 | ... Q48: =IFERROR(Q47/Q$4,0) -> 0
B49: ="% of "&B44 -> % of Capital Expenditures | C49: =IFERROR(C47/C44,0) -> 0.87212073 | D49: =IFERROR(D47/D44,0) -> 0.9941618 | E49: =IFERROR(E47/E44,0) -> 1.0041356 | F49: =IFERROR(F47/F44,0) -> 0.63698993 | G49: =IFERROR(G47/G44,0) -> 0.69056215 | H49: =Assumptions!I$192 -> 0.83959405 | I49: =Assumptions!J$192 -> 0.83959405 | J49: =Assumptions!K$192 -> 0.83959405 | K49: =Assumptions!L$192 -> 0.83959405 | L49: =Assumptions!M$192 -> 0.83959405 | M49: =Assumptions!N$192 -> 0 | N49: =Assumptions!O$192 -> 0 | O49: =Assumptions!P$192 -> 0 | ... Q49: =Assumptions!R$192 -> 0
B51: =_xlfn.TEXTBEFORE(Assumptions!B195," [") -> Cost of Capitalized Leases | C51: =Assumptions!D195 -> 0 | D51: =Assumptions!E195 -> 0 | E51: =Assumptions!F195 -> 0 | F51: =Assumptions!G195 -> 0 | G51: =Assumptions!H195 -> 0 | H51: =H$4*H52 -> 0 | I51: =I$4*I52 -> 0 | J51: =J$4*J52 -> 0 | K51: =K$4*K52 -> 0 | L51: =L$4*L52 -> 0 | M51: =M$4*M52 -> 0 | N51: =N$4*N52 -> 0 | O51: =O$4*O52 -> 0 | ... Q51: =Q$4*Q52 -> 0
B52: ="% of "&$B$4 -> % of Revenue | C52: =IFERROR(C51/C$4,0) -> 0 | D52: =D51/D$4 -> 0 | E52: =E51/E$4 -> 0 | F52: =F51/F$4 -> 0 | G52: =G51/G$4 -> 0 | H52: =+Assumptions!I196 -> 0 | I52: =+Assumptions!J196 -> 0 | J52: =+Assumptions!K196 -> 0 | K52: =+Assumptions!L196 -> 0 | L52: =+Assumptions!M196 -> 0 | M52: =+Assumptions!N196 -> 0 | N52: =+Assumptions!O196 -> 0 | O52: =+Assumptions!P196 -> 0 | ... Q52: =+Assumptions!R196 -> 0
B53: EBITDA | C53: =SUM(C43,C47,C51) -> 4161 | D53: =SUM(D43,D47,D51) -> 4095 | E53: =SUM(E43,E47,E51) -> 5462 | F53: =SUM(F43,F47,F51) -> 5564 | G53: =SUM(G43,G47,G51) -> 2233 | H53: =SUM(H43,H47,H51) -> 4901.4021 | I53: =SUM(I43,I47,I51) -> 4950.4161 | J53: =SUM(J43,J47,J51) -> 4999.9203 | ... Q53: =SUM(Q43,Q47,Q51) -> 0
B56: NOPAT Calculation
B57: =B$22 -> Operating Income (Loss) ~ EBIT | C57: =C$22 -> 3063 | D57: =D$22 -> 2903 | E57: =E$22 -> 4248 | F57: =F$22 -> 4362 | G57: =G$22 -> 894 | H57: =H$22 -> 3509.19 | I57: =I$22 -> 3544.2819 | ... Q57: =Q$22 -> 0
B58: =B$31 -> Income Tax Expense (Benefit) | C58: =C$31 -> 396 | D58: =D$31 -> 593 | E58: =E$31 -> 981 | F58: =F$31 -> 900 | G58: =G$31 -> -29 | H58: =H$31 -> 626.86646 | I58: =I$31 -> 637.33259 | ... Q58: =Q$31 -> 0
B59: Net Profit After Tax - NOPAT | C59: =C57-C58 -> 2667 | D59: =D57-D58 -> 2310 | E59: =E57-E58 -> 3267 | F59: =F57-F58 -> 3462 | G59: =G57-G58 -> 923 | H59: =H57-H58 -> 2882.3235 | I59: =I57-I58 -> 2906.9493 | J59: =J57-J58 -> 2935.4675 | ... Q59: =Q57-Q58 -> 0

Sheet IS Bear
B2: Income Statement - Bear
B3: =Assumptions!$B$132 -> Year Ending 09/31/2024, In USD Millions | C3: {=_xlfn.SEQUENCE(1,5+Assumptions!$C$20,(YEAR('Valuation Summary'!$C$4)-5))} -> 2019 | D3: 2020 | E3: 2021 | F3: 2022 | G3: 2023 | H3: 2024 | I3: 2025 | J3: 2026 | K3: 2027 | L3: 2028
B4: =Assumptions!B136 -> Revenue | C4: =Assumptions!D136 -> 42405 | D4: =Assumptions!E136 -> 43185 | E4: =Assumptions!F136 -> 47049 | F4: =Assumptions!G136 -> 53282 | G4: =Assumptions!H136 -> 52881 | H4: =IF(H3="",0,G4*(1+H6)) -> 52352.19 | I4: =IF(I3="",0,H4*(1+I6)) -> 51828.668 | J4: =IF(J3="",0,I4*(1+J6)) -> 51310.381 | K4: =IF(K3="",0,J4*(1+K6)) -> 50797.278 | L4: =IF(L3="",0,K4*(1+L6)) -> 50289.305 | M4: =IF(M3="",0,L4*(1+M6)) -> 0 | N4: =IF(N3="",0,M4*(1+N6)) -> 0 | O4: =IF(O3="",0,N4*(1+O6)) -> 0 | ... Q4: =IF(Q3="",0,P4*(1+Q6)) -> 0
B5: ="% of "&$B$4 -> % of Revenue | C5: =IFERROR(C4/C$4,0) -> 1 | D5: =D4/D$4 -> 1 | E5: =E4/E$4 -> 1 | F5: =F4/F$4 -> 1 | G5: =G4/G$4 -> 1 | H5: =IFERROR(H4/H$4,0) -> 1 | I5: =IFERROR(I4/I$4,0) -> 1 | J5: =IFERROR(J4/J$4,0) -> 1 | K5: =IFERROR(K4/K$4,0) -> 1 | L5: =IFERROR(L4/L$4,0) -> 1 | M5: =IFERROR(M4/M$4,0) -> 0 | N5: =IFERROR(N4/N$4,0) -> 0 | O5: =IFERROR(O4/O$4,0) -> 0 | ... Q5: =IFERROR(Q4/Q$4,0) -> 0
B6: Year over Year Growth % | D6: =D4/C4-1 -> 0.018394057 | E6: =E4/D4-1 -> 0.089475512 | F6: =F4/E4-1 -> 0.1324789 | G6: =G4/F4-1 -> -0.0075259938 | H6: =Assumptions!I$138 -> -0.01 | I6: =Assumptions!J$138 -> -0.01 | J6: =Assumptions!K$138 -> -0.01 | K6: =Assumptions!L$138 -> -0.01 | L6: =Assumptions!M$138 -> -0.01 | M6: =Assumptions!N$138 -> 0 | N6: =Assumptions!O$138 -> 0 | O6: =Assumptions!P$138 -> 0 | ... Q6: =Assumptions!R$138 -> 0
B8: =Assumptions!B142 -> Cost of Revenue ~ Cost of Goods Sold | C8: =Assumptions!D142 -> 37383 | D8: =Assumptions!E142 -> 37801 | E8: =Assumptions!F142 -> 40523 | F8: =Assumptions!G142 -> 46614 | G8: =Assumptions!H142 -> 50250 | H8: =H$4*H9 -> 46523.219 | I8: =I$4*I9 -> 46057.987 | J8: =J$4*J9 -> 45597.407 | K8: =K$4*K9 -> 45141.433 | L8: =L$4*L9 -> 44690.018 | M8: =M$4*M9 -> 0 | N8: =N$4*N9 -> 0 | O8: =O$4*O9 -> 0 | ... Q8: =Q$4*Q9 -> 0
B9: ="% of "&$B$4 -> % of Revenue | C9: =IFERROR(C8/C$4,0) -> 0.88157057 | D9: =D8/D$4 -> 0.87532708 | E9: =E8/E$4 -> 0.86129355 | F9: =F8/F$4 -> 0.87485455 | G9: =G8/G$4 -> 0.95024678 | H9: =Assumptions!I$143 -> 0.8886585 | I9: =Assumptions!J$143 -> 0.8886585 | J9: =Assumptions!K$143 -> 0.8886585 | K9: =Assumptions!L$143 -> 0.8886585 | L9: =Assumptions!M$143 -> 0.8886585 | M9: =Assumptions!N$143 -> 0 | N9: =Assumptions!O$143 -> 0 | O9: =Assumptions!P$143 -> 0 | ... Q9: =Assumptions!R$143 -> 0
B10: Year over Year Growth % | D10: {=D8/C8-1} -> 0.011181553 | E10: {=E8/D8-1} -> 0.072008677 | F10: {=F8/E8-1} -> 0.1503097 | G10: {=G8/F8-1} -> 0.078002317 | H10: =IF(H$3="",0,H8/G8-1) -> -0.074164798 | I10: =IF(I$3="",0,I8/H8-1) -> -0.01 | J10: =IF(J$3="",0,J8/I8-1) -> -0.01 | K10: =IF(K$3="",0,K8/J8-1) -> -0.01 | L10: =IF(L$3="",0,L8/K8-1) -> -0.01 | M10: =IF(M$3="",0,M8/L8-1) -> 0 | N10: =IF(N$3="",0,N8/M8-1) -> 0 | O10: =IF(O$3="",0,O8/N8-1) -> 0 | ... Q10: =IF(Q$3="",0,Q8/P8-1) -> 0
B12: Gross Profit | C12: =C4-C8 -> 5022 | D12: =D4-D8 -> 5384 | E12: =E4-E8 -> 6526 | F12: =F4-F8 -> 6668 | G12: =G4-G8 -> 2631 | H12: =H4-H8 -> 5828.9711 | I12: =I4-I8 -> 5770.6814 | J12: =J4-J8 -> 5712.9746 | ... Q12: =Q4-Q8 -> 0
B13: ="% of "&$B$4 -> % of Revenue | C13: =IFERROR(C12/C$4,0) -> 0.11842943 | D13: =D12/D$4 -> 0.12467292 | E13: =E12/E$4 -> 0.13870645 | F13: =F12/F$4 -> 0.12514545 | G13: =G12/G$4 -> 0.049753219 | H13: =IFERROR(H12/H$4,0) -> 0.1113415 | I13: =IFERROR(I12/I$4,0) -> 0.1113415 | J13: =IFERROR(J12/J$4,0) -> 0.1113415 | K13: =IFERROR(K12/K$4,0) -> 0.1113415 | L13: =IFERROR(L12/L$4,0) -> 0.1113415 | M13: =IFERROR(M12/M$4,0) -> 0 | N13: =IFERROR(N12/N$4,0) -> 0 | O13: =IFERROR(O12/O$4,0) -> 0 | ... Q13: =IFERROR(Q12/Q$4,0) -> 0
B14: Year over Year Growth % | D14: =D12/C12-1 -> 0.072082836 | E14: =E12/D12-1 -> 0.21210996 | F14: =F12/E12-1 -> 0.021759117 | G14: =G12/F12-1 -> -0.60542891 | H14: =IF(H3="",0,H12/G12-1) -> 1.2154964 | I14: =IF(I3="",0,I12/H12-1) -> -0.01 | J14: =IF(J3="",0,J12/I12-1) -> -0.01 | K14: =IF(K3="",0,K12/J12-1) -> -0.01 | L14: =IF(L3="",0,L12/K12-1) -> -0.01 | M14: =IF(M3="",0,M12/L12-1) -> 0 | N14: =IF(N3="",0,N12/M12-1) -> 0 | O14: =IF(O3="",0,O12/N12-1) -> 0 | ... Q14: =IF(Q3="",0,Q12/P12-1) -> 0
B16: =Assumptions!B146 -> Other Operating Income | C16: =Assumptions!D146 -> 0 | D16: =Assumptions!E146 -> 0 | E16: =Assumptions!F146 -> 0 | F16: =Assumptions!G146 -> 0 | G16: =Assumptions!H146 -> 0 | H16: =H$4*H17 -> 0 | I16: =I$4*I17 -> 0 | J16: =J$4*J17 -> 0 | K16: =K$4*K17 -> 0 | L16: =L$4*L17 -> 0 | M16: =M$4*M17 -> 0 | N16: =N$4*N17 -> 0 | O16: =O$4*O17 -> 0 | ... Q16: =Q$4*Q17 -> 0
B17: ="% of "&$B$4 -> % of Revenue | C17: =IFERROR(C16/C$4,0) -> 0 | D17: =D16/D$4 -> 0 | E17: =E16/E$4 -> 0 | F17: =F16/F$4 -> 0 | G17: =G16/G$4 -> 0 | H17: =Assumptions!I$147 -> 0 | I17: =Assumptions!J$147 -> 0 | J17: =Assumptions!K$147 -> 0 | K17: =Assumptions!L$147 -> 0 | L17: =Assumptions!M$147 -> 0 | M17: =Assumptions!N$147 -> 0 | N17: =Assumptions!O$147 -> 0 | O17: =Assumptions!P$147 -> 0 | ... Q17: =Assumptions!R$147 -> 0
B19: =Assumptions!B150 -> Operating Expenses | C19: =Assumptions!D150 -> 1959 | D19: =Assumptions!E150 -> 2481 | E19: =Assumptions!F150 -> 2278 | F19: =Assumptions!G150 -> 2306 | G19: =Assumptions!H150 -> 1737 | H19: =H$4*H20 -> 2389.27 | I19: =I$4*I20 -> 2365.3773 | J19: =J$4*J20 -> 2341.7236 | K19: =K$4*K20 -> 2318.3063 | L19: =L$4*L20 -> 2295.1233 | M19: =M$4*M20 -> 0 | N19: =N$4*N20 -> 0 | O19: =O$4*O20 -> 0 | ... Q19: =Q$4*Q20 -> 0
B20: ="% of "&$B$4 -> % of Revenue | C20: =IFERROR(C19/C$4,0) -> 0.046197382 | D20: =D19/D$4 -> 0.057450504 | E20: =E19/E$4 -> 0.048417607 | F20: =F19/F$4 -> 0.043279156 | G20: =G19/G$4 -> 0.032847336 | H20: =Assumptions!I$151 -> 0.045638397 | I20: =Assumptions!J$151 -> 0.045638397 | J20: =Assumptions!K$151 -> 0.045638397 | K20: =Assumptions!L$151 -> 0.045638397 | L20: =Assumptions!M$151 -> 0.045638397 | M20: =Assumptions!N$151 -> 0 | N20: =Assumptions!O$151 -> 0 | O20: =Assumptions!P$151 -> 0 | ... Q20: =Assumptions!R$151 -> 0
B22: Operating Income (Loss) ~ EBIT | C22: =C12+C16-C19 -> 3063 | D22: =D12+D16-D19 -> 2903 | E22: =E12+E16-E19 -> 4248 | F22: =F12+F16-F19 -> 4362 | G22: =G12+G16-G19 -> 894 | H22: =H12+H16-H19 -> 3439.7011 | I22: =I12+I16-I19 -> 3405.3041 | J22: =J12+J16-J19 -> 3371.251 | ... Q22: =Q12+Q16-Q19 -> 0
B23: ="% of "&$B$4 -> % of Revenue | C23: =IFERROR(C22/C$4,0) -> 0.072232048 | D23: =D22/D$4 -> 0.067222415 | E23: =E22/E$4 -> 0.090288848 | F23: =F22/F$4 -> 0.081866296 | G23: =G22/G$4 -> 0.016905883 | H23: =IFERROR(H22/H$4,0) -> 0.065703098 | I23: =IFERROR(I22/I$4,0) -> 0.065703098 | J23: =IFERROR(J22/J$4,0) -> 0.065703098 | K23: =IFERROR(K22/K$4,0) -> 0.065703098 | L23: =IFERROR(L22/L$4,0) -> 0.065703098 | M23: =IFERROR(M22/M$4,0) -> 0 | N23: =IFERROR(N22/N$4,0) -> 0 | O23: =IFERROR(O22/O$4,0) -> 0 | ... Q23: =IFERROR(Q22/Q$4,0) -> 0
B25: =Assumptions!B154 -> Non-Operating (Income) Loss | C25: =Assumptions!D154 -> 632 | D25: =Assumptions!E154 -> 239 | E25: =Assumptions!F154 -> 207 | F25: =Assumptions!G154 -> 213 | G25: =Assumptions!H154 -> 1572 | H25: =+Assumptions!I$154+H4*Assumptions!$I$167+H4*Assumptions!I$169 -> 520.87022 | I25: =+Assumptions!J$154+I4*Assumptions!$I$167+I4*Assumptions!J$169 -> 502.88206 | J25: =+Assumptions!K$154+J4*Assumptions!$I$167+J4*Assumptions!K$169 -> 502.10882 | K25: =+Assumptions!L$154+K4*Assumptions!$I$167+K4*Assumptions!L$169 -> 512.49927 | L25: =+Assumptions!M$154+L4*Assumptions!$I$167+L4*Assumptions!M$169 -> 517.63667 | M25: =+Assumptions!N$154+M4*Assumptions!$I$167+M4*Assumptions!N$169 -> 0 | N25: =+Assumptions!O$154+N4*Assumptions!$I$167+N4*Assumptions!O$169 -> 0 | O25: =+Assumptions!P$154+O4*Assumptions!$I$167+O4*Assumptions!P$169 -> 0 | ... Q25: =+Assumptions!R$154+Q4*Assumptions!$I$167+Q4*Assumptions!R$169 -> 0
B26: ="% of "&$B$4 -> % of Revenue | C26: =IFERROR(C25/C$4,0) -> 0.014903903 | D26: =D25/D$4 -> 0.005534329 | E26: =E25/E$4 -> 0.0043996684 | F26: =F25/F$4 -> 0.0039975977 | G26: =G25/G$4 -> 0.029727123 | H26: =IFERROR(H25/H$4,0) -> 0.0099493493 | I26: =IFERROR(I25/I$4,0) -> 0.009702778 | J26: =IFERROR(J25/J$4,0) -> 0.009785716 | K26: =IFERROR(K25/K$4,0) -> 0.010089109 | L26: =IFERROR(L25/L$4,0) -> 0.010293176 | M26: =IFERROR(M25/M$4,0) -> 0 | N26: =IFERROR(N25/N$4,0) -> 0 | O26: =IFERROR(O25/O$4,0) -> 0 | ... Q26: =IFERROR(Q25/Q$4,0) -> 0
B28: Pretax Income (Loss), GAAP ~ EBT | C28: =C22-C25 -> 2431 | D28: =D22-D25 -> 2664 | E28: =E22-E25 -> 4041 | F28: =F22-F25 -> 4149 | G28: =G22-G25 -> -678 | H28: =H22-H25 -> 2918.8308 | I28: =I22-I25 -> 2902.422 | J28: =J22-J25 -> 2869.1422 | ... Q28: =Q22-Q25 -> 0
B29: ="% of "&$B$4 -> % of Revenue | C29: =IFERROR(C28/C$4,0) -> 0.057328145 | D29: =D28/D$4 -> 0.061688086 | E29: =E28/E$4 -> 0.085889179 | F29: =F28/F$4 -> 0.077868699 | G29: =G28/G$4 -> -0.01282124 | H29: =IFERROR(H28/H$4,0) -> 0.055753749 | I29: =IFERROR(I28/I$4,0) -> 0.05600032 | J29: =IFERROR(J28/J$4,0) -> 0.055917382 | K29: =IFERROR(K28/K$4,0) -> 0.055613989 | L29: =IFERROR(L28/L$4,0) -> 0.055409922 | M29: =IFERROR(M28/M$4,0) -> 0 | N29: =IFERROR(N28/N$4,0) -> 0 | O29: =IFERROR(O28/O$4,0) -> 0 | ... Q29: =IFERROR(Q28/Q$4,0) -> 0
B31: =Assumptions!B172 -> Income Tax Expense (Benefit) | C31: =Assumptions!D172 -> 396 | D31: =Assumptions!E172 -> 593 | E31: =Assumptions!F172 -> 981 | F31: =Assumptions!G172 -> 900 | G31: =Assumptions!H172 -> -29 | H31: =H28*Assumptions!I174 -> 612.95448 | I31: =I28*Assumptions!J174 -> 609.50862 | J31: =J28*Assumptions!K174 -> 602.51986 | K31: =K28*Assumptions!L174 -> 593.25824 | L31: =L28*Assumptions!M174 -> 585.17056 | M31: =M28*Assumptions!N174 -> 0 | N31: =N28*Assumptions!O174 -> 0 | O31: =O28*Assumptions!P174 -> 0 | ... Q31: =Q28*Assumptions!R174 -> 0
B32: ="% of "&$B$4 -> % of Revenue | C32: =IFERROR(C31/C$4,0) -> 0.0093385214 | D32: =D31/D$4 -> 0.01373162 | E32: =E31/E$4 -> 0.020850603 | F32: =F31/F$4 -> 0.016891258 | G32: =G31/G$4 -> -0.00054840113 | H32: =IFERROR(H31/H$4,0) -> 0.011708287 | I32: =IFERROR(I31/I$4,0) -> 0.011760067 | J32: =IFERROR(J31/J$4,0) -> 0.01174265 | K32: =IFERROR(K31/K$4,0) -> 0.011678938 | L32: =IFERROR(L31/L$4,0) -> 0.011636084 | M32: =IFERROR(M31/M$4,0) -> 0 | N32: =IFERROR(N31/N$4,0) -> 0 | O32: =IFERROR(O31/O$4,0) -> 0 | ... Q32: =IFERROR(Q31/Q$4,0) -> 0
B34: =Assumptions!B177 -> Miscellaneous After Tax Expenditures | C34: =Assumptions!D177 -> 13 | D34: =Assumptions!E177 -> 10 | E34: =Assumptions!F177 -> 13 | F34: =Assumptions!G177 -> 11 | G34: =Assumptions!H177 -> -1 | H34: =H$4*H35 -> 10.491122 | I34: =I$4*I35 -> 10.386211 | J34: =J$4*J35 -> 10.282349 | K34: =K$4*K35 -> 10.179526 | L34: =L$4*L35 -> 10.07773 | M34: =M$4*M35 -> 0 | N34: =N$4*N35 -> 0 | O34: =O$4*O35 -> 0 | ... Q34: =Q$4*Q35 -> 0
B35: ="% of "&$B$4 -> % of Revenue | C35: =IFERROR(C34/C$4,0) -> 0.00030656762 | D35: =D34/D$4 -> 0.00023156188 | E35: =E34/E$4 -> 0.00027630768 | F35: =F34/F$4 -> 0.00020644871 | G35: =G34/G$4 -> -1.8910384e-05 | H35: =Assumptions!I178 -> 0.0002003951 | I35: =Assumptions!J178 -> 0.0002003951 | J35: =Assumptions!K178 -> 0.0002003951 | K35: =Assumptions!L178 -> 0.0002003951 | L35: =Assumptions!M178 -> 0.0002003951 | M35: =Assumptions!N178 -> 0 | N35: =Assumptions!O178 -> 0 | O35: =Assumptions!P178 -> 0 | ... Q35: =Assumptions!R178 -> 0
B37: Net Income (Loss), GAAP | C37: =C28-C31-C34 -> 2022 | D37: =D28-D31-D34 -> 2061 | E37: =E28-E31-E34 -> 3047 | F37: =F28-F31-F34 -> 3238 | G37: =G28-G31-G34 -> -648 | H37: =H28-H31-H34 -> 2295.3852 | I37: =I28-I31-I34 -> 2282.5272 | J37: =J28-J31-J34 -> 2256.34 | ... Q37: =Q28-Q31-Q34 -> 0
B38: ="% of "&$B$4 -> % of Revenue | C38: =IFERROR(C37/C$4,0) -> 0.047683056 | D38: =D37/D$4 -> 0.047724904 | E38: =E37/E$4 -> 0.064762269 | F38: =F37/F$4 -> 0.060770992 | G38: =G37/G$4 -> -0.012253929 | H38: =IFERROR(H37/H$4,0) -> 0.043845066 | I38: =IFERROR(I37/I$4,0) -> 0.044039858 | J38: =IFERROR(J37/J$4,0) -> 0.043974337 | K38: =IFERROR(K37/K$4,0) -> 0.043734656 | L38: =IFERROR(L37/L$4,0) -> 0.043573443 | M38: =IFERROR(M37/M$4,0) -> 0 | N38: =IFERROR(N37/N$4,0) -> 0 | O38: =IFERROR(O37/O$4,0) -> 0 | ... Q38: =IFERROR(Q37/Q$4,0) -> 0
B39: Year over Year Growth % | D39: =D37/C37-1 -> 0.019287834 | E39: =E37/D37-1 -> 0.47840854 | F39: =F37/E37-1 -> 0.062684608 | G39: =G37/F37-1 -> -1.2001235 | H39: =IF(H$3="",0,H37/G37-1) -> -4.5422612 | I39: =IF(I$3="",0,I37/H37-1) -> -0.0056017082 | J39: =IF(J$3="",0,J37/I37-1) -> -0.011472888 | K39: =IF(K$3="",0,K37/J37-1) -> -0.015395959 | L39: =IF(L$3="",0,L37/K37-1) -> -0.0136493 | M39: =IF(M$3="",0,M37/L37-1) -> 0 | N39: =IF(N$3="",0,N37/M37-1) -> 0 | O39: =IF(O$3="",0,O37/N37-1) -> 0 | ... Q39: =IF(Q$3="",0,Q37/P37-1) -> 0
B42: EBITDA Calculation
B43: =B$22 -> Operating Income (Loss) ~ EBIT | C43: =C$22 -> 3063 | D43: =D$22 -> 2903 | E43: =E$22 -> 4248 | F43: =F$22 -> 4362 | G43: =G$22 -> 894 | H43: =H$22 -> 3439.7011 | I43: =I$22 -> 3405.3041 | ... Q43: =Q$22 -> 0
B44: =Assumptions!B187 -> Capital Expenditures | C44: =Assumptions!D187 -> 1259 | D44: =Assumptions!E187 -> 1199 | E44: =Assumptions!F187 -> 1209 | F44: =Assumptions!G187 -> 1887 | G44: =Assumptions!H187 -> 1939 | H44: =H4*H45 -> 1625.3612 | I44: =I4*I45 -> 1609.1076 | J44: =J4*J45 -> 1593.0165 | K44: =K4*K45 -> 1577.0863 | L44: =L4*L45 -> 1561.3155 | M44: =M4*M45 -> 0 | N44: =N4*N45 -> 0 | O44: =O4*O45 -> 0 | ... Q44: =Q4*Q45 -> 0
B45: ="% of "&$B$4 -> % of Revenue | C45: =IFERROR(C44/C$4,0) -> 0.029689895 | D45: =D44/D$4 -> 0.02776427 | E45: =E44/E$4 -> 0.025696614 | F45: =F44/F$4 -> 0.035415337 | G45: =G44/G$4 -> 0.036667234 | H45: =Assumptions!I$188 -> 0.03104667 | I45: =Assumptions!J188 -> 0.03104667 | J45: =Assumptions!K188 -> 0.03104667 | K45: =Assumptions!L188 -> 0.03104667 | L45: =Assumptions!M188 -> 0.03104667 | M45: =Assumptions!N188 -> 0 | N45: =Assumptions!O188 -> 0 | O45: =Assumptions!P188 -> 0 | P45: =Assumptions!Q188 -> 0 | Q45: =Assumptions!R188 -> 0
B47: =Assumptions!B191 -> Depreciation and Amortization | C47: =Assumptions!D191 -> 1098 | D47: =Assumptions!E191 -> 1192 | E47: =Assumptions!F191 -> 1214 | F47: =Assumptions!G191 -> 1202 | G47: =Assumptions!H191 -> 1339 | H47: =H44*H49 -> 1364.6436 | I47: =I44*I49 -> 1350.9971 | J47: =J44*J49 -> 1337.4872 | K47: =K44*K49 -> 1324.1123 | L47: =L44*L49 -> 1310.8712 | M47: =M44*M49 -> 0 | N47: =N44*N49 -> 0 | O47: =O44*O49 -> 0 | ... Q47: =Q44*Q49 -> 0
B48: ="% of "&$B$4 -> % of Revenue | C48: =IFERROR(C47/C$4,0) -> 0.025893173 | D48: =D47/D$4 -> 0.027602177 | E48: =E47/E$4 -> 0.025802886 | F48: =F47/F$4 -> 0.022559213 | G48: =G47/G$4 -> 0.025321004 | H48: =IFERROR(H47/H$4,0) -> 0.0260666 | I48: =IFERROR(I47/I$4,0) -> 0.0260666 | J48: =IFERROR(J47/J$4,0) -> 0.0260666 | K48: =IFERROR(K47/K$4,0) -> 0.0260666 | L48: =IFERROR(L47/L$4,0) -> 0.0260666 | M48: =IFERROR(M47/M$4,0) -> 0 | N48: =IFERROR(N47/N$4,0) -> 0 | O48: =IFERROR(O47/O$4,0) -> 0 | ... Q48: =IFERROR(Q47/Q$4,0) -> 0
B49: ="% of "&B44 -> % of Capital Expenditures | C49: =IFERROR(C47/C44,0) -> 0.87212073 | D49: =IFERROR(D47/D44,0) -> 0.9941618 | E49: =IFERROR(E47/E44,0) -> 1.0041356 | F49: =IFERROR(F47/F44,0) -> 0.63698993 | G49: =IFERROR(G47/G44,0) -> 0.69056215 | H49: =Assumptions!I$192 -> 0.83959405 | I49: =Assumptions!J$192 -> 0.83959405 | J49: =Assumptions!K$192 -> 0.83959405 | K49: =Assumptions!L$192 -> 0.83959405 | L49: =Assumptions!M$192 -> 0.83959405 | M49: =Assumptions!N$192 -> 0 | N49: =Assumptions!O$192 -> 0 | O49: =Assumptions!P$192 -> 0 | ... Q49: =Assumptions!R$192 -> 0
B51: =_xlfn.TEXTBEFORE(Assumptions!B195," [") -> Cost of Capitalized Leases | C51: =Assumptions!D195 -> 0 | D51: =Assumptions!E195 -> 0 | E51: =Assumptions!F195 -> 0 | F51: =Assumptions!G195 -> 0 | G51: =Assumptions!H195 -> 0 | H51: =H$4*H52 -> 0 | I51: =I$4*I52 -> 0 | J51: =J$4*J52 -> 0 | K51: =K$4*K52 -> 0 | L51: =L$4*L52 -> 0 | M51: =M$4*M52 -> 0 | N51: =N$4*N52 -> 0 | O51: =O$4*O52 -> 0 | ... Q51: =Q$4*Q52 -> 0
B52: ="% of "&$B$4 -> % of Revenue | C52: =IFERROR(C51/C$4,0) -> 0 | D52: =D51/D$4 -> 0 | E52: =E51/E$4 -> 0 | F52: =F51/F$4 -> 0 | G52: =G51/G$4 -> 0 | H52: =+Assumptions!I196 -> 0 | I52: =+Assumptions!J196 -> 0 | J52: =+Assumptions!K196 -> 0 | K52: =+Assumptions!L196 -> 0 | L52: =+Assumptions!M196 -> 0 | M52: =+Assumptions!N196 -> 0 | N52: =+Assumptions!O196 -> 0 | O52: =+Assumptions!P196 -> 0 | ... Q52: =+Assumptions!R196 -> 0
B53: EBITDA | C53: =SUM(C43,C47,C51) -> 4161 | D53: =SUM(D43,D47,D51) -> 4095 | E53: =SUM(E43,E47,E51) -> 5462 | F53: =SUM(F43,F47,F51) -> 5564 | G53: =SUM(G43,G47,G51) -> 2233 | H53: =SUM(H43,H47,H51) -> 4804.3446 | I53: =SUM(I43,I47,I51) -> 4756.3012 | J53: =SUM(J43,J47,J51) -> 4708.7382 | ... Q53: =SUM(Q43,Q47,Q51) -> 0
B56: NOPAT Calculation
B57: =B$22 -> Operating Income (Loss) ~ EBIT | C57: =C$22 -> 3063 | D57: =D$22 -> 2903 | E57: =E$22 -> 4248 | F57: =F$22 -> 4362 | G57: =G$22 -> 894 | H57: =H$22 -> 3439.7011 | I57: =I$22 -> 3405.3041 | ... Q57: =Q$22 -> 0
B58: =B$31 -> Income Tax Expense (Benefit) | C58: =C$31 -> 396 | D58: =D$31 -> 593 | E58: =E$31 -> 981 | F58: =F$31 -> 900 | G58: =G$31 -> -29 | H58: =H$31 -> 612.95448 | I58: =I$31 -> 609.50862 | ... Q58: =Q$31 -> 0
B59: Net Profit After Tax - NOPAT | C59: =C57-C58 -> 2667 | D59: =D57-D58 -> 2310 | E59: =E57-E58 -> 3267 | F59: =F57-F58 -> 3462 | G59: =G57-G58 -> 923 | H59: =H57-H58 -> 2826.7466 | I59: =I57-I58 -> 2795.7954 | J59: =J57-J58 -> 2768.7312 | ... Q59: =Q57-Q58 -> 0

Sheet IS Bull
B2: Income Statement - Bear
B3: =Assumptions!$B$132 -> Year Ending 09/31/2024, In USD Millions | C3: {=_xlfn.SEQUENCE(1,5+Assumptions!$C$20,(YEAR('Valuation Summary'!$C$4)-5))} -> 2019 | D3: 2020 | E3: 2021 | F3: 2022 | G3: 2023 | H3: 2024 | I3: 2025 | J3: 2026 | K3: 2027 | L3: 2028
B4: =Assumptions!B136 -> Revenue | C4: =Assumptions!D136 -> 42405 | D4: =Assumptions!E136 -> 43185 | E4: =Assumptions!F136 -> 47049 | F4: =Assumptions!G136 -> 53282 | G4: =Assumptions!H136 -> 52881 | H4: =IF(H3="",0,G4*(1+H6)) -> 54467.43 | I4: =IF(I3="",0,H4*(1+I6)) -> 56101.453 | J4: =IF(J3="",0,I4*(1+J6)) -> 57784.496 | K4: =IF(K3="",0,J4*(1+K6)) -> 59518.031 | L4: =IF(L3="",0,K4*(1+L6)) -> 61303.572 | M4: =IF(M3="",0,L4*(1+M6)) -> 0 | N4: =IF(N3="",0,M4*(1+N6)) -> 0 | O4: =IF(O3="",0,N4*(1+O6)) -> 0 | ... Q4: =IF(Q3="",0,P4*(1+Q6)) -> 0
B5: ="% of "&$B$4 -> % of Revenue | C5: =IFERROR(C4/C$4,0) -> 1 | D5: =D4/D$4 -> 1 | E5: =E4/E$4 -> 1 | F5: =F4/F$4 -> 1 | G5: =G4/G$4 -> 1 | H5: =IFERROR(H4/H$4,0) -> 1 | I5: =IFERROR(I4/I$4,0) -> 1 | J5: =IFERROR(J4/J$4,0) -> 1 | K5: =IFERROR(K4/K$4,0) -> 1 | L5: =IFERROR(L4/L$4,0) -> 1 | M5: =IFERROR(M4/M$4,0) -> 0 | N5: =IFERROR(N4/N$4,0) -> 0 | O5: =IFERROR(O4/O$4,0) -> 0 | ... Q5: =IFERROR(Q4/Q$4,0) -> 0
B6: Year over Year Growth % | D6: =D4/C4-1 -> 0.018394057 | E6: =E4/D4-1 -> 0.089475512 | F6: =F4/E4-1 -> 0.1324789 | G6: =G4/F4-1 -> -0.0075259938 | H6: =Assumptions!I$139 -> 0.03 | I6: =Assumptions!J$139 -> 0.03 | J6: =Assumptions!K$139 -> 0.03 | K6: =Assumptions!L$139 -> 0.03 | L6: =Assumptions!M$139 -> 0.03 | M6: =Assumptions!N$139 -> 0 | N6: =Assumptions!O$139 -> 0 | O6: =Assumptions!P$139 -> 0 | ... Q6: =Assumptions!R$139 -> 0
B8: =Assumptions!B142 -> Cost of Revenue ~ Cost of Goods Sold | C8: =Assumptions!D142 -> 37383 | D8: =Assumptions!E142 -> 37801 | E8: =Assumptions!F142 -> 40523 | F8: =Assumptions!G142 -> 46614 | G8: =Assumptions!H142 -> 50250 | H8: =H$4*H9 -> 48402.945 | I8: =I$4*I9 -> 49855.033 | J8: =J$4*J9 -> 51350.684 | K8: =K$4*K9 -> 52891.205 | L8: =L$4*L9 -> 54477.941 | M8: =M$4*M9 -> 0 | N8: =N$4*N9 -> 0 | O8: =O$4*O9 -> 0 | ... Q8: =Q$4*Q9 -> 0
B9: ="% of "&$B$4 -> % of Revenue | C9: =IFERROR(C8/C$4,0) -> 0.88157057 | D9: =D8/D$4 -> 0.87532708 | E9: =E8/E$4 -> 0.86129355 | F9: =F8/F$4 -> 0.87485455 | G9: =G8/G$4 -> 0.95024678 | H9: =Assumptions!I$143 -> 0.8886585 | I9: =Assumptions!J$143 -> 0.8886585 | J9: =Assumptions!K$143 -> 0.8886585 | K9: =Assumptions!L$143 -> 0.8886585 | L9: =Assumptions!M$143 -> 0.8886585 | M9: =Assumptions!N$143 -> 0 | N9: =Assumptions!O$143 -> 0 | O9: =Assumptions!P$143 -> 0 | ... Q9: =Assumptions!R$143 -> 0
B10: Year over Year Growth % | D10: {=D8/C8-1} -> 0.011181553 | E10: {=E8/D8-1} -> 0.072008677 | F10: {=F8/E8-1} -> 0.1503097 | G10: {=G8/F8-1} -> 0.078002317 | H10: =IF(H$3="",0,H8/G8-1) -> -0.036757315 | I10: =IF(I$3="",0,I8/H8-1) -> 0.03 | J10: =IF(J$3="",0,J8/I8-1) -> 0.03 | K10: =IF(K$3="",0,K8/J8-1) -> 0.03 | L10: =IF(L$3="",0,L8/K8-1) -> 0.03 | M10: =IF(M$3="",0,M8/L8-1) -> 0 | N10: =IF(N$3="",0,N8/M8-1) -> 0 | O10: =IF(O$3="",0,O8/N8-1) -> 0 | ... Q10: =IF(Q$3="",0,Q8/P8-1) -> 0
B12: Gross Profit | C12: =C4-C8 -> 5022 | D12: =D4-D8 -> 5384 | E12: =E4-E8 -> 6526 | F12: =F4-F8 -> 6668 | G12: =G4-G8 -> 2631 | H12: =H4-H8 -> 6064.4851 | I12: =I4-I8 -> 6246.4197 | J12: =J4-J8 -> 6433.8122 | ... Q12: =Q4-Q8 -> 0
B13: ="% of "&$B$4 -> % of Revenue | C13: =IFERROR(C12/C$4,0) -> 0.11842943 | D13: =D12/D$4 -> 0.12467292 | E13: =E12/E$4 -> 0.13870645 | F13: =F12/F$4 -> 0.12514545 | G13: =G12/G$4 -> 0.049753219 | H13: =IFERROR(H12/H$4,0) -> 0.1113415 | I13: =IFERROR(I12/I$4,0) -> 0.1113415 | J13: =IFERROR(J12/J$4,0) -> 0.1113415 | K13: =IFERROR(K12/K$4,0) -> 0.1113415 | L13: =IFERROR(L12/L$4,0) -> 0.1113415 | M13: =IFERROR(M12/M$4,0) -> 0 | N13: =IFERROR(N12/N$4,0) -> 0 | O13: =IFERROR(O12/O$4,0) -> 0 | ... Q13: =IFERROR(Q12/Q$4,0) -> 0
B14: Year over Year Growth % | D14: =D12/C12-1 -> 0.072082836 | E14: =E12/D12-1 -> 0.21210996 | F14: =F12/E12-1 -> 0.021759117 | G14: =G12/F12-1 -> -0.60542891 | H14: =IF(H3="",0,H12/G12-1) -> 1.3050114 | I14: =IF(I3="",0,I12/H12-1) -> 0.03 | J14: =IF(J3="",0,J12/I12-1) -> 0.03 | K14: =IF(K3="",0,K12/J12-1) -> 0.03 | L14: =IF(L3="",0,L12/K12-1) -> 0.03 | M14: =IF(M3="",0,M12/L12-1) -> 0 | N14: =IF(N3="",0,N12/M12-1) -> 0 | O14: =IF(O3="",0,O12/N12-1) -> 0 | ... Q14: =IF(Q3="",0,Q12/P12-1) -> 0
B16: =Assumptions!B146 -> Other Operating Income | C16: =Assumptions!D146 -> 0 | D16: =Assumptions!E146 -> 0 | E16: =Assumptions!F146 -> 0 | F16: =Assumptions!G146 -> 0 | G16: =Assumptions!H146 -> 0 | H16: =H$4*H17 -> 0 | I16: =I$4*I17 -> 0 | J16: =J$4*J17 -> 0 | K16: =K$4*K17 -> 0 | L16: =L$4*L17 -> 0 | M16: =M$4*M17 -> 0 | N16: =N$4*N17 -> 0 | O16: =O$4*O17 -> 0 | ... Q16: =Q$4*Q17 -> 0
B17: ="% of "&$B$4 -> % of Revenue | C17: =IFERROR(C16/C$4,0) -> 0 | D17: =D16/D$4 -> 0 | E17: =E16/E$4 -> 0 | F17: =F16/F$4 -> 0 | G17: =G16/G$4 -> 0 | H17: =Assumptions!I$147 -> 0 | I17: =Assumptions!J$147 -> 0 | J17: =Assumptions!K$147 -> 0 | K17: =Assumptions!L$147 -> 0 | L17: =Assumptions!M$147 -> 0 | M17: =Assumptions!N$147 -> 0 | N17: =Assumptions!O$147 -> 0 | O17: =Assumptions!P$147 -> 0 | ... Q17: =Assumptions!R$147 -> 0
B19: =Assumptions!B150 -> Operating Expenses | C19: =Assumptions!D150 -> 1959 | D19: =Assumptions!E150 -> 2481 | E19: =Assumptions!F150 -> 2278 | F19: =Assumptions!G150 -> 2306 | G19: =Assumptions!H150 -> 1737 | H19: =H$4*H20 -> 2485.8062 | I19: =I$4*I20 -> 2560.3804 | J19: =J$4*J20 -> 2637.1918 | K19: =K$4*K20 -> 2716.3076 | L19: =L$4*L20 -> 2797.7968 | M19: =M$4*M20 -> 0 | N19: =N$4*N20 -> 0 | O19: =O$4*O20 -> 0 | ... Q19: =Q$4*Q20 -> 0
B20: ="% of "&$B$4 -> % of Revenue | C20: =IFERROR(C19/C$4,0) -> 0.046197382 | D20: =D19/D$4 -> 0.057450504 | E20: =E19/E$4 -> 0.048417607 | F20: =F19/F$4 -> 0.043279156 | G20: =G19/G$4 -> 0.032847336 | H20: =Assumptions!I$151 -> 0.045638397 | I20: =Assumptions!J$151 -> 0.045638397 | J20: =Assumptions!K$151 -> 0.045638397 | K20: =Assumptions!L$151 -> 0.045638397 | L20: =Assumptions!M$151 -> 0.045638397 | M20: =Assumptions!N$151 -> 0 | N20: =Assumptions!O$151 -> 0 | O20: =Assumptions!P$151 -> 0 | ... Q20: =Assumptions!R$151 -> 0
B22: Operating Income (Loss) ~ EBIT | C22: =C12+C16-C19 -> 3063 | D22: =D12+D16-D19 -> 2903 | E22: =E12+E16-E19 -> 4248 | F22: =F12+F16-F19 -> 4362 | G22: =G12+G16-G19 -> 894 | H22: =H12+H16-H19 -> 3578.6789 | I22: =I12+I16-I19 -> 3686.0393 | J22: =J12+J16-J19 -> 3796.6204 | ... Q22: =Q12+Q16-Q19 -> 0
B23: ="% of "&$B$4 -> % of Revenue | C23: =IFERROR(C22/C$4,0) -> 0.072232048 | D23: =D22/D$4 -> 0.067222415 | E23: =E22/E$4 -> 0.090288848 | F23: =F22/F$4 -> 0.081866296 | G23: =G22/G$4 -> 0.016905883 | H23: =IFERROR(H22/H$4,0) -> 0.065703098 | I23: =IFERROR(I22/I$4,0) -> 0.065703098 | J23: =IFERROR(J22/J$4,0) -> 0.065703098 | K23: =IFERROR(K22/K$4,0) -> 0.065703098 | L23: =IFERROR(L22/L$4,0) -> 0.065703098 | M23: =IFERROR(M22/M$4,0) -> 0 | N23: =IFERROR(N22/N$4,0) -> 0 | O23: =IFERROR(O22/O$4,0) -> 0 | ... Q23: =IFERROR(Q22/Q$4,0) -> 0
B25: =Assumptions!B154 -> Non-Operating (Income) Loss | C25: =Assumptions!D154 -> 632 | D25: =Assumptions!E154 -> 239 | E25: =Assumptions!F154 -> 207 | F25: =Assumptions!G154 -> 213 | G25: =Assumptions!H154 -> 1572 | H25: =+Assumptions!I$154+H4*Assumptions!$I$167+H4*Assumptions!I$169 -> 527.35296 | I25: =+Assumptions!J$154+I4*Assumptions!$I$167+I4*Assumptions!J$169 -> 515.97718 | J25: =+Assumptions!K$154+J4*Assumptions!$I$167+J4*Assumptions!K$169 -> 521.95052 | K25: =+Assumptions!L$154+K4*Assumptions!$I$167+K4*Assumptions!L$169 -> 539.22641 | L25: =+Assumptions!M$154+L4*Assumptions!$I$167+L4*Assumptions!M$169 -> 551.39291 | M25: =+Assumptions!N$154+M4*Assumptions!$I$167+M4*Assumptions!N$169 -> 0 | N25: =+Assumptions!O$154+N4*Assumptions!$I$167+N4*Assumptions!O$169 -> 0 | O25: =+Assumptions!P$154+O4*Assumptions!$I$167+O4*Assumptions!P$169 -> 0 | ... Q25: =+Assumptions!R$154+Q4*Assumptions!$I$167+Q4*Assumptions!R$169 -> 0
B26: ="% of "&$B$4 -> % of Revenue | C26: =IFERROR(C25/C$4,0) -> 0.014903903 | D26: =D25/D$4 -> 0.005534329 | E26: =E25/E$4 -> 0.0043996684 | F26: =F25/F$4 -> 0.0039975977 | G26: =G25/G$4 -> 0.029727123 | H26: =IFERROR(H25/H$4,0) -> 0.0096819871 | I26: =IFERROR(I25/I$4,0) -> 0.009197216 | J26: =IFERROR(J25/J$4,0) -> 0.0090327086 | K26: =IFERROR(K25/K$4,0) -> 0.0090598832 | L26: =IFERROR(L25/L$4,0) -> 0.0089944662 | M26: =IFERROR(M25/M$4,0) -> 0 | N26: =IFERROR(N25/N$4,0) -> 0 | O26: =IFERROR(O25/O$4,0) -> 0 | ... Q26: =IFERROR(Q25/Q$4,0) -> 0
B28: Pretax Income (Loss), GAAP ~ EBT | C28: =C22-C25 -> 2431 | D28: =D22-D25 -> 2664 | E28: =E22-E25 -> 4041 | F28: =F22-F25 -> 4149 | G28: =G22-G25 -> -678 | H28: =H22-H25 -> 3051.3259 | I28: =I22-I25 -> 3170.0621 | J28: =J22-J25 -> 3274.6699 | ... Q28: =Q22-Q25 -> 0
B29: ="% of "&$B$4 -> % of Revenue | C29: =IFERROR(C28/C$4,0) -> 0.057328145 | D29: =D28/D$4 -> 0.061688086 | E29: =E28/E$4 -> 0.085889179 | F29: =F28/F$4 -> 0.077868699 | G29: =G28/G$4 -> -0.01282124 | H29: =IFERROR(H28/H$4,0) -> 0.056021111 | I29: =IFERROR(I28/I$4,0) -> 0.056505882 | J29: =IFERROR(J28/J$4,0) -> 0.056670389 | K29: =IFERROR(K28/K$4,0) -> 0.056643215 | L29: =IFERROR(L28/L$4,0) -> 0.056708632 | M29: =IFERROR(M28/M$4,0) -> 0 | N29: =IFERROR(N28/N$4,0) -> 0 | O29: =IFERROR(O28/O$4,0) -> 0 | ... Q29: =IFERROR(Q28/Q$4,0) -> 0
B31: =Assumptions!B172 -> Income Tax Expense (Benefit) | C31: =Assumptions!D172 -> 396 | D31: =Assumptions!E172 -> 593 | E31: =Assumptions!F172 -> 981 | F31: =Assumptions!G172 -> 900 | G31: =Assumptions!H172 -> -29 | H31: =H28*Assumptions!I174 -> 640.77845 | I31: =I28*Assumptions!J174 -> 665.71304 | J31: =J28*Assumptions!K174 -> 687.68068 | K31: =K28*Assumptions!L174 -> 707.97146 | L31: =L28*Assumptions!M174 -> 730.05276 | M31: =M28*Assumptions!N174 -> 0 | N31: =N28*Assumptions!O174 -> 0 | O31: =O28*Assumptions!P174 -> 0 | ... Q31: =Q28*Assumptions!R174 -> 0
B32: ="% of "&$B$4 -> % of Revenue | C32: =IFERROR(C31/C$4,0) -> 0.0093385214 | D32: =D31/D$4 -> 0.01373162 | E32: =E31/E$4 -> 0.020850603 | F32: =F31/F$4 -> 0.016891258 | G32: =G31/G$4 -> -0.00054840113 | H32: =IFERROR(H31/H$4,0) -> 0.011764433 | I32: =IFERROR(I31/I$4,0) -> 0.011866235 | J32: =IFERROR(J31/J$4,0) -> 0.011900782 | K32: =IFERROR(K31/K$4,0) -> 0.011895075 | L32: =IFERROR(L31/L$4,0) -> 0.011908813 | M32: =IFERROR(M31/M$4,0) -> 0 | N32: =IFERROR(N31/N$4,0) -> 0 | O32: =IFERROR(O31/O$4,0) -> 0 | ... Q32: =IFERROR(Q31/Q$4,0) -> 0
B34: =Assumptions!B177 -> Miscellaneous After Tax Expenditures | C34: =Assumptions!D177 -> 13 | D34: =Assumptions!E177 -> 10 | E34: =Assumptions!F177 -> 13 | F34: =Assumptions!G177 -> 11 | G34: =Assumptions!H177 -> -1 | H34: =H$4*H35 -> 10.915006 | I34: =I$4*I35 -> 11.242456 | J34: =J$4*J35 -> 11.57973 | K34: =K$4*K35 -> 11.927122 | L34: =L$4*L35 -> 12.284936 | M34: =M$4*M35 -> 0 | N34: =N$4*N35 -> 0 | O34: =O$4*O35 -> 0 | ... Q34: =Q$4*Q35 -> 0
B35: ="% of "&$B$4 -> % of Revenue | C35: =IFERROR(C34/C$4,0) -> 0.00030656762 | D35: =D34/D$4 -> 0.00023156188 | E35: =E34/E$4 -> 0.00027630768 | F35: =F34/F$4 -> 0.00020644871 | G35: =G34/G$4 -> -1.8910384e-05 | H35: =Assumptions!I178 -> 0.0002003951 | I35: =Assumptions!J178 -> 0.0002003951 | J35: =Assumptions!K178 -> 0.0002003951 | K35: =Assumptions!L178 -> 0.0002003951 | L35: =Assumptions!M178 -> 0.0002003951 | M35: =Assumptions!N178 -> 0 | N35: =Assumptions!O178 -> 0 | O35: =Assumptions!P178 -> 0 | ... Q35: =Assumptions!R178 -> 0
B37: Net Income (Loss), GAAP | C37: =C28-C31-C34 -> 2022 | D37: =D28-D31-D34 -> 2061 | E37: =E28-E31-E34 -> 3047 | F37: =F28-F31-F34 -> 3238 | G37: =G28-G31-G34 -> -648 | H37: =H28-H31-H34 -> 2399.6325 | I37: =I28-I31-I34 -> 2493.1066 | J37: =J28-J31-J34 -> 2575.4095 | ... Q37: =Q28-Q31-Q34 -> 0
B38: ="% of "&$B$4 -> % of Revenue | C38: =IFERROR(C37/C$4,0) -> 0.047683056 | D38: =D37/D$4 -> 0.047724904 | E38: =E37/E$4 -> 0.064762269 | F38: =F37/F$4 -> 0.060770992 | G38: =G37/G$4 -> -0.012253929 | H38: =IFERROR(H37/H$4,0) -> 0.044056283 | I38: =IFERROR(I37/I$4,0) -> 0.044439252 | J38: =IFERROR(J37/J$4,0) -> 0.044569213 | K38: =IFERROR(K37/K$4,0) -> 0.044547745 | L38: =IFERROR(L37/L$4,0) -> 0.044599424 | M38: =IFERROR(M37/M$4,0) -> 0 | N38: =IFERROR(N37/N$4,0) -> 0 | O38: =IFERROR(O37/O$4,0) -> 0 | ... Q38: =IFERROR(Q37/Q$4,0) -> 0
B39: Year over Year Growth % | D39: =D37/C37-1 -> 0.019287834 | E39: =E37/D37-1 -> 0.47840854 | F39: =F37/E37-1 -> 0.062684608 | G39: =G37/F37-1 -> -1.2001235 | H39: =IF(H$3="",0,H37/G37-1) -> -4.7031366 | I39: =IF(I$3="",0,I37/H37-1) -> 0.038953508 | J39: =IF(J$3="",0,J37/I37-1) -> 0.033012195 | K39: =IF(K$3="",0,K37/J37-1) -> 0.029503874 | L39: =IF(L$3="",0,L37/K37-1) -> 0.031194893 | M39: =IF(M$3="",0,M37/L37-1) -> 0 | N39: =IF(N$3="",0,N37/M37-1) -> 0 | O39: =IF(O$3="",0,O37/N37-1) -> 0 | ... Q39: =IF(Q$3="",0,Q37/P37-1) -> 0
B42: EBITDA Calculation
B43: =B$22 -> Operating Income (Loss) ~ EBIT | C43: =C$22 -> 3063 | D43: =D$22 -> 2903 | E43: =E$22 -> 4248 | F43: =F$22 -> 4362 | G43: =G$22 -> 894 | H43: =H$22 -> 3578.6789 | I43: =I$22 -> 3686.0393 | ... Q43: =Q$22 -> 0
B44: =Assumptions!B187 -> Capital Expenditures | C44: =Assumptions!D187 -> 1259 | D44: =Assumptions!E187 -> 1199 | E44: =Assumptions!F187 -> 1209 | F44: =Assumptions!G187 -> 1887 | G44: =Assumptions!H187 -> 1939 | H44: =H4*H45 -> 1691.0323 | I44: =I4*I45 -> 1741.7633 | J44: =J4*J45 -> 1794.0162 | K44: =K4*K45 -> 1847.8367 | L44: =L4*L45 -> 1903.2718 | M44: =M4*M45 -> 0 | N44: =N4*N45 -> 0 | O44: =O4*O45 -> 0 | ... Q44: =Q4*Q45 -> 0
B45: ="% of "&$B$4 -> % of Revenue | C45: =IFERROR(C44/C$4,0) -> 0.029689895 | D45: =D44/D$4 -> 0.02776427 | E45: =E44/E$4 -> 0.025696614 | F45: =F44/F$4 -> 0.035415337 | G45: =G44/G$4 -> 0.036667234 | H45: =Assumptions!I$188 -> 0.03104667 | I45: =Assumptions!J188 -> 0.03104667 | J45: =Assumptions!K188 -> 0.03104667 | K45: =Assumptions!L188 -> 0.03104667 | L45: =Assumptions!M188 -> 0.03104667 | M45: =Assumptions!N188 -> 0 | N45: =Assumptions!O188 -> 0 | O45: =Assumptions!P188 -> 0 | P45: =Assumptions!Q188 -> 0 | Q45: =Assumptions!R188 -> 0
B47: =Assumptions!B191 -> Depreciation and Amortization | C47: =Assumptions!D191 -> 1098 | D47: =Assumptions!E191 -> 1192 | E47: =Assumptions!F191 -> 1214 | F47: =Assumptions!G191 -> 1202 | G47: =Assumptions!H191 -> 1339 | H47: =H44*H49 -> 1419.7807 | I47: =I44*I49 -> 1462.3741 | J47: =J44*J49 -> 1506.2453 | K47: =K44*K49 -> 1551.4327 | L47: =L44*L49 -> 1597.9757 | M47: =M44*M49 -> 0 | N47: =N44*N49 -> 0 | O47: =O44*O49 -> 0 | ... Q47: =Q44*Q49 -> 0
B48: ="% of "&$B$4 -> % of Revenue | C48: =IFERROR(C47/C$4,0) -> 0.025893173 | D48: =D47/D$4 -> 0.027602177 | E48: =E47/E$4 -> 0.025802886 | F48: =F47/F$4 -> 0.022559213 | G48: =G47/G$4 -> 0.025321004 | H48: =IFERROR(H47/H$4,0) -> 0.0260666 | I48: =IFERROR(I47/I$4,0) -> 0.0260666 | J48: =IFERROR(J47/J$4,0) -> 0.0260666 | K48: =IFERROR(K47/K$4,0) -> 0.0260666 | L48: =IFERROR(L47/L$4,0) -> 0.0260666 | M48: =IFERROR(M47/M$4,0) -> 0 | N48: =IFERROR(N47/N$4,0) -> 0 | O48: =IFERROR(O47/O$4,0) -> 0 | ... Q48: =IFERROR(Q47/Q$4,0) -> 0
B49: ="% of "&B44 -> % of Capital Expenditures | C49: =IFERROR(C47/C44,0) -> 0.87212073 | D49: =IFERROR(D47/D44,0) -> 0.9941618 | E49: =IFERROR(E47/E44,0) -> 1.0041356 | F49: =IFERROR(F47/F44,0) -> 0.63698993 | G49: =IFERROR(G47/G44,0) -> 0.69056215 | H49: =Assumptions!I$192 -> 0.83959405 | I49: =Assumptions!J$192 -> 0.83959405 | J49: =Assumptions!K$192 -> 0.83959405 | K49: =Assumptions!L$192 -> 0.83959405 | L49: =Assumptions!M$192 -> 0.83959405 | M49: =Assumptions!N$192 -> 0 | N49: =Assumptions!O$192 -> 0 | O49: =Assumptions!P$192 -> 0 | ... Q49: =Assumptions!R$192 -> 0
B51: =_xlfn.TEXTBEFORE(Assumptions!B195," [") -> Cost of Capitalized Leases | C51: =Assumptions!D195 -> 0 | D51: =Assumptions!E195 -> 0 | E51: =Assumptions!F195 -> 0 | F51: =Assumptions!G195 -> 0 | G51: =Assumptions!H195 -> 0 | H51: =H$4*H52 -> 0 | I51: =I$4*I52 -> 0 | J51: =J$4*J52 -> 0 | K51: =K$4*K52 -> 0 | L51: =L$4*L52 -> 0 | M51: =M$4*M52 -> 0 | N51: =N$4*N52 -> 0 | O51: =O$4*O52 -> 0 | ... Q51: =Q$4*Q52 -> 0
B52: ="% of "&$B$4 -> % of Revenue | C52: =IFERROR(C51/C$4,0) -> 0 | D52: =D51/D$4 -> 0 | E52: =E51/E$4 -> 0 | F52: =F51/F$4 -> 0 | G52: =G51/G$4 -> 0 | H52: =+Assumptions!I196 -> 0 | I52: =+Assumptions!J196 -> 0 | J52: =+Assumptions!K196 -> 0 | K52: =+Assumptions!L196 -> 0 | L52: =+Assumptions!M196 -> 0 | M52: =+Assumptions!N196 -> 0 | N52: =+Assumptions!O196 -> 0 | O52: =+Assumptions!P196 -> 0 | ... Q52: =+Assumptions!R196 -> 0
B53: EBITDA | C53: =SUM(C43,C47,C51) -> 4161 | D53: =SUM(D43,D47,D51) -> 4095 | E53: =SUM(E43,E47,E51) -> 5462 | F53: =SUM(F43,F47,F51) -> 5564 | G53: =SUM(G43,G47,G51) -> 2233 | H53: =SUM(H43,H47,H51) -> 4998.4596 | I53: =SUM(I43,I47,I51) -> 5148.4134 | J53: =SUM(J43,J47,J51) -> 5302.8658 | ... Q53: =SUM(Q43,Q47,Q51) -> 0
B56: NOPAT Calculation
B57: =B$22 -> Operating Income (Loss) ~ EBIT | C57: =C$22 -> 3063 | D57: =D$22 -> 2903 | E57: =E$22 -> 4248 | F57: =F$22 -> 4362 | G57: =G$22 -> 894 | H57: =H$22 -> 3578.6789 | I57: =I$22 -> 3686.0393 | ... Q57: =Q$22 -> 0
B58: =B$31 -> Income Tax Expense (Benefit) | C58: =C$31 -> 396 | D58: =D$31 -> 593 | E58: =E$31 -> 981 | F58: =F$31 -> 900 | G58: =G$31 -> -29 | H58: =H$31 -> 640.77845 | I58: =I$31 -> 665.71304 | ... Q58: =Q$31 -> 0
B59: Net Profit After Tax - NOPAT | C59: =C57-C58 -> 2667 | D59: =D57-D58 -> 2310 | E59: =E57-E58 -> 3267 | F59: =F57-F58 -> 3462 | G59: =G57-G58 -> 923 | H59: =H57-H58 -> 2937.9004 | I59: =I57-I58 -> 3020.3262 | J59: =J57-J58 -> 3108.9398 | ... Q59: =Q57-Q58 -> 0

Sheet Cash Flows
B2: Statement of Cash Flows - Base
B3: =Assumptions!$B$132 -> Year Ending 09/31/2024, In USD Millions | C3: {=_xlfn.SEQUENCE(1,5+Assumptions!$C$20,(YEAR('Valuation Summary'!$C$4)-5))} -> 2019 | D3: 2020 | E3: 2021 | F3: 2022 | G3: 2023 | H3: 2024 | I3: 2025 | J3: 2026 | K3: 2027 | L3: 2028
B4: Operating Activities
B5: ='Income Statement'!B37 -> Net Income (Loss), GAAP | C5: ='Income Statement'!C37 -> 2022 | D5: ='Income Statement'!D37 -> 2061 | E5: ='Income Statement'!E37 -> 3047 | F5: ='Income Statement'!F37 -> 3238 | G5: ='Income Statement'!G37 -> -648 | H5: =IF(H$3="",0,'Income Statement'!H37) -> 2347.5089 | I5: =IF(I$3="",0,'Income Statement'!I37) -> 2386.7744 | J5: =IF(J$3="",0,'Income Statement'!J37) -> 2412.7161 | K5: =IF(K$3="",0,'Income Statement'!K37) -> 2430.1168 | L5: =IF(L$3="",0,'Income Statement'!L37) -> 2451.9484 | M5: =IF(M$3="",0,'Income Statement'!M37) -> 0 | N5: =IF(N$3="",0,'Income Statement'!N37) -> 0 | O5: =IF(O$3="",0,'Income Statement'!O37) -> 0 | ... Q5: =IF(Q$3="",0,'Income Statement'!Q37) -> 0
B6: ='Income Statement'!B47 -> Depreciation and Amortization | C6: ='Income Statement'!C47 -> 1098 | D6: ='Income Statement'!D47 -> 1192 | E6: ='Income Statement'!E47 -> 1214 | F6: ='Income Statement'!F47 -> 1202 | G6: ='Income Statement'!G47 -> 1339 | H6: =IF(H$3="",0,'Income Statement'!H47) -> 1392.2121 | I6: =IF(I$3="",0,'Income Statement'!I47) -> 1406.1342 | J6: =IF(J$3="",0,'Income Statement'!J47) -> 1420.1956 | K6: =IF(K$3="",0,'Income Statement'!K47) -> 1434.3975 | L6: =IF(L$3="",0,'Income Statement'!L47) -> 1448.7415 | M6: =IF(M$3="",0,'Income Statement'!M47) -> 0 | N6: =IF(N$3="",0,'Income Statement'!N47) -> 0 | O6: =IF(O$3="",0,'Income Statement'!O47) -> 0 | ... Q6: =IF(Q$3="",0,'Income Statement'!Q47) -> 0
B7: =Assumptions!B206 -> Non-Cash Items | C7: =Assumptions!D206 -> 70 | D7: =Assumptions!E206 -> -66 | E7: =Assumptions!F206 -> -768 | F7: =Assumptions!G206 -> -6 | G7: =Assumptions!H206 -> 996 | H7: =IF(H$3="",0,H40*Assumptions!I208) -> 0 | I7: =IF(I$3="",0,I40*Assumptions!J208) -> 0 | J7: =IF(J$3="",0,J40*Assumptions!K208) -> 0 | K7: =IF(K$3="",0,K40*Assumptions!L208) -> 0 | L7: =IF(L$3="",0,L40*Assumptions!M208) -> 0 | M7: =IF(M$3="",0,M40*Assumptions!N208) -> 0 | N7: =IF(N$3="",0,N40*Assumptions!O208) -> 0 | O7: =IF(O$3="",0,O40*Assumptions!P208) -> 0 | ... Q7: =IF(Q$3="",0,Q40*Assumptions!R208) -> 0
B8: =Assumptions!B213 -> Change in Non-Cash Working Capital | C8: =Assumptions!D213 -> -846 | D8: =Assumptions!E213 -> 580 | E8: =Assumptions!F213 -> 381 | F8: =Assumptions!G213 -> -2104 | G8: =Assumptions!H213 -> 187 | H8: =IF(H$3="",0,IFERROR(AVERAGE(C8:G8),0)) -> -360.4 | I8: =IF(I$3="",0,IFERROR(AVERAGE(D8:H8),0)) -> -263.28 | J8: =IF(J$3="",0,IFERROR(AVERAGE(E8:I8),0)) -> -431.936 | K8: =IF(K$3="",0,IFERROR(AVERAGE(F8:J8),0)) -> -594.5232 | L8: =IF(L$3="",0,IFERROR(AVERAGE(G8:K8),0)) -> -292.62784 | M8: =IF(M$3="",0,IFERROR(AVERAGE(H8:L8),0)) -> 0 | N8: =IF(N$3="",0,IFERROR(AVERAGE(I8:M8),0)) -> 0 | O8: =IF(O$3="",0,IFERROR(AVERAGE(J8:N8),0)) -> 0 | ... Q8: =IF(Q$3="",0,IFERROR(AVERAGE(L8:P8),0)) -> 0
B9: =Assumptions!B224 -> Net Cash from Discontinued Operations | C9: =Assumptions!D224 -> 0 | D9: =Assumptions!E224 -> 0 | E9: =Assumptions!F224 -> 0 | F9: =Assumptions!G224 -> 0 | G9: =Assumptions!H224 -> 0 | H9: =IF(H$3="",0,Assumptions!I224) -> 0 | I9: =IF(I$3="",0,Assumptions!J224) -> 0 | J9: =IF(J$3="",0,Assumptions!K224) -> 0 | K9: =IF(K$3="",0,Assumptions!L224) -> 0 | L9: =IF(L$3="",0,Assumptions!M224) -> 0 | M9: =IF(M$3="",0,Assumptions!N224) -> 0 | N9: =IF(N$3="",0,Assumptions!O224) -> 0 | O9: =IF(O$3="",0,Assumptions!P224) -> 0 | ... Q9: =IF(Q$3="",0,Assumptions!R224) -> 0
B10: Cash from Operating Activities | C10: =SUM(C5:C9) -> 2344 | D10: =SUM(D5:D9) -> 3767 | E10: =SUM(E5:E9) -> 3874 | F10: =SUM(F5:F9) -> 2330 | G10: =SUM(G5:G9) -> 1874 | H10: =SUM(H5:H9) -> 3379.321 | I10: =SUM(I5:I9) -> 3529.6287 | J10: =SUM(J5:J9) -> 3400.9757 | ... Q10: =SUM(Q5:Q9) -> 0
B12: Investing Activities
B13: Change in Fixed Assets and Intangibles | C13: =-'Income Statement'!C44+Assumptions!D229 -> -1259 | D13: =-'Income Statement'!D44+Assumptions!E229 -> -1199 | E13: =-'Income Statement'!E44+Assumptions!F229 -> -1209 | F13: =-'Income Statement'!F44+Assumptions!G229 -> -1887 | G13: =-'Income Statement'!G44+Assumptions!H229 -> -1939 | H13: =IF(H$3="",0,-'Income Statement'!H44+('Balance Sheet'!H12*Assumptions!I230)) -> -1658.1968 | I13: =IF(I$3="",0,-'Income Statement'!I44+('Balance Sheet'!I12*Assumptions!J230)) -> -1674.7787 | J13: =IF(J$3="",0,-'Income Statement'!J44+('Balance Sheet'!J12*Assumptions!K230)) -> -1691.5265 | K13: =IF(K$3="",0,-'Income Statement'!K44+('Balance Sheet'!K12*Assumptions!L230)) -> -1708.4418 | L13: =IF(L$3="",0,-'Income Statement'!L44+('Balance Sheet'!L12*Assumptions!M230)) -> -1725.5262 | M13: =IF(M$3="",0,-'Income Statement'!M44+('Balance Sheet'!M12*Assumptions!N230)) -> 0 | N13: =IF(N$3="",0,-'Income Statement'!N44+('Balance Sheet'!N12*Assumptions!O230)) -> 0 | O13: =IF(O$3="",0,-'Income Statement'!O44+('Balance Sheet'!O12*Assumptions!P230)) -> 0 | ... Q13: =IF(Q$3="",0,-'Income Statement'!Q44+('Balance Sheet'!Q12*Assumptions!R230)) -> 0
B14: Net Change in Long-Term Investments | C14: =Assumptions!D233 -> 0 | D14: =Assumptions!E233 -> 0 | E14: =Assumptions!F233 -> 0 | F14: =Assumptions!G233 -> 0 | G14: =Assumptions!H233 -> 0 | H14: =IF(H$3="",0,IFERROR(AVERAGE(C14:G14),0)) -> 0 | I14: =IF(I$3="",0,IFERROR(AVERAGE(D14:H14),0)) -> 0 | J14: =IF(J$3="",0,IFERROR(AVERAGE(E14:I14),0)) -> 0 | K14: =IF(K$3="",0,IFERROR(AVERAGE(F14:J14),0)) -> 0 | L14: =IF(L$3="",0,IFERROR(AVERAGE(G14:K14),0)) -> 0 | M14: =IF(M$3="",0,IFERROR(AVERAGE(H14:L14),0)) -> 0 | N14: =IF(N$3="",0,IFERROR(AVERAGE(I14:M14),0)) -> 0 | O14: =IF(O$3="",0,IFERROR(AVERAGE(J14:N14),0)) -> 0 | ... Q14: =IF(Q$3="",0,IFERROR(AVERAGE(L14:P14),0)) -> 0
B15: Net Cash from Acquistions and Divestitures | C15: =Assumptions!D236 -> -2292 | D15: =Assumptions!E236 -> -154 | E15: =Assumptions!F236 -> 1144 | F15: =Assumptions!G236 -> -177 | G15: =Assumptions!H236 -> -262 | H15: =IF(H$3="",0,IFERROR(AVERAGE(C15:G15),0)) -> -348.2 | I15: =IF(I$3="",0,IFERROR(AVERAGE(D15:H15),0)) -> 40.56 | J15: =IF(J$3="",0,IFERROR(AVERAGE(E15:I15),0)) -> 79.472 | K15: =IF(K$3="",0,IFERROR(AVERAGE(F15:J15),0)) -> -133.4336 | L15: =IF(L$3="",0,IFERROR(AVERAGE(G15:K15),0)) -> -124.72032 | M15: =IF(M$3="",0,IFERROR(AVERAGE(H15:L15),0)) -> 0 | N15: =IF(N$3="",0,IFERROR(AVERAGE(I15:M15),0)) -> 0 | O15: =IF(O$3="",0,IFERROR(AVERAGE(J15:N15),0)) -> 0 | ... Q15: =IF(Q$3="",0,IFERROR(AVERAGE(L15:P15),0)) -> 0
B16: Other Investing Actvities | C16: =Assumptions!D239 -> 89 | D16: =Assumptions!E239 -> -1068 | E16: =Assumptions!F239 -> 1082 | F16: =Assumptions!G239 -> -106 | G16: =Assumptions!H239 -> 64 | H16: =IF(H$3="",0,IFERROR(AVERAGE(C16:G16),0)) -> 12.2 | I16: =IF(I$3="",0,IFERROR(AVERAGE(D16:H16),0)) -> -3.16 | J16: =IF(J$3="",0,IFERROR(AVERAGE(E16:I16),0)) -> 209.808 | K16: =IF(K$3="",0,IFERROR(AVERAGE(F16:J16),0)) -> 35.3696 | L16: =IF(L$3="",0,IFERROR(AVERAGE(G16:K16),0)) -> 63.64352 | M16: =IF(M$3="",0,IFERROR(AVERAGE(H16:L16),0)) -> 0 | N16: =IF(N$3="",0,IFERROR(AVERAGE(I16:M16),0)) -> 0 | O16: =IF(O$3="",0,IFERROR(AVERAGE(J16:N16),0)) -> 0 | ... Q16: =IF(Q$3="",0,IFERROR(AVERAGE(L16:P16),0)) -> 0
B17: Net Cash from Discontinued Operations | C17: =Assumptions!D242 -> 0 | D17: =Assumptions!E242 -> 0 | E17: =Assumptions!F242 -> 0 | F17: =Assumptions!G242 -> 0 | G17: =Assumptions!H242 -> 0 | H17: =IF(H$3="",0,IFERROR(AVERAGE(C17:G17),0)) -> 0 | I17: =IF(I$3="",0,IFERROR(AVERAGE(D17:H17),0)) -> 0 | J17: =IF(J$3="",0,IFERROR(AVERAGE(E17:I17),0)) -> 0 | K17: =IF(K$3="",0,IFERROR(AVERAGE(F17:J17),0)) -> 0 | L17: =IF(L$3="",0,IFERROR(AVERAGE(G17:K17),0)) -> 0 | M17: =IF(M$3="",0,IFERROR(AVERAGE(H17:L17),0)) -> 0 | N17: =IF(N$3="",0,IFERROR(AVERAGE(I17:M17),0)) -> 0 | O17: =IF(O$3="",0,IFERROR(AVERAGE(J17:N17),0)) -> 0 | ... Q17: =IF(Q$3="",0,IFERROR(AVERAGE(L17:P17),0)) -> 0
B18: Cash from Investing Activities | C18: =SUM(C13:C17) -> -3462 | D18: =SUM(D13:D17) -> -2421 | E18: =SUM(E13:E17) -> 1017 | F18: =SUM(F13:F17) -> -2170 | G18: =SUM(G13:G17) -> -2137 | H18: =SUM(H13:H17) -> -1994.1968 | I18: =SUM(I13:I17) -> -1637.3787 | J18: =SUM(J13:J17) -> -1402.2465 | ... Q18: =SUM(Q13:Q17) -> 0
B21: Financing Activities
B22: =Assumptions!B245 -> Dividends Paid | C22: =Assumptions!D245 -> -537 | D22: =Assumptions!E245 -> -601 | E22: =Assumptions!F245 -> -636 | F22: =Assumptions!G245 -> -653 | G22: =Assumptions!H245 -> -670 | H22: =IF(H$3="",0,H41*Assumptions!I246) -> 31.160068 | I22: =IF(I$3="",0,I41*Assumptions!J246) -> 31.681266 | J22: =IF(J$3="",0,J41*Assumptions!K246) -> 32.025607 | K22: =IF(K$3="",0,K41*Assumptions!L246) -> 32.256579 | L22: =IF(L$3="",0,L41*Assumptions!M246) -> 32.546364 | M22: =IF(M$3="",0,M41*Assumptions!N246) -> 0 | N22: =IF(N$3="",0,N41*Assumptions!O246) -> 0 | O22: =IF(O$3="",0,O41*Assumptions!P246) -> 0 | ... Q22: =IF(Q$3="",0,Q41*Assumptions!R246) -> 0
B23: =Assumptions!B249 -> Net Cash from (Repayment) Debt | C23: =Assumptions!D249 -> 1891 | D23: =Assumptions!E249 -> -672 | E23: =Assumptions!F249 -> -2047 | F23: =Assumptions!G249 -> -1088 | G23: =Assumptions!H249 -> 1117 | H23: =IF(H$3="",0,IFERROR(AVERAGE(C23:G23),0)) -> -159.8 | I23: =IF(I$3="",0,IFERROR(AVERAGE(D23:H23),0)) -> -569.96 | J23: =IF(J$3="",0,IFERROR(AVERAGE(E23:I23),0)) -> -549.552 | K23: =IF(K$3="",0,IFERROR(AVERAGE(F23:J23),0)) -> -250.0624 | L23: =IF(L$3="",0,IFERROR(AVERAGE(G23:K23),0)) -> -82.47488 | M23: =IF(M$3="",0,IFERROR(AVERAGE(H23:L23),0)) -> 0 | N23: =IF(N$3="",0,IFERROR(AVERAGE(I23:M23),0)) -> 0 | O23: =IF(O$3="",0,IFERROR(AVERAGE(J23:N23),0)) -> 0 | ... Q23: =IF(Q$3="",0,IFERROR(AVERAGE(L23:P23),0)) -> 0
B24: =Assumptions!B252 -> Cash (Repurchase) of Equity | C24: =Assumptions!D252 -> -153 | D24: =Assumptions!E252 -> -177 | E24: =Assumptions!F252 -> -26 | F24: =Assumptions!G252 -> -576 | G24: =Assumptions!H252 -> -343 | H24: =IF(H$3="",0,IFERROR(AVERAGE(C24:G24),0)) -> -255 | I24: =IF(I$3="",0,IFERROR(AVERAGE(D24:H24),0)) -> -275.4 | J24: =IF(J$3="",0,IFERROR(AVERAGE(E24:I24),0)) -> -295.08 | K24: =IF(K$3="",0,IFERROR(AVERAGE(F24:J24),0)) -> -348.896 | L24: =IF(L$3="",0,IFERROR(AVERAGE(G24:K24),0)) -> -303.4752 | M24: =IF(M$3="",0,IFERROR(AVERAGE(H24:L24),0)) -> 0 | N24: =IF(N$3="",0,IFERROR(AVERAGE(I24:M24),0)) -> 0 | O24: =IF(O$3="",0,IFERROR(AVERAGE(J24:N24),0)) -> 0 | ... Q24: =IF(Q$3="",0,IFERROR(AVERAGE(L24:P24),0)) -> 0
B25: =Assumptions!B255 -> Other Financing Activities | C25: =Assumptions!D255 -> -30 | D25: =Assumptions!E255 -> -18 | E25: =Assumptions!F255 -> -22 | F25: =Assumptions!G255 -> -6 | G25: =Assumptions!H255 -> -16 | H25: =IF(H$3="",0,IFERROR(AVERAGE(C25:G25),0)) -> -18.4 | I25: =IF(I$3="",0,IFERROR(AVERAGE(D25:H25),0)) -> -16.08 | J25: =IF(J$3="",0,IFERROR(AVERAGE(E25:I25),0)) -> -15.696 | K25: =IF(K$3="",0,IFERROR(AVERAGE(F25:J25),0)) -> -14.4352 | L25: =IF(L$3="",0,IFERROR(AVERAGE(G25:K25),0)) -> -16.12224 | M25: =IF(M$3="",0,IFERROR(AVERAGE(H25:L25),0)) -> 0 | N25: =IF(N$3="",0,IFERROR(AVERAGE(I25:M25),0)) -> 0 | O25: =IF(O$3="",0,IFERROR(AVERAGE(J25:N25),0)) -> 0 | ... Q25: =IF(Q$3="",0,IFERROR(AVERAGE(L25:P25),0)) -> 0
B26: =Assumptions!B258 -> Net Cash from Discontinued Operations | C26: =Assumptions!D258 -> 0 | D26: =Assumptions!E258 -> 0 | E26: =Assumptions!F258 -> 0 | F26: =Assumptions!G258 -> 0 | G26: =Assumptions!H258 -> 0 | H26: =IF(H$3="",0,IFERROR(AVERAGE(C26:G26),0)) -> 0 | I26: =IF(I$3="",0,IFERROR(AVERAGE(D26:H26),0)) -> 0 | J26: =IF(J$3="",0,IFERROR(AVERAGE(E26:I26),0)) -> 0 | K26: =IF(K$3="",0,IFERROR(AVERAGE(F26:J26),0)) -> 0 | L26: =IF(L$3="",0,IFERROR(AVERAGE(G26:K26),0)) -> 0 | M26: =IF(M$3="",0,IFERROR(AVERAGE(H26:L26),0)) -> 0 | N26: =IF(N$3="",0,IFERROR(AVERAGE(I26:M26),0)) -> 0 | O26: =IF(O$3="",0,IFERROR(AVERAGE(J26:N26),0)) -> 0 | ... Q26: =IF(Q$3="",0,IFERROR(AVERAGE(L26:P26),0)) -> 0
B27: Cash from Financing Activities | C27: =SUM(C22:C26) -> 1171 | D27: =SUM(D22:D26) -> -1468 | E27: =SUM(E22:E26) -> -2731 | F27: =SUM(F22:F26) -> -2323 | G27: =SUM(G22:G26) -> 88 | H27: =SUM(H22:H26) -> -402.03993 | I27: =SUM(I22:I26) -> -829.75873 | J27: =SUM(J22:J26) -> -828.30239 | ... Q27: =SUM(Q22:Q26) -> 0
B29: =Assumptions!B261 -> Effect of Foreign Exchange Rates | C29: =+Assumptions!D261 -> -6 | D29: =+Assumptions!E261 -> -1 | E29: =+Assumptions!F261 -> 4 | F29: =+Assumptions!G261 -> -35 | G29: =+Assumptions!H261 -> 1 | H29: =IF(H$3="",0,IFERROR(AVERAGE(C29:G29),0)) -> -7.4 | I29: =IF(I$3="",0,IFERROR(AVERAGE(D29:H29),0)) -> -7.68 | J29: =IF(J$3="",0,IFERROR(AVERAGE(E29:I29),0)) -> -9.016 | K29: =IF(K$3="",0,IFERROR(AVERAGE(F29:J29),0)) -> -11.6192 | L29: =IF(L$3="",0,IFERROR(AVERAGE(G29:K29),0)) -> -6.94304 | M29: =IF(M$3="",0,IFERROR(AVERAGE(H29:L29),0)) -> 0 | N29: =IF(N$3="",0,IFERROR(AVERAGE(I29:M29),0)) -> 0 | O29: =IF(O$3="",0,IFERROR(AVERAGE(J29:N29),0)) -> 0 | ... Q29: =IF(Q$3="",0,IFERROR(AVERAGE(L29:P29),0)) -> 0
B31: Net Change in Cash | C31: =SUM(C10,C18,C27,C29) -> 47 | D31: =SUM(D10,D18,D27,D29) -> -123 | E31: =SUM(E10,E18,E27,E29) -> 2164 | F31: =SUM(F10,F18,F27,F29) -> -2198 | G31: =SUM(G10,G18,G27,G29) -> -174 | H31: =SUM(H10,H18,H27,H29) -> 975.68431 | I31: =SUM(I10,I18,I27,I29) -> 1054.8112 | J31: =SUM(J10,J18,J27,J29) -> 1161.4108 | ... Q31: =SUM(Q10,Q18,Q27,Q29) -> 0
B33: Cash Balance
B34: =+Assumptions!B264 -> Opening Cash | C34: =+Assumptions!C265+C31 -> 317 | D34: =+C36 -> 317 | E34: =+D36 -> 148 | F34: =+E36 -> 2228 | G34: =+F36 -> 160 | H34: =IF(H$3="",0,G36) -> -14 | I34: =IF(I$3="",0,H36) -> 961.68431 | J34: =IF(J$3="",0,I36) -> 2016.4955 | K34: =IF(K$3="",0,J36) -> 3177.9063 | L34: =IF(L$3="",0,K36) -> 4048.6354 | M34: =IF(M$3="",0,L36) -> 0 | N34: =IF(N$3="",0,M36) -> 0 | O34: =IF(O$3="",0,N36) -> 0 | ... Q34: =IF(Q$3="",0,P36) -> 0
B35: =Assumptions!B267 -> Restricted Cash | C35: =+Assumptions!D269 -> 0 | D35: =+Assumptions!E269 -> 46 | E35: =+Assumptions!F269 -> 84 | F35: =+Assumptions!G269 -> -130 | G35: =+Assumptions!H269 -> 0 | H35: =IF(H$3="",0,Assumptions!I269) -> 0 | I35: =IF(I$3="",0,Assumptions!J269) -> 0 | J35: =IF(J$3="",0,Assumptions!K269) -> 0 | K35: =IF(K$3="",0,Assumptions!L269) -> 0 | L35: =IF(L$3="",0,Assumptions!M269) -> 0 | M35: =IF(M$3="",0,Assumptions!N269) -> 0 | N35: =IF(N$3="",0,Assumptions!O269) -> 0 | O35: =IF(O$3="",0,Assumptions!P269) -> 0 | ... Q35: =IF(Q$3="",0,Assumptions!R269) -> 0
B36: Closing Cash Balance | C36: =+C34-C35 -> 317 | D36: =+D31+D34-D35 -> 148 | E36: =+E31+E34-E35 -> 2228 | F36: =+F31+F34-F35 -> 160 | G36: =+G31+G34-G35 -> -14 | H36: =+H31+H34-H35 -> 961.68431 | I36: =+I31+I34-I35 -> 2016.4955 | J36: =+J31+J34-J35 -> 3177.9063 | K36: =+K31+K34-K35 -> 4048.6354 | ... Q36: =+Q31+Q34-Q35 -> 0
B39: Data from Financial Statements
B40: ='Income Statement'!B4 -> Revenue | C40: ='Income Statement'!C4 -> 42405 | D40: ='Income Statement'!D4 -> 43185 | E40: ='Income Statement'!E4 -> 47049 | F40: ='Income Statement'!F4 -> 53282 | G40: ='Income Statement'!G4 -> 52881 | H40: ='Income Statement'!H4 -> 53409.81 | I40: ='Income Statement'!I4 -> 53943.908 | ... Q40: ='Income Statement'!Q4 -> 0
B41: ='Income Statement'!B37 -> Net Income (Loss), GAAP | C41: ='Income Statement'!C37 -> 2022 | D41: ='Income Statement'!D37 -> 2061 | E41: ='Income Statement'!E37 -> 3047 | F41: ='Income Statement'!F37 -> 3238 | G41: ='Income Statement'!G37 -> -648 | H41: ='Income Statement'!H37 -> 2347.5089 | I41: ='Income Statement'!I37 -> 2386.7744 | ... Q41: ='Income Statement'!Q37 -> 0

Sheet CF Bear
B2: Statement of Cash Flows - Base
B3: =Assumptions!$B$132 -> Year Ending 09/31/2024, In USD Millions | C3: {=_xlfn.SEQUENCE(1,5+Assumptions!$C$20,(YEAR('Valuation Summary'!$C$4)-5))} -> 2019 | D3: 2020 | E3: 2021 | F3: 2022 | G3: 2023 | H3: 2024 | I3: 2025 | J3: 2026 | K3: 2027 | L3: 2028
B4: Operating Activities
B5: ='Income Statement'!B37 -> Net Income (Loss), GAAP | C5: ='IS Bear'!C37 -> 2022 | D5: ='Income Statement'!D37 -> 2061 | E5: ='Income Statement'!E37 -> 3047 | F5: ='Income Statement'!F37 -> 3238 | G5: ='Income Statement'!G37 -> -648 | H5: =IF(H$3="",0,'IS Bear'!H37) -> 2295.3852 | I5: =IF(I$3="",0,'IS Bear'!I37) -> 2282.5272 | J5: =IF(J$3="",0,'IS Bear'!J37) -> 2256.34 | K5: =IF(K$3="",0,'IS Bear'!K37) -> 2221.6015 | L5: =IF(L$3="",0,'IS Bear'!L37) -> 2191.2782 | M5: =IF(M$3="",0,'IS Bear'!M37) -> 0 | N5: =IF(N$3="",0,'IS Bear'!N37) -> 0 | O5: =IF(O$3="",0,'IS Bear'!O37) -> 0 | ... Q5: =IF(Q$3="",0,'IS Bear'!Q37) -> 0
B6: ='Income Statement'!B47 -> Depreciation and Amortization | C6: ='IS Bear'!C47 -> 1098 | D6: ='Income Statement'!D47 -> 1192 | E6: ='Income Statement'!E47 -> 1214 | F6: ='Income Statement'!F47 -> 1202 | G6: ='Income Statement'!G47 -> 1339 | H6: =IF(H$3="",0,'IS Bear'!H47) -> 1364.6436 | I6: =IF(I$3="",0,'IS Bear'!I47) -> 1350.9971 | J6: =IF(J$3="",0,'IS Bear'!J47) -> 1337.4872 | K6: =IF(K$3="",0,'IS Bear'!K47) -> 1324.1123 | L6: =IF(L$3="",0,'IS Bear'!L47) -> 1310.8712 | M6: =IF(M$3="",0,'IS Bear'!M47) -> 0 | N6: =IF(N$3="",0,'IS Bear'!N47) -> 0 | O6: =IF(O$3="",0,'IS Bear'!O47) -> 0 | ... Q6: =IF(Q$3="",0,'IS Bear'!Q47) -> 0
B7: =Assumptions!B206 -> Non-Cash Items | C7: =Assumptions!D206 -> 70 | D7: =Assumptions!E206 -> -66 | E7: =Assumptions!F206 -> -768 | F7: =Assumptions!G206 -> -6 | G7: =Assumptions!H206 -> 996 | H7: =IF(H$3="",0,H40*Assumptions!I208) -> 0 | I7: =IF(I$3="",0,I40*Assumptions!J208) -> 0 | J7: =IF(J$3="",0,J40*Assumptions!K208) -> 0 | K7: =IF(K$3="",0,K40*Assumptions!L208) -> 0 | L7: =IF(L$3="",0,L40*Assumptions!M208) -> 0 | M7: =IF(M$3="",0,M40*Assumptions!N208) -> 0 | N7: =IF(N$3="",0,N40*Assumptions!O208) -> 0 | O7: =IF(O$3="",0,O40*Assumptions!P208) -> 0 | ... Q7: =IF(Q$3="",0,Q40*Assumptions!R208) -> 0
B8: =Assumptions!B213 -> Change in Non-Cash Working Capital | C8: =Assumptions!D213 -> -846 | D8: =Assumptions!E213 -> 580 | E8: =Assumptions!F213 -> 381 | F8: =Assumptions!G213 -> -2104 | G8: =Assumptions!H213 -> 187 | H8: =IF(H$3="",0,IFERROR(AVERAGE(C8:G8),0)) -> -360.4 | I8: =IF(I$3="",0,IFERROR(AVERAGE(D8:H8),0)) -> -263.28 | J8: =IF(J$3="",0,IFERROR(AVERAGE(E8:I8),0)) -> -431.936 | K8: =IF(K$3="",0,IFERROR(AVERAGE(F8:J8),0)) -> -594.5232 | L8: =IF(L$3="",0,IFERROR(AVERAGE(G8:K8),0)) -> -292.62784 | M8: =IF(M$3="",0,IFERROR(AVERAGE(H8:L8),0)) -> 0 | N8: =IF(N$3="",0,IFERROR(AVERAGE(I8:M8),0)) -> 0 | O8: =IF(O$3="",0,IFERROR(AVERAGE(J8:N8),0)) -> 0 | ... Q8: =IF(Q$3="",0,IFERROR(AVERAGE(L8:P8),0)) -> 0
B9: =Assumptions!B224 -> Net Cash from Discontinued Operations | C9: =Assumptions!D224 -> 0 | D9: =Assumptions!E224 -> 0 | E9: =Assumptions!F224 -> 0 | F9: =Assumptions!G224 -> 0 | G9: =Assumptions!H224 -> 0 | H9: =IF(H$3="",0,Assumptions!I224) -> 0 | I9: =IF(I$3="",0,Assumptions!J224) -> 0 | J9: =IF(J$3="",0,Assumptions!K224) -> 0 | K9: =IF(K$3="",0,Assumptions!L224) -> 0 | L9: =IF(L$3="",0,Assumptions!M224) -> 0 | M9: =IF(M$3="",0,Assumptions!N224) -> 0 | N9: =IF(N$3="",0,Assumptions!O224) -> 0 | O9: =IF(O$3="",0,Assumptions!P224) -> 0 | ... Q9: =IF(Q$3="",0,Assumptions!R224) -> 0
B10: Cash from Operating Activities | C10: =SUM(C5:C9) -> 2344 | D10: =SUM(D5:D9) -> 3767 | E10: =SUM(E5:E9) -> 3874 | F10: =SUM(F5:F9) -> 2330 | G10: =SUM(G5:G9) -> 1874 | H10: =SUM(H5:H9) -> 3299.6288 | I10: =SUM(I5:I9) -> 3370.2443 | J10: =SUM(J5:J9) -> 3161.8912 | ... Q10: =SUM(Q5:Q9) -> 0
B12: Investing Activities
B13: Change in Fixed Assets and Intangibles | C13: =-'IS Bear'!C44+Assumptions!D229 -> -1259 | D13: =-'Income Statement'!D44+Assumptions!E229 -> -1199 | E13: =-'Income Statement'!E44+Assumptions!F229 -> -1209 | F13: =-'Income Statement'!F44+Assumptions!G229 -> -1887 | G13: =-'Income Statement'!G44+Assumptions!H229 -> -1939 | H13: =IF(H$3="",0,-'IS Bear'!H44+('BS Bear'!H12*Assumptions!I230)) -> -1625.3612 | I13: =IF(I$3="",0,-'IS Bear'!I44+('BS Bear'!I12*Assumptions!J230)) -> -1609.1076 | J13: =IF(J$3="",0,-'IS Bear'!J44+('BS Bear'!J12*Assumptions!K230)) -> -1593.0165 | K13: =IF(K$3="",0,-'IS Bear'!K44+('BS Bear'!K12*Assumptions!L230)) -> -1577.0863 | L13: =IF(L$3="",0,-'IS Bear'!L44+('BS Bear'!L12*Assumptions!M230)) -> -1561.3155 | M13: =IF(M$3="",0,-'IS Bear'!M44+('BS Bear'!M12*Assumptions!N230)) -> 0 | N13: =IF(N$3="",0,-'IS Bear'!N44+('BS Bear'!N12*Assumptions!O230)) -> 0 | O13: =IF(O$3="",0,-'IS Bear'!O44+('BS Bear'!O12*Assumptions!P230)) -> 0 | ... Q13: =IF(Q$3="",0,-'IS Bear'!Q44+('BS Bear'!Q12*Assumptions!R230)) -> 0
B14: Net Change in Long-Term Investments | C14: =Assumptions!D233 -> 0 | D14: =Assumptions!E233 -> 0 | E14: =Assumptions!F233 -> 0 | F14: =Assumptions!G233 -> 0 | G14: =Assumptions!H233 -> 0 | H14: =IF(H$3="",0,IFERROR(AVERAGE(C14:G14),0)) -> 0 | I14: =IF(I$3="",0,IFERROR(AVERAGE(D14:H14),0)) -> 0 | J14: =IF(J$3="",0,IFERROR(AVERAGE(E14:I14),0)) -> 0 | K14: =IF(K$3="",0,IFERROR(AVERAGE(F14:J14),0)) -> 0 | L14: =IF(L$3="",0,IFERROR(AVERAGE(G14:K14),0)) -> 0 | M14: =IF(M$3="",0,IFERROR(AVERAGE(H14:L14),0)) -> 0 | N14: =IF(N$3="",0,IFERROR(AVERAGE(I14:M14),0)) -> 0 | O14: =IF(O$3="",0,IFERROR(AVERAGE(J14:N14),0)) -> 0 | ... Q14: =IF(Q$3="",0,IFERROR(AVERAGE(L14:P14),0)) -> 0
B15: Net Cash from Acquistions and Divestitures | C15: =Assumptions!D236 -> -2292 | D15: =Assumptions!E236 -> -154 | E15: =Assumptions!F236 -> 1144 | F15: =Assumptions!G236 -> -177 | G15: =Assumptions!H236 -> -262 | H15: =IF(H$3="",0,IFERROR(AVERAGE(C15:G15),0)) -> -348.2 | I15: =IF(I$3="",0,IFERROR(AVERAGE(D15:H15),0)) -> 40.56 | J15: =IF(J$3="",0,IFERROR(AVERAGE(E15:I15),0)) -> 79.472 | K15: =IF(K$3="",0,IFERROR(AVERAGE(F15:J15),0)) -> -133.4336 | L15: =IF(L$3="",0,IFERROR(AVERAGE(G15:K15),0)) -> -124.72032 | M15: =IF(M$3="",0,IFERROR(AVERAGE(H15:L15),0)) -> 0 | N15: =IF(N$3="",0,IFERROR(AVERAGE(I15:M15),0)) -> 0 | O15: =IF(O$3="",0,IFERROR(AVERAGE(J15:N15),0)) -> 0 | ... Q15: =IF(Q$3="",0,IFERROR(AVERAGE(L15:P15),0)) -> 0
B16: Other Investing Actvities | C16: =Assumptions!D239 -> 89 | D16: =Assumptions!E239 -> -1068 | E16: =Assumptions!F239 -> 1082 | F16: =Assumptions!G239 -> -106 | G16: =Assumptions!H239 -> 64 | H16: =IF(H$3="",0,IFERROR(AVERAGE(C16:G16),0)) -> 12.2 | I16: =IF(I$3="",0,IFERROR(AVERAGE(D16:H16),0)) -> -3.16 | J16: =IF(J$3="",0,IFERROR(AVERAGE(E16:I16),0)) -> 209.808 | K16: =IF(K$3="",0,IFERROR(AVERAGE(F16:J16),0)) -> 35.3696 | L16: =IF(L$3="",0,IFERROR(AVERAGE(G16:K16),0)) -> 63.64352 | M16: =IF(M$3="",0,IFERROR(AVERAGE(H16:L16),0)) -> 0 | N16: =IF(N$3="",0,IFERROR(AVERAGE(I16:M16),0)) -> 0 | O16: =IF(O$3="",0,IFERROR(AVERAGE(J16:N16),0)) -> 0 | ... Q16: =IF(Q$3="",0,IFERROR(AVERAGE(L16:P16),0)) -> 0
B17: Net Cash from Discontinued Operations | C17: =Assumptions!D242 -> 0 | D17: =Assumptions!E242 -> 0 | E17: =Assumptions!F242 -> 0 | F17: =Assumptions!G242 -> 0 | G17: =Assumptions!H242 -> 0 | H17: =IF(H$3="",0,IFERROR(AVERAGE(C17:G17),0)) -> 0 | I17: =IF(I$3="",0,IFERROR(AVERAGE(D17:H17),0)) -> 0 | J17: =IF(J$3="",0,IFERROR(AVERAGE(E17:I17),0)) -> 0 | K17: =IF(K$3="",0,IFERROR(AVERAGE(F17:J17),0)) -> 0 | L17: =IF(L$3="",0,IFERROR(AVERAGE(G17:K17),0)) -> 0 | M17: =IF(M$3="",0,IFERROR(AVERAGE(H17:L17),0)) -> 0 | N17: =IF(N$3="",0,IFERROR(AVERAGE(I17:M17),0)) -> 0 | O17: =IF(O$3="",0,IFERROR(AVERAGE(J17:N17),0)) -> 0 | ... Q17: =IF(Q$3="",0,IFERROR(AVERAGE(L17:P17),0)) -> 0
B18: Cash from Investing Activities | C18: =SUM(C13:C17) -> -3462 | D18: =SUM(D13:D17) -> -2421 | E18: =SUM(E13:E17) -> 1017 | F18: =SUM(F13:F17) -> -2170 | G18: =SUM(G13:G17) -> -2137 | H18: =SUM(H13:H17) -> -1961.3612 | I18: =SUM(I13:I17) -> -1571.7076 | J18: =SUM(J13:J17) -> -1303.7365 | ... Q18: =SUM(Q13:Q17) -> 0
B21: Financing Activities
B22: =Assumptions!B245 -> Dividends Paid | C22: =Assumptions!D245 -> -537 | D22: =Assumptions!E245 -> -601 | E22: =Assumptions!F245 -> -636 | F22: =Assumptions!G245 -> -653 | G22: =Assumptions!H245 -> -670 | H22: =IF(H$3="",0,H41*Assumptions!I246) -> 30.468196 | I22: =IF(I$3="",0,I41*Assumptions!J246) -> 30.297522 | J22: =IF(J$3="",0,J41*Assumptions!K246) -> 29.949922 | K22: =IF(K$3="",0,K41*Assumptions!L246) -> 29.488814 | L22: =IF(L$3="",0,L41*Assumptions!M246) -> 29.086313 | M22: =IF(M$3="",0,M41*Assumptions!N246) -> 0 | N22: =IF(N$3="",0,N41*Assumptions!O246) -> 0 | O22: =IF(O$3="",0,O41*Assumptions!P246) -> 0 | ... Q22: =IF(Q$3="",0,Q41*Assumptions!R246) -> 0
B23: =Assumptions!B249 -> Net Cash from (Repayment) Debt | C23: =Assumptions!D249 -> 1891 | D23: =Assumptions!E249 -> -672 | E23: =Assumptions!F249 -> -2047 | F23: =Assumptions!G249 -> -1088 | G23: =Assumptions!H249 -> 1117 | H23: =IF(H$3="",0,IFERROR(AVERAGE(C23:G23),0)) -> -159.8 | I23: =IF(I$3="",0,IFERROR(AVERAGE(D23:H23),0)) -> -569.96 | J23: =IF(J$3="",0,IFERROR(AVERAGE(E23:I23),0)) -> -549.552 | K23: =IF(K$3="",0,IFERROR(AVERAGE(F23:J23),0)) -> -250.0624 | L23: =IF(L$3="",0,IFERROR(AVERAGE(G23:K23),0)) -> -82.47488 | M23: =IF(M$3="",0,IFERROR(AVERAGE(H23:L23),0)) -> 0 | N23: =IF(N$3="",0,IFERROR(AVERAGE(I23:M23),0)) -> 0 | O23: =IF(O$3="",0,IFERROR(AVERAGE(J23:N23),0)) -> 0 | ... Q23: =IF(Q$3="",0,IFERROR(AVERAGE(L23:P23),0)) -> 0
B24: =Assumptions!B252 -> Cash (Repurchase) of Equity | C24: =Assumptions!D252 -> -153 | D24: =Assumptions!E252 -> -177 | E24: =Assumptions!F252 -> -26 | F24: =Assumptions!G252 -> -576 | G24: =Assumptions!H252 -> -343 | H24: =IF(H$3="",0,IFERROR(AVERAGE(C24:G24),0)) -> -255 | I24: =IF(I$3="",0,IFERROR(AVERAGE(D24:H24),0)) -> -275.4 | J24: =IF(J$3="",0,IFERROR(AVERAGE(E24:I24),0)) -> -295.08 | K24: =IF(K$3="",0,IFERROR(AVERAGE(F24:J24),0)) -> -348.896 | L24: =IF(L$3="",0,IFERROR(AVERAGE(G24:K24),0)) -> -303.4752 | M24: =IF(M$3="",0,IFERROR(AVERAGE(H24:L24),0)) -> 0 | N24: =IF(N$3="",0,IFERROR(AVERAGE(I24:M24),0)) -> 0 | O24: =IF(O$3="",0,IFERROR(AVERAGE(J24:N24),0)) -> 0 | ... Q24: =IF(Q$3="",0,IFERROR(AVERAGE(L24:P24),0)) -> 0
B25: =Assumptions!B255 -> Other Financing Activities | C25: =Assumptions!D255 -> -30 | D25: =Assumptions!E255 -> -18 | E25: =Assumptions!F255 -> -22 | F25: =Assumptions!G255 -> -6 | G25: =Assumptions!H255 -> -16 | H25: =IF(H$3="",0,IFERROR(AVERAGE(C25:G25),0)) -> -18.4 | I25: =IF(I$3="",0,IFERROR(AVERAGE(D25:H25),0)) -> -16.08 | J25: =IF(J$3="",0,IFERROR(AVERAGE(E25:I25),0)) -> -15.696 | K25: =IF(K$3="",0,IFERROR(AVERAGE(F25:J25),0)) -> -14.4352 | L25: =IF(L$3="",0,IFERROR(AVERAGE(G25:K25),0)) -> -16.12224 | M25: =IF(M$3="",0,IFERROR(AVERAGE(H25:L25),0)) -> 0 | N25: =IF(N$3="",0,IFERROR(AVERAGE(I25:M25),0)) -> 0 | O25: =IF(O$3="",0,IFERROR(AVERAGE(J25:N25),0)) -> 0 | ... Q25: =IF(Q$3="",0,IFERROR(AVERAGE(L25:P25),0)) -> 0
B26: =Assumptions!B258 -> Net Cash from Discontinued Operations | C26: =Assumptions!D258 -> 0 | D26: =Assumptions!E258 -> 0 | E26: =Assumptions!F258 -> 0 | F26: =Assumptions!G258 -> 0 | G26: =Assumptions!H258 -> 0 | H26: =IF(H$3="",0,IFERROR(AVERAGE(C26:G26),0)) -> 0 | I26: =IF(I$3="",0,IFERROR(AVERAGE(D26:H26),0)) -> 0 | J26: =IF(J$3="",0,IFERROR(AVERAGE(E26:I26),0)) -> 0 | K26: =IF(K$3="",0,IFERROR(AVERAGE(F26:J26),0)) -> 0 | L26: =IF(L$3="",0,IFERROR(AVERAGE(G26:K26),0)) -> 0 | M26: =IF(M$3="",0,IFERROR(AVERAGE(H26:L26),0)) -> 0 | N26: =IF(N$3="",0,IFERROR(AVERAGE(I26:M26),0)) -> 0 | O26: =IF(O$3="",0,IFERROR(AVERAGE(J26:N26),0)) -> 0 | ... Q26: =IF(Q$3="",0,IFERROR(AVERAGE(L26:P26),0)) -> 0
B27: Cash from Financing Activities | C27: =SUM(C22:C26) -> 1171 | D27: =SUM(D22:D26) -> -1468 | E27: =SUM(E22:E26) -> -2731 | F27: =SUM(F22:F26) -> -2323 | G27: =SUM(G22:G26) -> 88 | H27: =SUM(H22:H26) -> -402.7318 | I27: =SUM(I22:I26) -> -831.14248 | J27: =SUM(J22:J26) -> -830.37808 | ... Q27: =SUM(Q22:Q26) -> 0
B29: =Assumptions!B261 -> Effect of Foreign Exchange Rates | C29: =+Assumptions!D261 -> -6 | D29: =+Assumptions!E261 -> -1 | E29: =+Assumptions!F261 -> 4 | F29: =+Assumptions!G261 -> -35 | G29: =+Assumptions!H261 -> 1 | H29: =IF(H$3="",0,IFERROR(AVERAGE(C29:G29),0)) -> -7.4 | I29: =IF(I$3="",0,IFERROR(AVERAGE(D29:H29),0)) -> -7.68 | J29: =IF(J$3="",0,IFERROR(AVERAGE(E29:I29),0)) -> -9.016 | K29: =IF(K$3="",0,IFERROR(AVERAGE(F29:J29),0)) -> -11.6192 | L29: =IF(L$3="",0,IFERROR(AVERAGE(G29:K29),0)) -> -6.94304 | M29: =IF(M$3="",0,IFERROR(AVERAGE(H29:L29),0)) -> 0 | N29: =IF(N$3="",0,IFERROR(AVERAGE(I29:M29),0)) -> 0 | O29: =IF(O$3="",0,IFERROR(AVERAGE(J29:N29),0)) -> 0 | ... Q29: =IF(Q$3="",0,IFERROR(AVERAGE(L29:P29),0)) -> 0
B31: Net Change in Cash | C31: =SUM(C10,C18,C27,C29) -> 47 | D31: =SUM(D10,D18,D27,D29) -> -123 | E31: =SUM(E10,E18,E27,E29) -> 2164 | F31: =SUM(F10,F18,F27,F29) -> -2198 | G31: =SUM(G10,G18,G27,G29) -> -174 | H31: =SUM(H10,H18,H27,H29) -> 928.13584 | I31: =SUM(I10,I18,I27,I29) -> 959.71427 | J31: =SUM(J10,J18,J27,J29) -> 1018.7606 | ... Q31: =SUM(Q10,Q18,Q27,Q29) -> 0
B33: Cash Balance
B34: =+Assumptions!B264 -> Opening Cash | C34: =+Assumptions!C265+C31 -> 317 | D34: =+C36 -> 317 | E34: =+D36 -> 148 | F34: =+E36 -> 2228 | G34: =+F36 -> 160 | H34: =IF(H$3="",0,+G36) -> -14 | I34: =IF(I$3="",0,+H36) -> 914.13584 | J34: =IF(J$3="",0,+I36) -> 1873.8501 | K34: =IF(K$3="",0,+J36) -> 2892.6107 | L34: =IF(L$3="",0,+K36) -> 3573.127 | M34: =IF(M$3="",0,+L36) -> 0 | N34: =IF(N$3="",0,+M36) -> 0 | O34: =IF(O$3="",0,+N36) -> 0 | ... Q34: =IF(Q$3="",0,+P36) -> 0
B35: =Assumptions!B267 -> Restricted Cash | C35: =+Assumptions!D269 -> 0 | D35: =+Assumptions!E269 -> 46 | E35: =+Assumptions!F269 -> 84 | F35: =+Assumptions!G269 -> -130 | G35: =+Assumptions!H269 -> 0 | H35: =IF(H$3="",0,+Assumptions!I269) -> 0 | I35: =IF(I$3="",0,+Assumptions!J269) -> 0 | J35: =IF(J$3="",0,+Assumptions!K269) -> 0 | K35: =IF(K$3="",0,+Assumptions!L269) -> 0 | L35: =IF(L$3="",0,+Assumptions!M269) -> 0 | M35: =IF(M$3="",0,+Assumptions!N269) -> 0 | N35: =IF(N$3="",0,+Assumptions!O269) -> 0 | O35: =IF(O$3="",0,+Assumptions!P269) -> 0 | ... Q35: =IF(Q$3="",0,+Assumptions!R269) -> 0
B36: Closing Cash Balance | C36: =+C34-C35 -> 317 | D36: =+D31+D34-D35 -> 148 | E36: =+E31+E34-E35 -> 2228 | F36: =+F31+F34-F35 -> 160 | G36: =+G31+G34-G35 -> -14 | H36: =+H31+H34-H35 -> 914.13584 | I36: =+I31+I34-I35 -> 1873.8501 | J36: =+J31+J34-J35 -> 2892.6107 | K36: =+K31+K34-K35 -> 3573.127 | ... Q36: =+Q31+Q34-Q35 -> 0
B39: Data from Financial Statements
B40: ='Income Statement'!B4 -> Revenue | C40: ='IS Bear'!C4 -> 42405 | D40: ='IS Bear'!D4 -> 43185 | E40: ='IS Bear'!E4 -> 47049 | F40: ='IS Bear'!F4 -> 53282 | G40: ='IS Bear'!G4 -> 52881 | H40: ='IS Bear'!H4 -> 52352.19 | I40: ='IS Bear'!I4 -> 51828.668 | J40: ='IS Bear'!J4 -> 51310.381 | ... Q40: ='IS Bear'!Q4 -> 0
B41: ='Income Statement'!B37 -> Net Income (Loss), GAAP | C41: ='IS Bear'!C37 -> 2022 | D41: ='IS Bear'!D37 -> 2061 | E41: ='IS Bear'!E37 -> 3047 | F41: ='IS Bear'!F37 -> 3238 | G41: ='IS Bear'!G37 -> -648 | H41: ='IS Bear'!H37 -> 2295.3852 | I41: ='IS Bear'!I37 -> 2282.5272 | J41: ='IS Bear'!J37 -> 2256.34 | ... Q41: ='IS Bear'!Q37 -> 0

Sheet CF Bull
B2: Statement of Cash Flows - Base
B3: =Assumptions!$B$132 -> Year Ending 09/31/2024, In USD Millions | C3: {=_xlfn.SEQUENCE(1,5+Assumptions!$C$20,(YEAR('Valuation Summary'!$C$4)-5))} -> 2019 | D3: 2020 | E3: 2021 | F3: 2022 | G3: 2023 | H3: 2024 | I3: 2025 | J3: 2026 | K3: 2027 | L3: 2028
B4: Operating Activities
B5: ='Income Statement'!B37 -> Net Income (Loss), GAAP | C5: ='IS Bull'!C37 -> 2022 | D5: ='IS Bull'!D37 -> 2061 | E5: ='IS Bull'!E37 -> 3047 | F5: ='IS Bull'!F37 -> 3238 | G5: ='IS Bull'!G37 -> -648 | H5: =IF(H$3="",0,'IS Bull'!H37) -> 2399.6325 | I5: =IF(I$3="",0,'IS Bull'!I37) -> 2493.1066 | J5: =IF(J$3="",0,'IS Bull'!J37) -> 2575.4095 | K5: =IF(K$3="",0,'IS Bull'!K37) -> 2651.3941 | L5: =IF(L$3="",0,'IS Bull'!L37) -> 2734.104 | M5: =IF(M$3="",0,'IS Bull'!M37) -> 0 | N5: =IF(N$3="",0,'IS Bull'!N37) -> 0 | O5: =IF(O$3="",0,'IS Bull'!O37) -> 0 | ... Q5: =IF(Q$3="",0,'IS Bull'!Q37) -> 0
B6: ='Income Statement'!B47 -> Depreciation and Amortization | C6: ='IS Bull'!C47 -> 1098 | D6: ='IS Bull'!D47 -> 1192 | E6: ='IS Bull'!E47 -> 1214 | F6: ='IS Bull'!F47 -> 1202 | G6: ='IS Bull'!G47 -> 1339 | H6: =IF(H$3="",0,'IS Bull'!H47) -> 1419.7807 | I6: =IF(I$3="",0,'IS Bull'!I47) -> 1462.3741 | J6: =IF(J$3="",0,'IS Bull'!J47) -> 1506.2453 | K6: =IF(K$3="",0,'IS Bull'!K47) -> 1551.4327 | L6: =IF(L$3="",0,'IS Bull'!L47) -> 1597.9757 | M6: =IF(M$3="",0,'IS Bull'!M47) -> 0 | N6: =IF(N$3="",0,'IS Bull'!N47) -> 0 | O6: =IF(O$3="",0,'IS Bull'!O47) -> 0 | ... Q6: =IF(Q$3="",0,'IS Bull'!Q47) -> 0
B7: =Assumptions!B206 -> Non-Cash Items | C7: =Assumptions!D206 -> 70 | D7: =Assumptions!E206 -> -66 | E7: =Assumptions!F206 -> -768 | F7: =Assumptions!G206 -> -6 | G7: =Assumptions!H206 -> 996 | H7: =IF(H$3="",0,H40*Assumptions!I208) -> 0 | I7: =IF(I$3="",0,I40*Assumptions!J208) -> 0 | J7: =IF(J$3="",0,J40*Assumptions!K208) -> 0 | K7: =IF(K$3="",0,K40*Assumptions!L208) -> 0 | L7: =IF(L$3="",0,L40*Assumptions!M208) -> 0 | M7: =IF(M$3="",0,M40*Assumptions!N208) -> 0 | N7: =IF(N$3="",0,N40*Assumptions!O208) -> 0 | O7: =IF(O$3="",0,O40*Assumptions!P208) -> 0 | ... Q7: =IF(Q$3="",0,Q40*Assumptions!R208) -> 0
B8: =Assumptions!B213 -> Change in Non-Cash Working Capital | C8: =Assumptions!D213 -> -846 | D8: =Assumptions!E213 -> 580 | E8: =Assumptions!F213 -> 381 | F8: =Assumptions!G213 -> -2104 | G8: =Assumptions!H213 -> 187 | H8: =IF(H$3="",0,IFERROR(AVERAGE(C8:G8),0)) -> -360.4 | I8: =IF(I$3="",0,IFERROR(AVERAGE(D8:H8),0)) -> -263.28 | J8: =IF(J$3="",0,IFERROR(AVERAGE(E8:I8),0)) -> -431.936 | K8: =IF(K$3="",0,IFERROR(AVERAGE(F8:J8),0)) -> -594.5232 | L8: =IF(L$3="",0,IFERROR(AVERAGE(G8:K8),0)) -> -292.62784 | M8: =IF(M$3="",0,IFERROR(AVERAGE(H8:L8),0)) -> 0 | N8: =IF(N$3="",0,IFERROR(AVERAGE(I8:M8),0)) -> 0 | O8: =IF(O$3="",0,IFERROR(AVERAGE(J8:N8),0)) -> 0 | ... Q8: =IF(Q$3="",0,IFERROR(AVERAGE(L8:P8),0)) -> 0
B9: =Assumptions!B224 -> Net Cash from Discontinued Operations | C9: =Assumptions!D224 -> 0 | D9: =Assumptions!E224 -> 0 | E9: =Assumptions!F224 -> 0 | F9: =Assumptions!G224 -> 0 | G9: =Assumptions!H224 -> 0 | H9: =IF(H$3="",0,Assumptions!I224) -> 0 | I9: =IF(I$3="",0,Assumptions!J224) -> 0 | J9: =IF(J$3="",0,Assumptions!K224) -> 0 | K9: =IF(K$3="",0,Assumptions!L224) -> 0 | L9: =IF(L$3="",0,Assumptions!M224) -> 0 | M9: =IF(M$3="",0,Assumptions!N224) -> 0 | N9: =IF(N$3="",0,Assumptions!O224) -> 0 | O9: =IF(O$3="",0,Assumptions!P224) -> 0 | ... Q9: =IF(Q$3="",0,Assumptions!R224) -> 0
B10: Cash from Operating Activities | C10: =SUM(C5:C9) -> 2344 | D10: =SUM(D5:D9) -> 3767 | E10: =SUM(E5:E9) -> 3874 | F10: =SUM(F5:F9) -> 2330 | G10: =SUM(G5:G9) -> 1874 | H10: =SUM(H5:H9) -> 3459.0132 | I10: =SUM(I5:I9) -> 3692.2007 | J10: =SUM(J5:J9) -> 3649.7188 | ... Q10: =SUM(Q5:Q9) -> 0
B12: Investing Activities
B13: Change in Fixed Assets and Intangibles | C13: =-'IS Bull'!C44+Assumptions!D229 -> -1259 | D13: =-'IS Bull'!D44+Assumptions!E229 -> -1199 | E13: =-'IS Bull'!E44+Assumptions!F229 -> -1209 | F13: =-'IS Bull'!F44+Assumptions!G229 -> -1887 | G13: =-'IS Bull'!G44+Assumptions!H229 -> -1939 | H13: =IF(H$3="",0,-'IS Bull'!H44+('BS Bull'!H12*Assumptions!I230)) -> -1691.0323 | I13: =IF(I$3="",0,-'IS Bull'!I44+('BS Bull'!I12*Assumptions!J230)) -> -1741.7633 | J13: =IF(J$3="",0,-'IS Bull'!J44+('BS Bull'!J12*Assumptions!K230)) -> -1794.0162 | K13: =IF(K$3="",0,-'IS Bull'!K44+('BS Bull'!K12*Assumptions!L230)) -> -1847.8367 | L13: =IF(L$3="",0,-'IS Bull'!L44+('BS Bull'!L12*Assumptions!M230)) -> -1903.2718 | M13: =IF(M$3="",0,-'IS Bull'!M44+('BS Bull'!M12*Assumptions!N230)) -> 0 | N13: =IF(N$3="",0,-'IS Bull'!N44+('BS Bull'!N12*Assumptions!O230)) -> 0 | O13: =IF(O$3="",0,-'IS Bull'!O44+('BS Bull'!O12*Assumptions!P230)) -> 0 | ... Q13: =IF(Q$3="",0,-'IS Bull'!Q44+('BS Bull'!Q12*Assumptions!R230)) -> 0
B14: Net Change in Long-Term Investments | C14: =Assumptions!D233 -> 0 | D14: =Assumptions!E233 -> 0 | E14: =Assumptions!F233 -> 0 | F14: =Assumptions!G233 -> 0 | G14: =Assumptions!H233 -> 0 | H14: =IF(H$3="",0,IFERROR(AVERAGE(C14:G14),0)) -> 0 | I14: =IF(I$3="",0,IFERROR(AVERAGE(D14:H14),0)) -> 0 | J14: =IF(J$3="",0,IFERROR(AVERAGE(E14:I14),0)) -> 0 | K14: =IF(K$3="",0,IFERROR(AVERAGE(F14:J14),0)) -> 0 | L14: =IF(L$3="",0,IFERROR(AVERAGE(G14:K14),0)) -> 0 | M14: =IF(M$3="",0,IFERROR(AVERAGE(H14:L14),0)) -> 0 | N14: =IF(N$3="",0,IFERROR(AVERAGE(I14:M14),0)) -> 0 | O14: =IF(O$3="",0,IFERROR(AVERAGE(J14:N14),0)) -> 0 | ... Q14: =IF(Q$3="",0,IFERROR(AVERAGE(L14:P14),0)) -> 0
B15: Net Cash from Acquistions and Divestitures | C15: =Assumptions!D236 -> -2292 | D15: =Assumptions!E236 -> -154 | E15: =Assumptions!F236 -> 1144 | F15: =Assumptions!G236 -> -177 | G15: =Assumptions!H236 -> -262 | H15: =IF(H$3="",0,IFERROR(AVERAGE(C15:G15),0)) -> -348.2 | I15: =IF(I$3="",0,IFERROR(AVERAGE(D15:H15),0)) -> 40.56 | J15: =IF(J$3="",0,IFERROR(AVERAGE(E15:I15),0)) -> 79.472 | K15: =IF(K$3="",0,IFERROR(AVERAGE(F15:J15),0)) -> -133.4336 | L15: =IF(L$3="",0,IFERROR(AVERAGE(G15:K15),0)) -> -124.72032 | M15: =IF(M$3="",0,IFERROR(AVERAGE(H15:L15),0)) -> 0 | N15: =IF(N$3="",0,IFERROR(AVERAGE(I15:M15),0)) -> 0 | O15: =IF(O$3="",0,IFERROR(AVERAGE(J15:N15),0)) -> 0 | ... Q15: =IF(Q$3="",0,IFERROR(AVERAGE(L15:P15),0)) -> 0
B16: Other Investing Actvities | C16: =Assumptions!D239 -> 89 | D16: =Assumptions!E239 -> -1068 | E16: =Assumptions!F239 -> 1082 | F16: =Assumptions!G239 -> -106 | G16: =Assumptions!H239 -> 64 | H16: =IF(H$3="",0,IFERROR(AVERAGE(C16:G16),0)) -> 12.2 | I16: =IF(I$3="",0,IFERROR(AVERAGE(D16:H16),0)) -> -3.16 | J16: =IF(J$3="",0,IFERROR(AVERAGE(E16:I16),0)) -> 209.808 | K16: =IF(K$3="",0,IFERROR(AVERAGE(F16:J16),0)) -> 35.3696 | L16: =IF(L$3="",0,IFERROR(AVERAGE(G16:K16),0)) -> 63.64352 | M16: =IF(M$3="",0,IFERROR(AVERAGE(H16:L16),0)) -> 0 | N16: =IF(N$3="",0,IFERROR(AVERAGE(I16:M16),0)) -> 0 | O16: =IF(O$3="",0,IFERROR(AVERAGE(J16:N16),0)) -> 0 | ... Q16: =IF(Q$3="",0,IFERROR(AVERAGE(L16:P16),0)) -> 0
B17: Net Cash from Discontinued Operations | C17: =Assumptions!D242 -> 0 | D17: =Assumptions!E242 -> 0 | E17: =Assumptions!F242 -> 0 | F17: =Assumptions!G242 -> 0 | G17: =Assumptions!H242 -> 0 | H17: =IF(H$3="",0,IFERROR(AVERAGE(C17:G17),0)) -> 0 | I17: =IF(I$3="",0,IFERROR(AVERAGE(D17:H17),0)) -> 0 | J17: =IF(J$3="",0,IFERROR(AVERAGE(E17:I17),0)) -> 0 | K17: =IF(K$3="",0,IFERROR(AVERAGE(F17:J17),0)) -> 0 | L17: =IF(L$3="",0,IFERROR(AVERAGE(G17:K17),0)) -> 0 | M17: =IF(M$3="",0,IFERROR(AVERAGE(H17:L17),0)) -> 0 | N17: =IF(N$3="",0,IFERROR(AVERAGE(I17:M17),0)) -> 0 | O17: =IF(O$3="",0,IFERROR(AVERAGE(J17:N17),0)) -> 0 | ... Q17: =IF(Q$3="",0,IFERROR(AVERAGE(L17:P17),0)) -> 0
B18: Cash from Investing Activities | C18: =SUM(C13:C17) -> -3462 | D18: =SUM(D13:D17) -> -2421 | E18: =SUM(E13:E17) -> 1017 | F18: =SUM(F13:F17) -> -2170 | G18: =SUM(G13:G17) -> -2137 | H18: =SUM(H13:H17) -> -2027.0323 | I18: =SUM(I13:I17) -> -1704.3633 | J18: =SUM(J13:J17) -> -1504.7362 | ... Q18: =SUM(Q13:Q17) -> 0
B21: Financing Activities
B22: =Assumptions!B245 -> Dividends Paid | C22: =Assumptions!D245 -> -537 | D22: =Assumptions!E245 -> -601 | E22: =Assumptions!F245 -> -636 | F22: =Assumptions!G245 -> -653 | G22: =Assumptions!H245 -> -670 | H22: =IF(H$3="",0,H41*Assumptions!I246) -> 31.85194 | I22: =IF(I$3="",0,I41*Assumptions!J246) -> 33.092685 | J22: =IF(J$3="",0,J41*Assumptions!K246) -> 34.185147 | K22: =IF(K$3="",0,K41*Assumptions!L246) -> 35.193741 | L22: =IF(L$3="",0,L41*Assumptions!M246) -> 36.291606 | M22: =IF(M$3="",0,M41*Assumptions!N246) -> 0 | N22: =IF(N$3="",0,N41*Assumptions!O246) -> 0 | O22: =IF(O$3="",0,O41*Assumptions!P246) -> 0 | ... Q22: =IF(Q$3="",0,Q41*Assumptions!R246) -> 0
B23: =Assumptions!B249 -> Net Cash from (Repayment) Debt | C23: =Assumptions!D249 -> 1891 | D23: =Assumptions!E249 -> -672 | E23: =Assumptions!F249 -> -2047 | F23: =Assumptions!G249 -> -1088 | G23: =Assumptions!H249 -> 1117 | H23: =IF(H$3="",0,IFERROR(AVERAGE(C23:G23),0)) -> -159.8 | I23: =IF(I$3="",0,IFERROR(AVERAGE(D23:H23),0)) -> -569.96 | J23: =IF(J$3="",0,IFERROR(AVERAGE(E23:I23),0)) -> -549.552 | K23: =IF(K$3="",0,IFERROR(AVERAGE(F23:J23),0)) -> -250.0624 | L23: =IF(L$3="",0,IFERROR(AVERAGE(G23:K23),0)) -> -82.47488 | M23: =IF(M$3="",0,IFERROR(AVERAGE(H23:L23),0)) -> 0 | N23: =IF(N$3="",0,IFERROR(AVERAGE(I23:M23),0)) -> 0 | O23: =IF(O$3="",0,IFERROR(AVERAGE(J23:N23),0)) -> 0 | ... Q23: =IF(Q$3="",0,IFERROR(AVERAGE(L23:P23),0)) -> 0
B24: =Assumptions!B252 -> Cash (Repurchase) of Equity | C24: =Assumptions!D252 -> -153 | D24: =Assumptions!E252 -> -177 | E24: =Assumptions!F252 -> -26 | F24: =Assumptions!G252 -> -576 | G24: =Assumptions!H252 -> -343 | H24: =IF(H$3="",0,IFERROR(AVERAGE(C24:G24),0)) -> -255 | I24: =IF(I$3="",0,IFERROR(AVERAGE(D24:H24),0)) -> -275.4 | J24: =IF(J$3="",0,IFERROR(AVERAGE(E24:I24),0)) -> -295.08 | K24: =IF(K$3="",0,IFERROR(AVERAGE(F24:J24),0)) -> -348.896 | L24: =IF(L$3="",0,IFERROR(AVERAGE(G24:K24),0)) -> -303.4752 | M24: =IF(M$3="",0,IFERROR(AVERAGE(H24:L24),0)) -> 0 | N24: =IF(N$3="",0,IFERROR(AVERAGE(I24:M24),0)) -> 0 | O24: =IF(O$3="",0,IFERROR(AVERAGE(J24:N24),0)) -> 0 | ... Q24: =IF(Q$3="",0,IFERROR(AVERAGE(L24:P24),0)) -> 0
B25: =Assumptions!B255 -> Other Financing Activities | C25: =Assumptions!D255 -> -30 | D25: =Assumptions!E255 -> -18 | E25: =Assumptions!F255 -> -22 | F25: =Assumptions!G255 -> -6 | G25: =Assumptions!H255 -> -16 | H25: =IF(H$3="",0,IFERROR(AVERAGE(C25:G25),0)) -> -18.4 | I25: =IF(I$3="",0,IFERROR(AVERAGE(D25:H25),0)) -> -16.08 | J25: =IF(J$3="",0,IFERROR(AVERAGE(E25:I25),0)) -> -15.696 | K25: =IF(K$3="",0,IFERROR(AVERAGE(F25:J25),0)) -> -14.4352 | L25: =IF(L$3="",0,IFERROR(AVERAGE(G25:K25),0)) -> -16.12224 | M25: =IF(M$3="",0,IFERROR(AVERAGE(H25:L25),0)) -> 0 | N25: =IF(N$3="",0,IFERROR(AVERAGE(I25:M25),0)) -> 0 | O25: =IF(O$3="",0,IFERROR(AVERAGE(J25:N25),0)) -> 0 | ... Q25: =IF(Q$3="",0,IFERROR(AVERAGE(L25:P25),0)) -> 0
B26: =Assumptions!B258 -> Net Cash from Discontinued Operations | C26: =Assumptions!D258 -> 0 | D26: =Assumptions!E258 -> 0 | E26: =Assumptions!F258 -> 0 | F26: =Assumptions!G258 -> 0 | G26: =Assumptions!H258 -> 0 | H26: =IF(H$3="",0,IFERROR(AVERAGE(C26:G26),0)) -> 0 | I26: =IF(I$3="",0,IFERROR(AVERAGE(D26:H26),0)) -> 0 | J26: =IF(J$3="",0,IFERROR(AVERAGE(E26:I26),0)) -> 0 | K26: =IF(K$3="",0,IFERROR(AVERAGE(F26:J26),0)) -> 0 | L26: =IF(L$3="",0,IFERROR(AVERAGE(G26:K26),0)) -> 0 | M26: =IF(M$3="",0,IFERROR(AVERAGE(H26:L26),0)) -> 0 | N26: =IF(N$3="",0,IFERROR(AVERAGE(I26:M26),0)) -> 0 | O26: =IF(O$3="",0,IFERROR(AVERAGE(J26:N26),0)) -> 0 | ... Q26: =IF(Q$3="",0,IFERROR(AVERAGE(L26:P26),0)) -> 0
B27: Cash from Financing Activities | C27: =SUM(C22:C26) -> 1171 | D27: =SUM(D22:D26) -> -1468 | E27: =SUM(E22:E26) -> -2731 | F27: =SUM(F22:F26) -> -2323 | G27: =SUM(G22:G26) -> 88 | H27: =SUM(H22:H26) -> -401.34806 | I27: =SUM(I22:I26) -> -828.34732 | J27: =SUM(J22:J26) -> -826.14285 | ... Q27: =SUM(Q22:Q26) -> 0
B29: =Assumptions!B261 -> Effect of Foreign Exchange Rates | C29: =+Assumptions!D261 -> -6 | D29: =+Assumptions!E261 -> -1 | E29: =+Assumptions!F261 -> 4 | F29: =+Assumptions!G261 -> -35 | G29: =+Assumptions!H261 -> 1 | H29: =IF(H$3="",0,IFERROR(AVERAGE(C29:G29),0)) -> -7.4 | I29: =IF(I$3="",0,IFERROR(AVERAGE(D29:H29),0)) -> -7.68 | J29: =IF(J$3="",0,IFERROR(AVERAGE(E29:I29),0)) -> -9.016 | K29: =IF(K$3="",0,IFERROR(AVERAGE(F29:J29),0)) -> -11.6192 | L29: =IF(L$3="",0,IFERROR(AVERAGE(G29:K29),0)) -> -6.94304 | M29: =IF(M$3="",0,IFERROR(AVERAGE(H29:L29),0)) -> 0 | N29: =IF(N$3="",0,IFERROR(AVERAGE(I29:M29),0)) -> 0 | O29: =IF(O$3="",0,IFERROR(AVERAGE(J29:N29),0)) -> 0 | ... Q29: =IF(Q$3="",0,IFERROR(AVERAGE(L29:P29),0)) -> 0
B31: Net Change in Cash | C31: =SUM(C10,C18,C27,C29) -> 47 | D31: =SUM(D10,D18,D27,D29) -> -123 | E31: =SUM(E10,E18,E27,E29) -> 2164 | F31: =SUM(F10,F18,F27,F29) -> -2198 | G31: =SUM(G10,G18,G27,G29) -> -174 | H31: =SUM(H10,H18,H27,H29) -> 1023.2328 | I31: =SUM(I10,I18,I27,I29) -> 1151.8101 | J31: =SUM(J10,J18,J27,J29) -> 1309.8238 | ... Q31: =SUM(Q10,Q18,Q27,Q29) -> 0
B33: Cash Balance
B34: =+Assumptions!B264 -> Opening Cash | C34: =+Assumptions!C265+C31 -> 317 | D34: =+C36 -> 317 | E34: =+D36 -> 148 | F34: =+E36 -> 2228 | G34: =+F36 -> 160 | H34: =IF(H$3="",0,+G36) -> -14 | I34: =IF(I$3="",0,+H36) -> 1009.2328 | J34: =IF(J$3="",0,+I36) -> 2161.0429 | K34: =IF(K$3="",0,+J36) -> 3470.8666 | L34: =IF(L$3="",0,+K36) -> 4543.4505 | M34: =IF(M$3="",0,+L36) -> 0 | N34: =IF(N$3="",0,+M36) -> 0 | O34: =IF(O$3="",0,+N36) -> 0 | ... Q34: =IF(Q$3="",0,+P36) -> 0
B35: =Assumptions!B267 -> Restricted Cash | C35: =+Assumptions!D269 -> 0 | D35: =+Assumptions!E269 -> 46 | E35: =+Assumptions!F269 -> 84 | F35: =+Assumptions!G269 -> -130 | G35: =+Assumptions!H269 -> 0 | H35: =IF(H$3="",0,+Assumptions!I269) -> 0 | I35: =IF(I$3="",0,+Assumptions!J269) -> 0 | J35: =IF(J$3="",0,+Assumptions!K269) -> 0 | K35: =IF(K$3="",0,+Assumptions!L269) -> 0 | L35: =IF(L$3="",0,+Assumptions!M269) -> 0 | M35: =IF(M$3="",0,+Assumptions!N269) -> 0 | N35: =IF(N$3="",0,+Assumptions!O269) -> 0 | O35: =IF(O$3="",0,+Assumptions!P269) -> 0 | ... Q35: =IF(Q$3="",0,+Assumptions!R269) -> 0
B36: Closing Cash Balance | C36: =+C34-C35 -> 317 | D36: =+D31+D34-D35 -> 148 | E36: =+E31+E34-E35 -> 2228 | F36: =+F31+F34-F35 -> 160 | G36: =+G31+G34-G35 -> -14 | H36: =+H31+H34-H35 -> 1009.2328 | I36: =+I31+I34-I35 -> 2161.0429 | J36: =+J31+J34-J35 -> 3470.8666 | K36: =+K31+K34-K35 -> 4543.4505 | ... Q36: =+Q31+Q34-Q35 -> 0
B39: Data from Financial Statements
B40: ='Income Statement'!B4 -> Revenue | C40: ='IS Bull'!C4 -> 42405 | D40: ='IS Bull'!D4 -> 43185 | E40: ='IS Bull'!E4 -> 47049 | F40: ='IS Bull'!F4 -> 53282 | G40: ='IS Bull'!G4 -> 52881 | H40: ='IS Bull'!H4 -> 54467.43 | I40: ='IS Bull'!I4 -> 56101.453 | J40: ='IS Bull'!J4 -> 57784.496 | ... Q40: ='IS Bull'!Q4 -> 0
B41: ='Income Statement'!B37 -> Net Income (Loss), GAAP | C41: ='IS Bull'!C37 -> 2022 | D41: ='IS Bull'!D37 -> 2061 | E41: ='IS Bull'!E37 -> 3047 | F41: ='IS Bull'!F37 -> 3238 | G41: ='IS Bull'!G37 -> -648 | H41: ='IS Bull'!H37 -> 2399.6325 | I41: ='IS Bull'!I37 -> 2493.1066 | J41: ='IS Bull'!J37 -> 2575.4095 | ... Q41: ='IS Bull'!Q37 -> 0

Sheet Balance Sheet
B2: Balance Sheet - Base
B3: =Assumptions!$B$132 -> Year Ending 09/31/2024, In USD Millions | C3: {=_xlfn.SEQUENCE(1,5+Assumptions!$C$20,(YEAR('Valuation Summary'!$C$4)-5))} -> 2019 | D3: 2020 | E3: 2021 | F3: 2022 | G3: 2023 | H3: 2024 | I3: 2025 | J3: 2026 | K3: 2027 | L3: 2028
B4: Assets
B5: Current Assets
B6: =Assumptions!B279 -> Cash, Cash Equivalents, and Short-Term Investments | C6: =+Assumptions!D280+'Cash Flows'!C36+167 -> 484 | D6: =+Assumptions!E280+'Cash Flows'!D36+1272 -> 1420 | E6: =+Assumptions!F280+'Cash Flows'!E36+279 -> 2507 | F6: =+Assumptions!G280+'Cash Flows'!F36+871 -> 1031 | G6: =+Assumptions!H280+'Cash Flows'!G36+587 -> 573 | H6: =IF(H$3="",0,'Cash Flows'!H36+'Income Statement'!H4*Assumptions!I$281) -> 961.68431 | I6: =IF(I$3="",0,'Cash Flows'!I36+'Income Statement'!I4*Assumptions!J$281) -> 2016.4955 | J6: =IF(J$3="",0,'Cash Flows'!J36+'Income Statement'!J4*Assumptions!K$281) -> 3177.9063 | K6: =IF(K$3="",0,'Cash Flows'!K36+'Income Statement'!K4*Assumptions!L$281) -> 4048.6354 | L6: =IF(L$3="",0,'Cash Flows'!L36+'Income Statement'!L4*Assumptions!M$281) -> 5493.6255 | M6: =IF(M$3="",0,'Cash Flows'!M36+'Income Statement'!M4*Assumptions!N$281) -> 0 | N6: =IF(N$3="",0,'Cash Flows'!N36+'Income Statement'!N4*Assumptions!O$281) -> 0 | O6: =IF(O$3="",0,'Cash Flows'!O36+'Income Statement'!O4*Assumptions!P$281) -> 0 | ... Q6: =IF(Q$3="",0,'Cash Flows'!Q36+'Income Statement'!Q4*Assumptions!R$281) -> 0
B7: =Assumptions!B284 -> Accounts and Notes Receivable | C7: =Assumptions!D284 -> 2173 | D7: =Assumptions!E284 -> 1952 | E7: =Assumptions!F284 -> 2400 | F7: =Assumptions!G284 -> 2577 | G7: =Assumptions!H284 -> 2476 | H7: =IF(H$3="",0,G7*(1+Assumptions!I$137)) -> 2500.76 | I7: =IF(I$3="",0,H7*(1+Assumptions!J$137)) -> 2525.7676 | J7: =IF(J$3="",0,I7*(1+Assumptions!K$137)) -> 2551.0253 | K7: =IF(K$3="",0,J7*(1+Assumptions!L$137)) -> 2576.5355 | L7: =IF(L$3="",0,K7*(1+Assumptions!M$137)) -> 2602.3009 | M7: =IF(M$3="",0,L7*(1+Assumptions!N$137)) -> 0 | N7: =IF(N$3="",0,M7*(1+Assumptions!O$137)) -> 0 | O7: =IF(O$3="",0,N7*(1+Assumptions!P$137)) -> 0 | ... Q7: =IF(Q$3="",0,P7*(1+Assumptions!R$137)) -> 0
B8: =Assumptions!B290 -> Inventory | C8: =Assumptions!D290 -> 4108 | D8: =Assumptions!E290 -> 3859 | E8: =Assumptions!F290 -> 4382 | F8: =Assumptions!G290 -> 5514 | G8: =Assumptions!H290 -> 5328 | H8: =IF(H$3="",0,+G8*(1+'Income Statement'!H$10)) -> 5032.5035 | I8: =IF(I$3="",0,+H8*(1+'Income Statement'!I$10)) -> 5082.8285 | J8: =IF(J$3="",0,+I8*(1+'Income Statement'!J$10)) -> 5133.6568 | K8: =IF(K$3="",0,+J8*(1+'Income Statement'!K$10)) -> 5184.9934 | L8: =IF(L$3="",0,+K8*(1+'Income Statement'!L$10)) -> 5236.8433 | M8: =IF(M$3="",0,+L8*(1+'Income Statement'!M$10)) -> 0 | N8: =IF(N$3="",0,+M8*(1+'Income Statement'!N$10)) -> 0 | O8: =IF(O$3="",0,+N8*(1+'Income Statement'!O$10)) -> 0 | ... Q8: =IF(Q$3="",0,+P8*(1+'Income Statement'!Q$10)) -> 0
B9: =Assumptions!B293 -> Other Short-Term Assets | C9: =Assumptions!D293 -> 404 | D9: =Assumptions!E293 -> 367 | E9: =Assumptions!F293 -> 533 | F9: =Assumptions!G293 -> 508 | G9: =Assumptions!H293 -> 345 | H9: =IF(H$3="",0,G9*(1+Assumptions!I$137)) -> 348.45 | I9: =IF(I$3="",0,H9*(1+Assumptions!J$137)) -> 351.9345 | J9: =IF(J$3="",0,I9*(1+Assumptions!K$137)) -> 355.45385 | K9: =IF(K$3="",0,J9*(1+Assumptions!L$137)) -> 359.00838 | L9: =IF(L$3="",0,K9*(1+Assumptions!M$137)) -> 362.59847 | M9: =IF(M$3="",0,L9*(1+Assumptions!N$137)) -> 0 | N9: =IF(N$3="",0,M9*(1+Assumptions!O$137)) -> 0 | O9: =IF(O$3="",0,N9*(1+Assumptions!P$137)) -> 0 | ... Q9: =IF(Q$3="",0,P9*(1+Assumptions!R$137)) -> 0
B10: ="Total "&B5 -> Total Current Assets | C10: =SUM(C6:C9) -> 7169 | D10: =SUM(D6:D9) -> 7598 | E10: =SUM(E6:E9) -> 9822 | F10: =SUM(F6:F9) -> 9630 | G10: =SUM(G6:G9) -> 8722 | H10: =SUM(H6:H9) -> 8843.3978 | I10: =SUM(I6:I9) -> 9977.0261 | J10: =SUM(J6:J9) -> 11218.042 | ... Q10: =SUM(Q6:Q9) -> 0
B11: Non-Current Assets
B12: =Assumptions!B296 -> Property, Plant, and Equipment | C12: =Assumptions!D296 -> 7282 | D12: =Assumptions!E296 -> 8128 | E12: =Assumptions!F296 -> 8368 | F12: =Assumptions!G296 -> 9192 | G12: =Assumptions!H296 -> 10178 | H12: =IF(H$3="",0,G12+H54-H55) -> 10443.985 | I12: =IF(I$3="",0,H12+I54-I55) -> 10712.629 | J12: =IF(J$3="",0,I12+J54-J55) -> 10983.96 | K12: =IF(K$3="",0,J12+K54-K55) -> 11258.004 | L12: =IF(L$3="",0,K12+L54-L55) -> 11534.789 | M12: =IF(M$3="",0,L12+M54-M55) -> 0 | N12: =IF(N$3="",0,M12+N54-N55) -> 0 | O12: =IF(O$3="",0,N12+O54-O55) -> 0 | ... Q12: =IF(Q$3="",0,P12+Q54-Q55) -> 0
B13: =Assumptions!B299 -> Long-Term Investments and Receivables | C13: =Assumptions!D299 -> 0 | D13: =Assumptions!E299 -> 0 | E13: =Assumptions!F299 -> 0 | F13: =Assumptions!G299 -> 0 | G13: =Assumptions!H299 -> 0 | H13: =IF(H$3="",0,G13) -> 0 | I13: =IF(I$3="",0,H13) -> 0 | J13: =IF(J$3="",0,I13) -> 0 | K13: =IF(K$3="",0,J13) -> 0 | L13: =IF(L$3="",0,K13) -> 0 | M13: =IF(M$3="",0,L13) -> 0 | N13: =IF(N$3="",0,M13) -> 0 | O13: =IF(O$3="",0,N13) -> 0 | ... Q13: =IF(Q$3="",0,P13) -> 0
B14: =Assumptions!B302 -> Other Long-Term Assets | C14: =Assumptions!D302 -> 18646 | D14: =Assumptions!E302 -> 18730 | E14: =Assumptions!F302 -> 18119 | F14: =Assumptions!G302 -> 17999 | G14: =Assumptions!H302 -> 17351 | H14: =IF(H$3="",0,G14) -> 17351 | I14: =IF(I$3="",0,H14) -> 17351 | J14: =IF(J$3="",0,I14) -> 17351 | K14: =IF(K$3="",0,J14) -> 17351 | L14: =IF(L$3="",0,K14) -> 17351 | M14: =IF(M$3="",0,L14) -> 0 | N14: =IF(N$3="",0,M14) -> 0 | O14: =IF(O$3="",0,N14) -> 0 | ... Q14: =IF(Q$3="",0,P14) -> 0
B15: ="Total "&B11 -> Total Non-Current Assets | C15: =SUM(C12:C14) -> 25928 | D15: =SUM(D12:D14) -> 26858 | E15: =SUM(E12:E14) -> 26487 | F15: =SUM(F12:F14) -> 27191 | G15: =SUM(G12:G14) -> 27529 | H15: =IF(H$3="",0,SUM(H12:H14)) -> 27794.985 | I15: =IF(I$3="",0,SUM(I12:I14)) -> 28063.629 | J15: =IF(J$3="",0,SUM(J12:J14)) -> 28334.96 | K15: =IF(K$3="",0,SUM(K12:K14)) -> 28609.004 | L15: =IF(L$3="",0,SUM(L12:L14)) -> 28885.789 | M15: =IF(M$3="",0,SUM(M12:M14)) -> 0 | N15: =IF(N$3="",0,SUM(N12:N14)) -> 0 | O15: =IF(O$3="",0,SUM(O12:O14)) -> 0 | ... Q15: =IF(Q$3="",0,SUM(Q12:Q14)) -> 0
B16: ="Total "&B4 -> Total Assets | C16: =SUM(C10,C15) -> 33097 | D16: =SUM(D10,D15) -> 34456 | E16: =SUM(E10,E15) -> 36309 | F16: =SUM(F10,F15) -> 36821 | G16: =SUM(G10,G15) -> 36251 | H16: =SUM(H10,H15) -> 36638.382 | I16: =SUM(I10,I15) -> 38040.655 | J16: =SUM(J10,J15) -> 39553.002 | ... Q16: =SUM(Q10,Q15) -> 0
B19: Liabilities
B20: Current Liabilities
B21: =Assumptions!B305 -> Payables and Accruals | C21: =Assumptions!D305 -> 1926 | D21: =Assumptions!E305 -> 1876 | E21: =Assumptions!F305 -> 2225 | F21: =Assumptions!G305 -> 2483 | G21: =Assumptions!H305 -> 2594 | H21: =IF(H$3="",0,+G21*(1+'Income Statement'!H$10)) -> 2450.134 | I21: =IF(I$3="",0,+H21*(1+'Income Statement'!I$10)) -> 2474.6354 | J21: =IF(J$3="",0,+I21*(1+'Income Statement'!J$10)) -> 2499.3817 | K21: =IF(K$3="",0,+J21*(1+'Income Statement'!K$10)) -> 2524.3755 | L21: =IF(L$3="",0,+K21*(1+'Income Statement'!L$10)) -> 2549.6193 | M21: =IF(M$3="",0,+L21*(1+'Income Statement'!M$10)) -> 0 | N21: =IF(N$3="",0,+M21*(1+'Income Statement'!N$10)) -> 0 | O21: =IF(O$3="",0,+N21*(1+'Income Statement'!O$10)) -> 0 | ... Q21: =IF(Q$3="",0,+P21*(1+'Income Statement'!Q$10)) -> 0
B22: =Assumptions!B308 -> Short-Term Debt | C22: =Assumptions!D308 -> 2102 | D22: =Assumptions!E308 -> 709 | E22: =Assumptions!F308 -> 1222 | F22: =Assumptions!G308 -> 604 | G22: =Assumptions!H308 -> 2048 | H22: =IF(H$3="",0,(Assumptions!I$162*Assumptions!I$161)+'Cash Flows'!H$23) -> 1036.0567 | I22: =IF(I$3="",0,(Assumptions!J$162*Assumptions!J$161)+'Cash Flows'!I$23) -> 625.89668 | J22: =IF(J$3="",0,(Assumptions!K$162*Assumptions!K$161)+'Cash Flows'!J$23) -> 646.30468 | K22: =IF(K$3="",0,(Assumptions!L$162*Assumptions!L$161)+'Cash Flows'!K$23) -> 945.79428 | L22: =IF(L$3="",0,(Assumptions!M$162*Assumptions!M$161)+'Cash Flows'!L$23) -> 1113.3818 | M22: =IF(M$3="",0,(Assumptions!N$162*Assumptions!N$161)+'Cash Flows'!M$23) -> 0 | N22: =IF(N$3="",0,(Assumptions!O$162*Assumptions!O$161)+'Cash Flows'!N$23) -> 0 | O22: =IF(O$3="",0,(Assumptions!P$162*Assumptions!P$161)+'Cash Flows'!O$23) -> 0 | ... Q22: =IF(Q$3="",0,(Assumptions!R$162*Assumptions!R$161)+'Cash Flows'!Q$23) -> 0
B23: =Assumptions!B311 -> Other Short-Term Liabilities | C23: =Assumptions!D311 -> 1485 | D23: =Assumptions!E311 -> 1649 | E23: =Assumptions!F311 -> 2878 | F23: =Assumptions!G311 -> 2226 | G23: =Assumptions!H311 -> 1857 | H23: =IF(H$3="",0,G23*(1+Assumptions!I137)) -> 1875.57 | I23: =IF(I$3="",0,H23*(1+Assumptions!J137)) -> 1894.3257 | J23: =IF(J$3="",0,I23*(1+Assumptions!K137)) -> 1913.269 | K23: =IF(K$3="",0,J23*(1+Assumptions!L137)) -> 1932.4016 | L23: =IF(L$3="",0,K23*(1+Assumptions!M137)) -> 1951.7257 | M23: =IF(M$3="",0,L23*(1+Assumptions!N137)) -> 0 | N23: =IF(N$3="",0,M23*(1+Assumptions!O137)) -> 0 | O23: =IF(O$3="",0,N23*(1+Assumptions!P137)) -> 0 | ... Q23: =IF(Q$3="",0,P23*(1+Assumptions!R137)) -> 0
B24: ="Total "&B20 -> Total Current Liabilities | C24: =SUM(C21:C23) -> 5513 | D24: =SUM(D21:D23) -> 4234 | E24: =SUM(E21:E23) -> 6325 | F24: =SUM(F21:F23) -> 5313 | G24: =SUM(G21:G23) -> 6499 | H24: =IF(H$3="",0,SUM(H21:H23)) -> 5361.7607 | I24: =IF(I$3="",0,SUM(I21:I23)) -> 4994.8577 | J24: =IF(J$3="",0,SUM(J21:J23)) -> 5058.9554 | K24: =IF(K$3="",0,SUM(K21:K23)) -> 5402.5715 | L24: =IF(L$3="",0,SUM(L21:L23)) -> 5614.7268 | M24: =IF(M$3="",0,SUM(M21:M23)) -> 0 | N24: =IF(N$3="",0,SUM(N21:N23)) -> 0 | O24: =IF(O$3="",0,SUM(O21:O23)) -> 0 | ... Q24: =IF(Q$3="",0,SUM(Q21:Q23)) -> 0
B25: Non-Current Liabilities
B26: =Assumptions!B314 -> Long-Term Debt | C26: =Assumptions!D314 -> 9830 | D26: =Assumptions!E314 -> 11159 | E26: =Assumptions!F314 -> 8649 | F26: =Assumptions!G314 -> 8212 | G26: =Assumptions!H314 -> 7987 | H26: =IF(H$3="",0,G26) -> 7987 | I26: =IF(I$3="",0,H26) -> 7987 | J26: =IF(J$3="",0,I26) -> 7987 | K26: =IF(K$3="",0,J26) -> 7987 | L26: =IF(L$3="",0,K26) -> 7987 | M26: =IF(M$3="",0,L26) -> 0 | N26: =IF(N$3="",0,M26) -> 0 | O26: =IF(O$3="",0,N26) -> 0 | ... Q26: =IF(Q$3="",0,P26) -> 0
B27: =Assumptions!B317 -> Other Long-Term Liabilities | C27: =Assumptions!D317 -> 3528 | D27: =Assumptions!E317 -> 3677 | E27: =Assumptions!F317 -> 3481 | F27: =Assumptions!G317 -> 3485 | G27: =Assumptions!H317 -> 3510 | H27: =IF(H$3="",0,G27) -> 3510 | I27: =IF(I$3="",0,H27) -> 3510 | J27: =IF(J$3="",0,I27) -> 3510 | K27: =IF(K$3="",0,J27) -> 3510 | L27: =IF(L$3="",0,K27) -> 3510 | M27: =IF(M$3="",0,L27) -> 0 | N27: =IF(N$3="",0,M27) -> 0 | O27: =IF(O$3="",0,N27) -> 0 | ... Q27: =IF(Q$3="",0,P27) -> 0
B28: ="Total "&B25 -> Total Non-Current Liabilities | C28: =SUM(C26:C27) -> 13358 | D28: =SUM(D26:D27) -> 14836 | E28: =SUM(E26:E27) -> 12130 | F28: =SUM(F26:F27) -> 11697 | G28: =SUM(G26:G27) -> 11497 | H28: =SUM(H26:H27) -> 11497 | I28: =SUM(I26:I27) -> 11497 | J28: =SUM(J26:J27) -> 11497 | ... Q28: =SUM(Q26:Q27) -> 0
B29: ="Total "&B19 -> Total Liabilities | C29: =SUM(C24,C28) -> 18871 | D29: =SUM(D24,D28) -> 19070 | E29: =SUM(E24,E28) -> 18455 | F29: =SUM(F24,F28) -> 17010 | G29: =SUM(G24,G28) -> 17996 | H29: =SUM(H24,H28) -> 16858.761 | I29: =SUM(I24,I28) -> 16491.858 | J29: =SUM(J24,J28) -> 16555.955 | ... Q29: =SUM(Q24,Q28) -> 0
B32: Equity
B33: =Assumptions!B326 -> Retained Earnings | C33: =Assumptions!D326 -> 13787 | D33: =Assumptions!E326 -> 15100 | E33: =Assumptions!F326 -> 17502 | F33: =Assumptions!G326 -> 20084 | G33: =Assumptions!H326 -> 18760 | H33: =IF(H$3="",0,G33+H56+H57) -> 21138.669 | I33: =IF(I$3="",0,H33+I56+I57) -> 23557.125 | J33: =IF(J$3="",0,I33+J56+J57) -> 26001.866 | K33: =IF(K$3="",0,J33+K56+K57) -> 28464.24 | L33: =IF(L$3="",0,K33+L56+L57) -> 30948.734 | M33: =IF(M$3="",0,L33+M56+M57) -> 0 | N33: =IF(N$3="",0,M33+N56+N57) -> 0 | O33: =IF(O$3="",0,N33+O56+O57) -> 0 | ... Q33: =IF(Q$3="",0,P33+Q56+Q57) -> 0
B34: =Assumptions!B320 -> Preferred and Hybrid Capital | C34: =Assumptions!D320 -> 0 | D34: =Assumptions!E320 -> 0 | E34: =Assumptions!F320 -> 0 | F34: =Assumptions!G320 -> 0 | G34: =Assumptions!H320 -> 0 | H34: =IF(H$3="",0,G34) -> 0 | I34: =IF(I$3="",0,H34) -> 0 | J34: =IF(J$3="",0,I34) -> 0 | K34: =IF(K$3="",0,J34) -> 0 | L34: =IF(L$3="",0,K34) -> 0 | M34: =IF(M$3="",0,L34) -> 0 | N34: =IF(N$3="",0,M34) -> 0 | O34: =IF(O$3="",0,N34) -> 0 | ... Q34: =IF(Q$3="",0,P34) -> 0
B35: =Assumptions!B323 -> Share Capital and Additional Paid in Capital | C35: =Assumptions!D323 -> 4423 | D35: =Assumptions!E323 -> 4478 | E35: =Assumptions!F323 -> 4531 | F35: =Assumptions!G323 -> 4598 | G35: =Assumptions!H323 -> 4605 | H35: =IF(H$3="",0,G35) -> 4605 | I35: =IF(I$3="",0,H35) -> 4605 | J35: =IF(J$3="",0,I35) -> 4605 | K35: =IF(K$3="",0,J35) -> 4605 | L35: =IF(L$3="",0,K35) -> 4605 | M35: =IF(M$3="",0,L35) -> 0 | N35: =IF(N$3="",0,M35) -> 0 | O35: =IF(O$3="",0,N35) -> 0 | ... Q35: =IF(Q$3="",0,P35) -> 0
B36: =Assumptions!B329 -> Other Equity | C36: =Assumptions!D329 -> -117 | D36: =Assumptions!E329 -> -179 | E36: =Assumptions!F329 -> -172 | F36: =Assumptions!G329 -> -297 | G36: =Assumptions!H329 -> -260 | H36: =IF(H$3="",0,G36) -> -260 | I36: =IF(I$3="",0,H36) -> -260 | J36: =IF(J$3="",0,I36) -> -260 | K36: =IF(K$3="",0,J36) -> -260 | L36: =IF(L$3="",0,K36) -> -260 | M36: =IF(M$3="",0,L36) -> 0 | N36: =IF(N$3="",0,M36) -> 0 | O36: =IF(O$3="",0,N36) -> 0 | ... Q36: =IF(Q$3="",0,P36) -> 0
B37: =Assumptions!B332 -> Minority and Non-Controlling Interest | C37: =Assumptions!D332 -> 144 | D37: =Assumptions!E332 -> 132 | E37: =Assumptions!F332 -> 131 | F37: =Assumptions!G332 -> 109 | G37: =Assumptions!H332 -> 122 | H37: =IF(H$3="",0,G37) -> 122 | I37: =IF(I$3="",0,H37) -> 122 | J37: =IF(J$3="",0,I37) -> 122 | K37: =IF(K$3="",0,J37) -> 122 | L37: =IF(L$3="",0,K37) -> 122 | M37: =IF(M$3="",0,L37) -> 0 | N37: =IF(N$3="",0,M37) -> 0 | O37: =IF(O$3="",0,N37) -> 0 | ... Q37: =IF(Q$3="",0,P37) -> 0
B38: =Assumptions!B335 -> Treasury Stock | C38: =Assumptions!D335 -> 4011 | D38: =Assumptions!E335 -> 4145 | E38: =Assumptions!F335 -> 4138 | F38: =Assumptions!G335 -> 4683 | G38: =Assumptions!H335 -> 4972 | H38: =IF(H$3="",0,G38) -> 4972 | I38: =IF(I$3="",0,H38) -> 4972 | J38: =IF(J$3="",0,I38) -> 4972 | K38: =IF(K$3="",0,J38) -> 4972 | L38: =IF(L$3="",0,K38) -> 4972 | M38: =IF(M$3="",0,L38) -> 0 | N38: =IF(N$3="",0,M38) -> 0 | O38: =IF(O$3="",0,N38) -> 0 | ... Q38: =IF(Q$3="",0,P38) -> 0
B39: Balancing Figure
B40: ="Total "&B32 -> Total Equity | C40: =SUM(C33:C37)-C38+C39 -> 14226 | D40: =SUM(D33:D37)-D38+D39 -> 15386 | E40: =SUM(E33:E37)-E38+E39 -> 17854 | F40: =SUM(F33:F37)-F38+F39 -> 19811 | G40: =SUM(G33:G37)-G38+G39 -> 18255 | H40: =SUM(H33:H37)-H38+H39 -> 20633.669 | I40: =SUM(I33:I37)-I38+I39 -> 23052.125 | J40: =SUM(J33:J37)-J38+J39 -> 25496.866 | ... Q40: =SUM(Q33:Q37)-Q38+Q39 -> 0
B42: ="Total "&B19&" and "&B32 -> Total Liabilities and Equity | C42: =C29+C40 -> 33097 | D42: =D29+D40 -> 34456 | E42: =E29+E40 -> 36309 | F42: =F29+F40 -> 36821 | G42: =G29+G40 -> 36251 | H42: =H29+H40 -> 37492.43 | I42: =I29+I40 -> 39543.982 | J42: =J29+J40 -> 42052.822 | ... Q42: =Q29+Q40 -> 0
B43: A = L + E Check, A > L + E = Positive, A < L + E = Negative | C43: =C16-C42 -> 0 | D43: =D16-D42 -> 0 | E43: =E16-E42 -> 0 | F43: =F16-F42 -> 0 | G43: =G16-G42 -> 0 | H43: =H16-H42 -> -854.04721 | I43: =I16-I42 -> -1503.3271 | J43: =J16-J42 -> -2499.8194 | ... Q43: =Q16-Q42 -> 0
B46: Ratios
B47: Working Capital | C47: =C10-C24 -> 1656 | D47: =D10-D24 -> 3364 | E47: =E10-E24 -> 3497 | F47: =F10-F24 -> 4317 | G47: =G10-G24 -> 2223 | H47: =H10-H24 -> 3481.6371 | I47: =I10-I24 -> 4982.1684 | J47: =J10-J24 -> 6159.0868 | ... Q47: =Q10-Q24 -> 0
B48: Net Debt | C48: =+C22+C26-C6 -> 11448 | D48: =+D22+D26-D6 -> 10448 | E48: =+E22+E26-E6 -> 7364 | F48: =+F22+F26-F6 -> 7785 | G48: =+G22+G26-G6 -> 9462 | H48: =+H22+H26-H6 -> 8061.3724 | I48: =+I22+I26-I6 -> 6596.4012 | J48: =+J22+J26-J6 -> 5455.3984 | ... Q48: =+Q22+Q26-Q6 -> 0
B51: Data from Financial Statements
B52: ='Income Statement'!B4 -> Revenue | C52: ='Income Statement'!C4 -> 42405 | D52: ='Income Statement'!D4 -> 43185 | E52: ='Income Statement'!E4 -> 47049 | F52: ='Income Statement'!F4 -> 53282 | G52: ='Income Statement'!G4 -> 52881 | H52: ='Income Statement'!H4 -> 53409.81 | I52: ='Income Statement'!I4 -> 53943.908 | ... Q52: ='Income Statement'!Q4 -> 0
B53: ='Income Statement'!B8 -> Cost of Revenue ~ Cost of Goods Sold | C53: ='Income Statement'!C8 -> 37383 | D53: ='Income Statement'!D8 -> 37801 | E53: ='Income Statement'!E8 -> 40523 | F53: ='Income Statement'!F8 -> 46614 | G53: ='Income Statement'!G8 -> 50250 | H53: ='Income Statement'!H8 -> 47463.082 | I53: ='Income Statement'!I8 -> 47937.713 | ... Q53: ='Income Statement'!Q8 -> 0
B54: ='Income Statement'!B44 -> Capital Expenditures | C54: ='Income Statement'!C44 -> 1259 | D54: ='Income Statement'!D44 -> 1199 | E54: ='Income Statement'!E44 -> 1209 | F54: ='Income Statement'!F44 -> 1887 | G54: ='Income Statement'!G44 -> 1939 | H54: ='Income Statement'!H44 -> 1658.1968 | I54: ='Income Statement'!I44 -> 1674.7787 | ... Q54: ='Income Statement'!Q44 -> 0
B55: ='Income Statement'!B47 -> Depreciation and Amortization | C55: ='Income Statement'!C47 -> 1098 | D55: ='Income Statement'!D47 -> 1192 | E55: ='Income Statement'!E47 -> 1214 | F55: ='Income Statement'!F47 -> 1202 | G55: ='Income Statement'!G47 -> 1339 | H55: ='Income Statement'!H47 -> 1392.2121 | I55: ='Income Statement'!I47 -> 1406.1342 | ... Q55: ='Income Statement'!Q47 -> 0
B56: ='Income Statement'!B37 -> Net Income (Loss), GAAP | C56: ='Income Statement'!C37 -> 2022 | D56: ='Income Statement'!D37 -> 2061 | E56: ='Income Statement'!E37 -> 3047 | F56: ='Income Statement'!F37 -> 3238 | G56: ='Income Statement'!G37 -> -648 | H56: ='Income Statement'!H37 -> 2347.5089 | I56: ='Income Statement'!I37 -> 2386.7744 | ... Q56: ='Income Statement'!Q37 -> 0
B57: ='Cash Flows'!B22 -> Dividends Paid | C57: ='Cash Flows'!C22 -> -537 | D57: ='Cash Flows'!D22 -> -601 | E57: ='Cash Flows'!E22 -> -636 | F57: ='Cash Flows'!F22 -> -653 | G57: ='Cash Flows'!G22 -> -670 | H57: ='Cash Flows'!H22 -> 31.160068 | I57: ='Cash Flows'!I22 -> 31.681266 | ... Q57: ='Cash Flows'!Q22 -> 0

Sheet BS Bear
B2: Balance Sheet - Base
B3: =Assumptions!$B$132 -> Year Ending 09/31/2024, In USD Millions | C3: {=_xlfn.SEQUENCE(1,5+Assumptions!$C$20,(YEAR('Valuation Summary'!$C$4)-5))} -> 2019 | D3: 2020 | E3: 2021 | F3: 2022 | G3: 2023 | H3: 2024 | I3: 2025 | J3: 2026 | K3: 2027 | L3: 2028
B4: Assets
B5: Current Assets
B6: =Assumptions!B279 -> Cash, Cash Equivalents, and Short-Term Investments | C6: =+Assumptions!D280+'CF Bear'!C36 -> 317 | D6: =+Assumptions!E280+'CF Bear'!D36 -> 148 | E6: =+Assumptions!F280+'CF Bear'!E36 -> 2228 | F6: =+Assumptions!G280+'CF Bear'!F36 -> 160 | G6: =+Assumptions!H280+'CF Bear'!G36 -> -14 | H6: =IF(H$3="",0,'CF Bear'!H36+'IS Bear'!H4*Assumptions!I$281) -> 914.13584 | I6: =IF(I$3="",0,'CF Bear'!I36+'IS Bear'!I4*Assumptions!J$281) -> 1873.8501 | J6: =IF(J$3="",0,'CF Bear'!J36+'IS Bear'!J4*Assumptions!K$281) -> 2892.6107 | K6: =IF(K$3="",0,'CF Bear'!K36+'IS Bear'!K4*Assumptions!L$281) -> 3573.127 | L6: =IF(L$3="",0,'CF Bear'!L36+'IS Bear'!L4*Assumptions!M$281) -> 4780.3272 | M6: =IF(M$3="",0,'CF Bear'!M36+'IS Bear'!M4*Assumptions!N$281) -> 0 | N6: =IF(N$3="",0,'CF Bear'!N36+'IS Bear'!N4*Assumptions!O$281) -> 0 | O6: =IF(O$3="",0,'CF Bear'!O36+'IS Bear'!O4*Assumptions!P$281) -> 0 | ... Q6: =IF(Q$3="",0,'CF Bear'!Q36+'IS Bear'!Q4*Assumptions!R$281) -> 0
B7: =Assumptions!B284 -> Accounts and Notes Receivable | C7: =Assumptions!D284 -> 2173 | D7: =Assumptions!E284 -> 1952 | E7: =Assumptions!F284 -> 2400 | F7: =Assumptions!G284 -> 2577 | G7: =Assumptions!H284 -> 2476 | H7: =IF(H$3="",0,G7*(1+Assumptions!I$138)) -> 2451.24 | I7: =IF(I$3="",0,H7*(1+Assumptions!J$138)) -> 2426.7276 | J7: =IF(J$3="",0,I7*(1+Assumptions!K$138)) -> 2402.4603 | K7: =IF(K$3="",0,J7*(1+Assumptions!L$138)) -> 2378.4357 | L7: =IF(L$3="",0,K7*(1+Assumptions!M$138)) -> 2354.6514 | M7: =IF(M$3="",0,L7*(1+Assumptions!N$138)) -> 0 | N7: =IF(N$3="",0,M7*(1+Assumptions!O$138)) -> 0 | O7: =IF(O$3="",0,N7*(1+Assumptions!P$138)) -> 0 | ... Q7: =IF(Q$3="",0,P7*(1+Assumptions!R$138)) -> 0
B8: =Assumptions!B290 -> Inventory | C8: =Assumptions!D290 -> 4108 | D8: =Assumptions!E290 -> 3859 | E8: =Assumptions!F290 -> 4382 | F8: =Assumptions!G290 -> 5514 | G8: =Assumptions!H290 -> 5328 | H8: =IF(H$3="",0,+G8*(1+'IS Bear'!H$10)) -> 4932.85 | I8: =IF(I$3="",0,+H8*(1+'IS Bear'!I$10)) -> 4883.5215 | J8: =IF(J$3="",0,+I8*(1+'IS Bear'!J$10)) -> 4834.6862 | K8: =IF(K$3="",0,+J8*(1+'IS Bear'!K$10)) -> 4786.3394 | L8: =IF(L$3="",0,+K8*(1+'IS Bear'!L$10)) -> 4738.476 | M8: =IF(M$3="",0,+L8*(1+'IS Bear'!M$10)) -> 0 | N8: =IF(N$3="",0,+M8*(1+'IS Bear'!N$10)) -> 0 | O8: =IF(O$3="",0,+N8*(1+'IS Bear'!O$10)) -> 0 | ... Q8: =IF(Q$3="",0,+P8*(1+'IS Bear'!Q$10)) -> 0
B9: =Assumptions!B293 -> Other Short-Term Assets | C9: =Assumptions!D293 -> 404 | D9: =Assumptions!E293 -> 367 | E9: =Assumptions!F293 -> 533 | F9: =Assumptions!G293 -> 508 | G9: =Assumptions!H293 -> 345 | H9: =IF(H$3="",0,G9*(1+Assumptions!I$138)) -> 341.55 | I9: =IF(I$3="",0,H9*(1+Assumptions!J$138)) -> 338.1345 | J9: =IF(J$3="",0,I9*(1+Assumptions!K$138)) -> 334.75315 | K9: =IF(K$3="",0,J9*(1+Assumptions!L$138)) -> 331.40562 | L9: =IF(L$3="",0,K9*(1+Assumptions!M$138)) -> 328.09157 | M9: =IF(M$3="",0,L9*(1+Assumptions!N$138)) -> 0 | N9: =IF(N$3="",0,M9*(1+Assumptions!O$138)) -> 0 | O9: =IF(O$3="",0,N9*(1+Assumptions!P$138)) -> 0 | ... Q9: =IF(Q$3="",0,P9*(1+Assumptions!R$138)) -> 0
B10: ="Total "&B5 -> Total Current Assets | C10: =SUM(C6:C9) -> 7002 | D10: =SUM(D6:D9) -> 6326 | E10: =SUM(E6:E9) -> 9543 | F10: =SUM(F6:F9) -> 8759 | G10: =SUM(G6:G9) -> 8135 | H10: =SUM(H6:H9) -> 8639.7758 | I10: =SUM(I6:I9) -> 9522.2337 | J10: =SUM(J6:J9) -> 10464.51 | ... Q10: =SUM(Q6:Q9) -> 0
B11: Non-Current Assets
B12: =Assumptions!B296 -> Property, Plant, and Equipment | C12: =Assumptions!D296 -> 7282 | D12: =Assumptions!E296 -> 8128 | E12: =Assumptions!F296 -> 8368 | F12: =Assumptions!G296 -> 9192 | G12: =Assumptions!H296 -> 10178 | H12: =IF(H$3="",0,G12+H54-H55) -> 10438.718 | I12: =IF(I$3="",0,H12+I54-I55) -> 10696.828 | J12: =IF(J$3="",0,I12+J54-J55) -> 10952.357 | K12: =IF(K$3="",0,J12+K54-K55) -> 11205.331 | L12: =IF(L$3="",0,K12+L54-L55) -> 11455.776 | M12: =IF(M$3="",0,L12+M54-M55) -> 0 | N12: =IF(N$3="",0,M12+N54-N55) -> 0 | O12: =IF(O$3="",0,N12+O54-O55) -> 0 | ... Q12: =IF(Q$3="",0,P12+Q54-Q55) -> 0
B13: =Assumptions!B299 -> Long-Term Investments and Receivables | C13: =Assumptions!D299 -> 0 | D13: =Assumptions!E299 -> 0 | E13: =Assumptions!F299 -> 0 | F13: =Assumptions!G299 -> 0 | G13: =Assumptions!H299 -> 0 | H13: =IF(H$3="",0,G13) -> 0 | I13: =IF(I$3="",0,H13) -> 0 | J13: =IF(J$3="",0,I13) -> 0 | K13: =IF(K$3="",0,J13) -> 0 | L13: =IF(L$3="",0,K13) -> 0 | M13: =IF(M$3="",0,L13) -> 0 | N13: =IF(N$3="",0,M13) -> 0 | O13: =IF(O$3="",0,N13) -> 0 | ... Q13: =IF(Q$3="",0,P13) -> 0
B14: =Assumptions!B302 -> Other Long-Term Assets | C14: =Assumptions!D302 -> 18646 | D14: =Assumptions!E302 -> 18730 | E14: =Assumptions!F302 -> 18119 | F14: =Assumptions!G302 -> 17999 | G14: =Assumptions!H302 -> 17351 | H14: =IF(H$3="",0,G14) -> 17351 | I14: =IF(I$3="",0,H14) -> 17351 | J14: =IF(J$3="",0,I14) -> 17351 | K14: =IF(K$3="",0,J14) -> 17351 | L14: =IF(L$3="",0,K14) -> 17351 | M14: =IF(M$3="",0,L14) -> 0 | N14: =IF(N$3="",0,M14) -> 0 | O14: =IF(O$3="",0,N14) -> 0 | ... Q14: =IF(Q$3="",0,P14) -> 0
B15: ="Total "&B11 -> Total Non-Current Assets | C15: =SUM(C12:C14) -> 25928 | D15: =SUM(D12:D14) -> 26858 | E15: =SUM(E12:E14) -> 26487 | F15: =SUM(F12:F14) -> 27191 | G15: =SUM(G12:G14) -> 27529 | H15: =SUM(H12:H14) -> 27789.718 | I15: =SUM(I12:I14) -> 28047.828 | J15: =SUM(J12:J14) -> 28303.357 | ... Q15: =SUM(Q12:Q14) -> 0
B16: ="Total "&B4 -> Total Assets | C16: =SUM(C10,C15) -> 32930 | D16: =SUM(D10,D15) -> 33184 | E16: =SUM(E10,E15) -> 36030 | F16: =SUM(F10,F15) -> 35950 | G16: =SUM(G10,G15) -> 35664 | H16: =SUM(H10,H15) -> 36429.493 | I16: =SUM(I10,I15) -> 37570.062 | J16: =SUM(J10,J15) -> 38767.868 | ... Q16: =SUM(Q10,Q15) -> 0
B19: Liabilities
B20: Current Liabilities
B21: =Assumptions!B305 -> Payables and Accruals | C21: =Assumptions!D305 -> 1926 | D21: =Assumptions!E305 -> 1876 | E21: =Assumptions!F305 -> 2225 | F21: =Assumptions!G305 -> 2483 | G21: =Assumptions!H305 -> 2594 | H21: =IF(H$3="",0,+G21*(1+'IS Bear'!H$10)) -> 2401.6165 | I21: =IF(I$3="",0,+H21*(1+'IS Bear'!I$10)) -> 2377.6003 | J21: =IF(J$3="",0,+I21*(1+'IS Bear'!J$10)) -> 2353.8243 | K21: =IF(K$3="",0,+J21*(1+'IS Bear'!K$10)) -> 2330.2861 | L21: =IF(L$3="",0,+K21*(1+'IS Bear'!L$10)) -> 2306.9832 | M21: =IF(M$3="",0,+L21*(1+'IS Bear'!M$10)) -> 0 | N21: =IF(N$3="",0,+M21*(1+'IS Bear'!N$10)) -> 0 | O21: =IF(O$3="",0,+N21*(1+'IS Bear'!O$10)) -> 0 | ... Q21: =IF(Q$3="",0,+P21*(1+'IS Bear'!Q$10)) -> 0
B22: =Assumptions!B308 -> Short-Term Debt | C22: =Assumptions!D308 -> 2102 | D22: =Assumptions!E308 -> 709 | E22: =Assumptions!F308 -> 1222 | F22: =Assumptions!G308 -> 604 | G22: =Assumptions!H308 -> 2048 | H22: =IF(H$3="",0,(Assumptions!I$162*Assumptions!I$161)+'CF Bear'!H$23) -> 1036.0567 | I22: =IF(I$3="",0,(Assumptions!J$162*Assumptions!J$161)+'CF Bear'!I$23) -> 625.89668 | J22: =IF(J$3="",0,(Assumptions!K$162*Assumptions!K$161)+'CF Bear'!J$23) -> 646.30468 | K22: =IF(K$3="",0,(Assumptions!L$162*Assumptions!L$161)+'CF Bear'!K$23) -> 945.79428 | L22: =IF(L$3="",0,(Assumptions!M$162*Assumptions!M$161)+'CF Bear'!L$23) -> 1113.3818 | M22: =IF(M$3="",0,(Assumptions!N$162*Assumptions!N$161)+'CF Bear'!M$23) -> 0 | N22: =IF(N$3="",0,(Assumptions!O$162*Assumptions!O$161)+'CF Bear'!N$23) -> 0 | O22: =IF(O$3="",0,(Assumptions!P$162*Assumptions!P$161)+'CF Bear'!O$23) -> 0 | ... Q22: =IF(Q$3="",0,(Assumptions!R$162*Assumptions!R$161)+'CF Bear'!Q$23) -> 0
B23: =Assumptions!B311 -> Other Short-Term Liabilities | C23: =Assumptions!D311 -> 1485 | D23: =Assumptions!E311 -> 1649 | E23: =Assumptions!F311 -> 2878 | F23: =Assumptions!G311 -> 2226 | G23: =Assumptions!H311 -> 1857 | H23: =IF(H$3="",0,G23*(1+Assumptions!I138)) -> 1838.43 | I23: =IF(I$3="",0,H23*(1+Assumptions!J138)) -> 1820.0457 | J23: =IF(J$3="",0,I23*(1+Assumptions!K138)) -> 1801.8452 | K23: =IF(K$3="",0,J23*(1+Assumptions!L138)) -> 1783.8268 | L23: =IF(L$3="",0,K23*(1+Assumptions!M138)) -> 1765.9885 | M23: =IF(M$3="",0,L23*(1+Assumptions!N138)) -> 0 | N23: =IF(N$3="",0,M23*(1+Assumptions!O138)) -> 0 | O23: =IF(O$3="",0,N23*(1+Assumptions!P138)) -> 0 | ... Q23: =IF(Q$3="",0,P23*(1+Assumptions!R138)) -> 0
B24: ="Total "&B20 -> Total Current Liabilities | C24: =SUM(C21:C23) -> 5513 | D24: =SUM(D21:D23) -> 4234 | E24: =SUM(E21:E23) -> 6325 | F24: =SUM(F21:F23) -> 5313 | G24: =SUM(G21:G23) -> 6499 | H24: =SUM(H21:H23) -> 5276.1032 | I24: =SUM(I21:I23) -> 4823.5427 | J24: =SUM(J21:J23) -> 4801.9743 | ... Q24: =SUM(Q21:Q23) -> 0
B25: Non-Current Liabilities
B26: =Assumptions!B314 -> Long-Term Debt | C26: =Assumptions!D314 -> 9830 | D26: =Assumptions!E314 -> 11159 | E26: =Assumptions!F314 -> 8649 | F26: =Assumptions!G314 -> 8212 | G26: =Assumptions!H314 -> 7987 | H26: =IF(H$3="",0,G26) -> 7987 | I26: =IF(I$3="",0,H26) -> 7987 | J26: =IF(J$3="",0,I26) -> 7987 | K26: =IF(K$3="",0,J26) -> 7987 | L26: =IF(L$3="",0,K26) -> 7987 | M26: =IF(M$3="",0,L26) -> 0 | N26: =IF(N$3="",0,M26) -> 0 | O26: =IF(O$3="",0,N26) -> 0 | ... Q26: =IF(Q$3="",0,P26) -> 0
B27: =Assumptions!B317 -> Other Long-Term Liabilities | C27: =Assumptions!D317 -> 3528 | D27: =Assumptions!E317 -> 3677 | E27: =Assumptions!F317 -> 3481 | F27: =Assumptions!G317 -> 3485 | G27: =Assumptions!H317 -> 3510 | H27: =IF(H$3="",0,G27) -> 3510 | I27: =IF(I$3="",0,H27) -> 3510 | J27: =IF(J$3="",0,I27) -> 3510 | K27: =IF(K$3="",0,J27) -> 3510 | L27: =IF(L$3="",0,K27) -> 3510 | M27: =IF(M$3="",0,L27) -> 0 | N27: =IF(N$3="",0,M27) -> 0 | O27: =IF(O$3="",0,N27) -> 0 | ... Q27: =IF(Q$3="",0,P27) -> 0
B28: ="Total "&B25 -> Total Non-Current Liabilities | C28: =SUM(C26:C27) -> 13358 | D28: =SUM(D26:D27) -> 14836 | E28: =SUM(E26:E27) -> 12130 | F28: =SUM(F26:F27) -> 11697 | G28: =SUM(G26:G27) -> 11497 | H28: =SUM(H26:H27) -> 11497 | I28: =SUM(I26:I27) -> 11497 | J28: =SUM(J26:J27) -> 11497 | ... Q28: =SUM(Q26:Q27) -> 0
B29: ="Total "&B19 -> Total Liabilities | C29: =SUM(C24,C28) -> 18871 | D29: =SUM(D24,D28) -> 19070 | E29: =SUM(E24,E28) -> 18455 | F29: =SUM(F24,F28) -> 17010 | G29: =SUM(G24,G28) -> 17996 | H29: =SUM(H24,H28) -> 16773.103 | I29: =SUM(I24,I28) -> 16320.543 | J29: =SUM(J24,J28) -> 16298.974 | ... Q29: =SUM(Q24,Q28) -> 0
B32: Equity
B33: =Assumptions!B326 -> Retained Earnings | C33: =Assumptions!D326 -> 13787 | D33: =Assumptions!E326 -> 15100 | E33: =Assumptions!F326 -> 17502 | F33: =Assumptions!G326 -> 20084 | G33: =Assumptions!H326 -> 18760 | H33: =IF(H$3="",0,G33+H56+H57) -> 21085.853 | I33: =IF(I$3="",0,H33+I56+I57) -> 23398.678 | J33: =IF(J$3="",0,I33+J56+J57) -> 25684.968 | K33: =IF(K$3="",0,J33+K56+K57) -> 27936.058 | L33: =IF(L$3="",0,K33+L56+L57) -> 30156.423 | M33: =IF(M$3="",0,L33+M56+M57) -> 0 | N33: =IF(N$3="",0,M33+N56+N57) -> 0 | O33: =IF(O$3="",0,N33+O56+O57) -> 0 | ... Q33: =IF(Q$3="",0,P33+Q56+Q57) -> 0
B34: =Assumptions!B320 -> Preferred and Hybrid Capital | C34: =Assumptions!D320 -> 0 | D34: =Assumptions!E320 -> 0 | E34: =Assumptions!F320 -> 0 | F34: =Assumptions!G320 -> 0 | G34: =Assumptions!H320 -> 0 | H34: =IF(H$3="",0,G34) -> 0 | I34: =IF(I$3="",0,H34) -> 0 | J34: =IF(J$3="",0,I34) -> 0 | K34: =IF(K$3="",0,J34) -> 0 | L34: =IF(L$3="",0,K34) -> 0 | M34: =IF(M$3="",0,L34) -> 0 | N34: =IF(N$3="",0,M34) -> 0 | O34: =IF(O$3="",0,N34) -> 0 | ... Q34: =IF(Q$3="",0,P34) -> 0
B35: =Assumptions!B323 -> Share Capital and Additional Paid in Capital | C35: =Assumptions!D323 -> 4423 | D35: =Assumptions!E323 -> 4478 | E35: =Assumptions!F323 -> 4531 | F35: =Assumptions!G323 -> 4598 | G35: =Assumptions!H323 -> 4605 | H35: =IF(H$3="",0,G35) -> 4605 | I35: =IF(I$3="",0,H35) -> 4605 | J35: =IF(J$3="",0,I35) -> 4605 | K35: =IF(K$3="",0,J35) -> 4605 | L35: =IF(L$3="",0,K35) -> 4605 | M35: =IF(M$3="",0,L35) -> 0 | N35: =IF(N$3="",0,M35) -> 0 | O35: =IF(O$3="",0,N35) -> 0 | ... Q35: =IF(Q$3="",0,P35) -> 0
B36: =Assumptions!B329 -> Other Equity | C36: =Assumptions!D329 -> -117 | D36: =Assumptions!E329 -> -179 | E36: =Assumptions!F329 -> -172 | F36: =Assumptions!G329 -> -297 | G36: =Assumptions!H329 -> -260 | H36: =IF(H$3="",0,G36) -> -260 | I36: =IF(I$3="",0,H36) -> -260 | J36: =IF(J$3="",0,I36) -> -260 | K36: =IF(K$3="",0,J36) -> -260 | L36: =IF(L$3="",0,K36) -> -260 | M36: =IF(M$3="",0,L36) -> 0 | N36: =IF(N$3="",0,M36) -> 0 | O36: =IF(O$3="",0,N36) -> 0 | ... Q36: =IF(Q$3="",0,P36) -> 0
B37: =Assumptions!B332 -> Minority and Non-Controlling Interest | C37: =Assumptions!D332 -> 144 | D37: =Assumptions!E332 -> 132 | E37: =Assumptions!F332 -> 131 | F37: =Assumptions!G332 -> 109 | G37: =Assumptions!H332 -> 122 | H37: =IF(H$3="",0,G37) -> 122 | I37: =IF(I$3="",0,H37) -> 122 | J37: =IF(J$3="",0,I37) -> 122 | K37: =IF(K$3="",0,J37) -> 122 | L37: =IF(L$3="",0,K37) -> 122 | M37: =IF(M$3="",0,L37) -> 0 | N37: =IF(N$3="",0,M37) -> 0 | O37: =IF(O$3="",0,N37) -> 0 | ... Q37: =IF(Q$3="",0,P37) -> 0
B38: =Assumptions!B335 -> Treasury Stock | C38: =Assumptions!D335 -> 4011 | D38: =Assumptions!E335 -> 4145 | E38: =Assumptions!F335 -> 4138 | F38: =Assumptions!G335 -> 4683 | G38: =Assumptions!H335 -> 4972 | H38: =IF(H$3="",0,G38) -> 4972 | I38: =IF(I$3="",0,H38) -> 4972 | J38: =IF(J$3="",0,I38) -> 4972 | K38: =IF(K$3="",0,J38) -> 4972 | L38: =IF(L$3="",0,K38) -> 4972 | M38: =IF(M$3="",0,L38) -> 0 | N38: =IF(N$3="",0,M38) -> 0 | O38: =IF(O$3="",0,N38) -> 0 | ... Q38: =IF(Q$3="",0,P38) -> 0
B39: Balancing Figure
B40: ="Total "&B32 -> Total Equity | C40: =SUM(C33:C37)-C38+C39 -> 14226 | D40: =SUM(D33:D37)-D38+D39 -> 15386 | E40: =SUM(E33:E37)-E38+E39 -> 17854 | F40: =SUM(F33:F37)-F38+F39 -> 19811 | G40: =SUM(G33:G37)-G38+G39 -> 18255 | H40: =SUM(H33:H37)-H38+H39 -> 20580.853 | I40: =SUM(I33:I37)-I38+I39 -> 22893.678 | J40: =SUM(J33:J37)-J38+J39 -> 25179.968 | ... Q40: =SUM(Q33:Q37)-Q38+Q39 -> 0
B42: ="Total "&B19&" and "&B32 -> Total Liabilities and Equity | C42: =C29+C40 -> 33097 | D42: =D29+D40 -> 34456 | E42: =E29+E40 -> 36309 | F42: =F29+F40 -> 36821 | G42: =G29+G40 -> 36251 | H42: =H29+H40 -> 37353.957 | I42: =I29+I40 -> 39214.221 | J42: =J29+J40 -> 41478.942 | ... Q42: =Q29+Q40 -> 0
B43: A = L + E Check, A > L + E = Positive, A < L + E = Negative | C43: =C16-C42 -> -167 | D43: =D16-D42 -> -1272 | E43: =E16-E42 -> -279 | F43: =F16-F42 -> -871 | G43: =G16-G42 -> -587 | H43: =H16-H42 -> -924.46324 | I43: =I16-I42 -> -1644.1592 | J43: =J16-J42 -> -2711.0746 | ... Q43: =Q16-Q42 -> 0
B46: Ratios
B47: Working Capital | C47: =C10-C24 -> 1489 | D47: =D10-D24 -> 2092 | E47: =E10-E24 -> 3218 | F47: =F10-F24 -> 3446 | G47: =G10-G24 -> 1636 | H47: =H10-H24 -> 3363.6726 | I47: =I10-I24 -> 4698.6909 | J47: =J10-J24 -> 5662.5362 | ... Q47: =Q10-Q24 -> 0
B48: Net Debt | C48: =+C22+C26-C6 -> 11615 | D48: =+D22+D26-D6 -> 11720 | E48: =+E22+E26-E6 -> 7643 | F48: =+F22+F26-F6 -> 8656 | G48: =+G22+G26-G6 -> 10049 | H48: =+H22+H26-H6 -> 8108.9208 | I48: =+I22+I26-I6 -> 6739.0466 | J48: =+J22+J26-J6 -> 5740.694 | ... Q48: =+Q22+Q26-Q6 -> 0
B51: Data from Financial Statements
B52: ='Income Statement'!B4 -> Revenue | C52: ='IS Bear'!C4 -> 42405 | D52: ='IS Bear'!D4 -> 43185 | E52: ='IS Bear'!E4 -> 47049 | F52: ='IS Bear'!F4 -> 53282 | G52: ='IS Bear'!G4 -> 52881 | H52: ='IS Bear'!H4 -> 52352.19 | I52: ='IS Bear'!I4 -> 51828.668 | J52: ='IS Bear'!J4 -> 51310.381 | ... Q52: ='IS Bear'!Q4 -> 0
B53: ='Income Statement'!B8 -> Cost of Revenue ~ Cost of Goods Sold | C53: ='IS Bear'!C8 -> 37383 | D53: ='IS Bear'!D8 -> 37801 | E53: ='IS Bear'!E8 -> 40523 | F53: ='IS Bear'!F8 -> 46614 | G53: ='IS Bear'!G8 -> 50250 | H53: ='IS Bear'!H8 -> 46523.219 | I53: ='IS Bear'!I8 -> 46057.987 | J53: ='IS Bear'!J8 -> 45597.407 | ... Q53: ='IS Bear'!Q8 -> 0
B54: ='Income Statement'!B44 -> Capital Expenditures | C54: ='IS Bear'!C44 -> 1259 | D54: ='IS Bear'!D44 -> 1199 | E54: ='IS Bear'!E44 -> 1209 | F54: ='IS Bear'!F44 -> 1887 | G54: ='IS Bear'!G44 -> 1939 | H54: ='IS Bear'!H44 -> 1625.3612 | I54: ='IS Bear'!I44 -> 1609.1076 | J54: ='IS Bear'!J44 -> 1593.0165 | ... Q54: ='IS Bear'!Q44 -> 0
B55: ='Income Statement'!B47 -> Depreciation and Amortization | C55: ='IS Bear'!C47 -> 1098 | D55: ='IS Bear'!D47 -> 1192 | E55: ='IS Bear'!E47 -> 1214 | F55: ='IS Bear'!F47 -> 1202 | G55: ='IS Bear'!G47 -> 1339 | H55: ='IS Bear'!H47 -> 1364.6436 | I55: ='IS Bear'!I47 -> 1350.9971 | J55: ='IS Bear'!J47 -> 1337.4872 | ... Q55: ='IS Bear'!Q47 -> 0
B56: ='Income Statement'!B37 -> Net Income (Loss), GAAP | C56: ='IS Bear'!C37 -> 2022 | D56: ='IS Bear'!D37 -> 2061 | E56: ='IS Bear'!E37 -> 3047 | F56: ='IS Bear'!F37 -> 3238 | G56: ='IS Bear'!G37 -> -648 | H56: ='IS Bear'!H37 -> 2295.3852 | I56: ='IS Bear'!I37 -> 2282.5272 | J56: ='IS Bear'!J37 -> 2256.34 | ... Q56: ='IS Bear'!Q37 -> 0
B57: ='Cash Flows'!B22 -> Dividends Paid | C57: ='CF Bear'!C22 -> -537 | D57: ='CF Bear'!D22 -> -601 | E57: ='CF Bear'!E22 -> -636 | F57: ='CF Bear'!F22 -> -653 | G57: ='CF Bear'!G22 -> -670 | H57: ='CF Bear'!H22 -> 30.468196 | I57: ='CF Bear'!I22 -> 30.297522 | J57: ='CF Bear'!J22 -> 29.949922 | ... Q57: ='CF Bear'!Q22 -> 0

Sheet BS Bull
B2: Balance Sheet - Base
B3: =Assumptions!$B$132 -> Year Ending 09/31/2024, In USD Millions | C3: {=_xlfn.SEQUENCE(1,5+Assumptions!$C$20,(YEAR('Valuation Summary'!$C$4)-5))} -> 2019 | D3: 2020 | E3: 2021 | F3: 2022 | G3: 2023 | H3: 2024 | I3: 2025 | J3: 2026 | K3: 2027 | L3: 2028
B4: Assets
B5: Current Assets
B6: =Assumptions!B279 -> Cash, Cash Equivalents, and Short-Term Investments | C6: =+Assumptions!D280+'CF Bull'!C36 -> 317 | D6: =+Assumptions!E280+'CF Bull'!D36 -> 148 | E6: =+Assumptions!F280+'CF Bull'!E36 -> 2228 | F6: =+Assumptions!G280+'CF Bull'!F36 -> 160 | G6: =+Assumptions!H280+'CF Bull'!G36 -> -14 | H6: =IF(H$3="",0,'CF Bull'!H36+'IS Bull'!H4*Assumptions!I$281) -> 1009.2328 | I6: =IF(I$3="",0,'CF Bull'!I36+'IS Bull'!I4*Assumptions!J$281) -> 2161.0429 | J6: =IF(J$3="",0,'CF Bull'!J36+'IS Bull'!J4*Assumptions!K$281) -> 3470.8666 | K6: =IF(K$3="",0,'CF Bull'!K36+'IS Bull'!K4*Assumptions!L$281) -> 4543.4505 | L6: =IF(L$3="",0,'CF Bull'!L36+'IS Bull'!L4*Assumptions!M$281) -> 6245.83 | M6: =IF(M$3="",0,'CF Bull'!M36+'IS Bull'!M4*Assumptions!N$281) -> 0 | N6: =IF(N$3="",0,'CF Bull'!N36+'IS Bull'!N4*Assumptions!O$281) -> 0 | O6: =IF(O$3="",0,'CF Bull'!O36+'IS Bull'!O4*Assumptions!P$281) -> 0 | ... Q6: =IF(Q$3="",0,'CF Bull'!Q36+'IS Bull'!Q4*Assumptions!R$281) -> 0
B7: =Assumptions!B284 -> Accounts and Notes Receivable | C7: =Assumptions!D284 -> 2173 | D7: =Assumptions!E284 -> 1952 | E7: =Assumptions!F284 -> 2400 | F7: =Assumptions!G284 -> 2577 | G7: =Assumptions!H284 -> 2476 | H7: =IF(H$3="",0,G7*(1+Assumptions!I$139)) -> 2550.28 | I7: =IF(I$3="",0,H7*(1+Assumptions!J$139)) -> 2626.7884 | J7: =IF(J$3="",0,I7*(1+Assumptions!K$139)) -> 2705.5921 | K7: =IF(K$3="",0,J7*(1+Assumptions!L$139)) -> 2786.7598 | L7: =IF(L$3="",0,K7*(1+Assumptions!M$139)) -> 2870.3626 | M7: =IF(M$3="",0,L7*(1+Assumptions!N$139)) -> 0 | N7: =IF(N$3="",0,M7*(1+Assumptions!O$139)) -> 0 | O7: =IF(O$3="",0,N7*(1+Assumptions!P$139)) -> 0 | ... Q7: =IF(Q$3="",0,P7*(1+Assumptions!R$139)) -> 0
B8: =Assumptions!B290 -> Inventory | C8: =Assumptions!D290 -> 4108 | D8: =Assumptions!E290 -> 3859 | E8: =Assumptions!F290 -> 4382 | F8: =Assumptions!G290 -> 5514 | G8: =Assumptions!H290 -> 5328 | H8: =IF(H$3="",0,+G8*(1+'IS Bull'!H$10)) -> 5132.157 | I8: =IF(I$3="",0,+H8*(1+'IS Bull'!I$10)) -> 5286.1217 | J8: =IF(J$3="",0,+I8*(1+'IS Bull'!J$10)) -> 5444.7054 | K8: =IF(K$3="",0,+J8*(1+'IS Bull'!K$10)) -> 5608.0465 | L8: =IF(L$3="",0,+K8*(1+'IS Bull'!L$10)) -> 5776.2879 | M8: =IF(M$3="",0,+L8*(1+'IS Bull'!M$10)) -> 0 | N8: =IF(N$3="",0,+M8*(1+'IS Bull'!N$10)) -> 0 | O8: =IF(O$3="",0,+N8*(1+'IS Bull'!O$10)) -> 0 | ... Q8: =IF(Q$3="",0,+P8*(1+'IS Bull'!Q$10)) -> 0
B9: =Assumptions!B293 -> Other Short-Term Assets | C9: =Assumptions!D293 -> 404 | D9: =Assumptions!E293 -> 367 | E9: =Assumptions!F293 -> 533 | F9: =Assumptions!G293 -> 508 | G9: =Assumptions!H293 -> 345 | H9: =IF(H$3="",0,G9*(1+Assumptions!I$139)) -> 355.35 | I9: =IF(I$3="",0,H9*(1+Assumptions!J$139)) -> 366.0105 | J9: =IF(J$3="",0,I9*(1+Assumptions!K$139)) -> 376.99082 | K9: =IF(K$3="",0,J9*(1+Assumptions!L$139)) -> 388.30054 | L9: =IF(L$3="",0,K9*(1+Assumptions!M$139)) -> 399.94956 | M9: =IF(M$3="",0,L9*(1+Assumptions!N$139)) -> 0 | N9: =IF(N$3="",0,M9*(1+Assumptions!O$139)) -> 0 | O9: =IF(O$3="",0,N9*(1+Assumptions!P$139)) -> 0 | ... Q9: =IF(Q$3="",0,P9*(1+Assumptions!R$139)) -> 0
B10: ="Total "&B5 -> Total Current Assets | C10: =SUM(C6:C9) -> 7002 | D10: =SUM(D6:D9) -> 6326 | E10: =SUM(E6:E9) -> 9543 | F10: =SUM(F6:F9) -> 8759 | G10: =SUM(G6:G9) -> 8135 | H10: =SUM(H6:H9) -> 9047.0198 | I10: =SUM(I6:I9) -> 10439.963 | J10: =SUM(J6:J9) -> 11998.155 | ... Q10: =SUM(Q6:Q9) -> 0
B11: Non-Current Assets
B12: =Assumptions!B296 -> Property, Plant, and Equipment | C12: =Assumptions!D296 -> 7282 | D12: =Assumptions!E296 -> 8128 | E12: =Assumptions!F296 -> 8368 | F12: =Assumptions!G296 -> 9192 | G12: =Assumptions!H296 -> 10178 | H12: =IF(H$3="",0,G12+H54-H55) -> 10449.252 | I12: =IF(I$3="",0,H12+I54-I55) -> 10728.641 | J12: =IF(J$3="",0,I12+J54-J55) -> 11016.412 | K12: =IF(K$3="",0,J12+K54-K55) -> 11312.816 | L12: =IF(L$3="",0,K12+L54-L55) -> 11618.112 | M12: =IF(M$3="",0,L12+M54-M55) -> 0 | N12: =IF(N$3="",0,M12+N54-N55) -> 0 | O12: =IF(O$3="",0,N12+O54-O55) -> 0 | ... Q12: =IF(Q$3="",0,P12+Q54-Q55) -> 0
B13: =Assumptions!B299 -> Long-Term Investments and Receivables | C13: =Assumptions!D299 -> 0 | D13: =Assumptions!E299 -> 0 | E13: =Assumptions!F299 -> 0 | F13: =Assumptions!G299 -> 0 | G13: =Assumptions!H299 -> 0 | H13: =IF(H$3="",0,G13) -> 0 | I13: =IF(I$3="",0,H13) -> 0 | J13: =IF(J$3="",0,I13) -> 0 | K13: =IF(K$3="",0,J13) -> 0 | L13: =IF(L$3="",0,K13) -> 0 | M13: =IF(M$3="",0,L13) -> 0 | N13: =IF(N$3="",0,M13) -> 0 | O13: =IF(O$3="",0,N13) -> 0 | ... Q13: =IF(Q$3="",0,P13) -> 0
B14: =Assumptions!B302 -> Other Long-Term Assets | C14: =Assumptions!D302 -> 18646 | D14: =Assumptions!E302 -> 18730 | E14: =Assumptions!F302 -> 18119 | F14: =Assumptions!G302 -> 17999 | G14: =Assumptions!H302 -> 17351 | H14: =IF(H$3="",0,G14) -> 17351 | I14: =IF(I$3="",0,H14) -> 17351 | J14: =IF(J$3="",0,I14) -> 17351 | K14: =IF(K$3="",0,J14) -> 17351 | L14: =IF(L$3="",0,K14) -> 17351 | M14: =IF(M$3="",0,L14) -> 0 | N14: =IF(N$3="",0,M14) -> 0 | O14: =IF(O$3="",0,N14) -> 0 | ... Q14: =IF(Q$3="",0,P14) -> 0
B15: ="Total "&B11 -> Total Non-Current Assets | C15: =SUM(C12:C14) -> 25928 | D15: =SUM(D12:D14) -> 26858 | E15: =SUM(E12:E14) -> 26487 | F15: =SUM(F12:F14) -> 27191 | G15: =SUM(G12:G14) -> 27529 | H15: =SUM(H12:H14) -> 27800.252 | I15: =SUM(I12:I14) -> 28079.641 | J15: =SUM(J12:J14) -> 28367.412 | ... Q15: =SUM(Q12:Q14) -> 0
B16: ="Total "&B4 -> Total Assets | C16: =SUM(C10,C15) -> 32930 | D16: =SUM(D10,D15) -> 33184 | E16: =SUM(E10,E15) -> 36030 | F16: =SUM(F10,F15) -> 35950 | G16: =SUM(G10,G15) -> 35664 | H16: =SUM(H10,H15) -> 36847.271 | I16: =SUM(I10,I15) -> 38519.604 | J16: =SUM(J10,J15) -> 40365.567 | ... Q16: =SUM(Q10,Q15) -> 0
B19: Liabilities
B20: Current Liabilities
B21: =Assumptions!B305 -> Payables and Accruals | C21: =Assumptions!D305 -> 1926 | D21: =Assumptions!E305 -> 1876 | E21: =Assumptions!F305 -> 2225 | F21: =Assumptions!G305 -> 2483 | G21: =Assumptions!H305 -> 2594 | H21: =IF(H$3="",0,+G21*(1+'IS Bull'!H$10)) -> 2498.6515 | I21: =IF(I$3="",0,+H21*(1+'IS Bull'!I$10)) -> 2573.6111 | J21: =IF(J$3="",0,+I21*(1+'IS Bull'!J$10)) -> 2650.8194 | K21: =IF(K$3="",0,+J21*(1+'IS Bull'!K$10)) -> 2730.344 | L21: =IF(L$3="",0,+K21*(1+'IS Bull'!L$10)) -> 2812.2543 | M21: =IF(M$3="",0,+L21*(1+'IS Bull'!M$10)) -> 0 | N21: =IF(N$3="",0,+M21*(1+'IS Bull'!N$10)) -> 0 | O21: =IF(O$3="",0,+N21*(1+'IS Bull'!O$10)) -> 0 | ... Q21: =IF(Q$3="",0,+P21*(1+'IS Bull'!Q$10)) -> 0
B22: =Assumptions!B308 -> Short-Term Debt | C22: =Assumptions!D308 -> 2102 | D22: =Assumptions!E308 -> 709 | E22: =Assumptions!F308 -> 1222 | F22: =Assumptions!G308 -> 604 | G22: =Assumptions!H308 -> 2048 | H22: =IF(H$3="",0,(Assumptions!I$162*Assumptions!I$161)+'CF Bull'!H$23) -> 1036.0567 | I22: =IF(I$3="",0,(Assumptions!J$162*Assumptions!J$161)+'CF Bull'!I$23) -> 625.89668 | J22: =IF(J$3="",0,(Assumptions!K$162*Assumptions!K$161)+'CF Bull'!J$23) -> 646.30468 | K22: =IF(K$3="",0,(Assumptions!L$162*Assumptions!L$161)+'CF Bull'!K$23) -> 945.79428 | L22: =IF(L$3="",0,(Assumptions!M$162*Assumptions!M$161)+'CF Bull'!L$23) -> 1113.3818 | M22: =IF(M$3="",0,(Assumptions!N$162*Assumptions!N$161)+'CF Bull'!M$23) -> 0 | N22: =IF(N$3="",0,(Assumptions!O$162*Assumptions!O$161)+'CF Bull'!N$23) -> 0 | O22: =IF(O$3="",0,(Assumptions!P$162*Assumptions!P$161)+'CF Bull'!O$23) -> 0 | ... Q22: =IF(Q$3="",0,(Assumptions!R$162*Assumptions!R$161)+'CF Bull'!Q$23) -> 0
B23: =Assumptions!B311 -> Other Short-Term Liabilities | C23: =Assumptions!D311 -> 1485 | D23: =Assumptions!E311 -> 1649 | E23: =Assumptions!F311 -> 2878 | F23: =Assumptions!G311 -> 2226 | G23: =Assumptions!H311 -> 1857 | H23: =IF(H$3="",0,G23*(1+Assumptions!I139)) -> 1912.71 | I23: =IF(I$3="",0,H23*(1+Assumptions!J139)) -> 1970.0913 | J23: =IF(J$3="",0,I23*(1+Assumptions!K139)) -> 2029.194 | K23: =IF(K$3="",0,J23*(1+Assumptions!L139)) -> 2090.0699 | L23: =IF(L$3="",0,K23*(1+Assumptions!M139)) -> 2152.772 | M23: =IF(M$3="",0,L23*(1+Assumptions!N139)) -> 0 | N23: =IF(N$3="",0,M23*(1+Assumptions!O139)) -> 0 | O23: =IF(O$3="",0,N23*(1+Assumptions!P139)) -> 0 | ... Q23: =IF(Q$3="",0,P23*(1+Assumptions!R139)) -> 0
B24: ="Total "&B20 -> Total Current Liabilities | C24: =SUM(C21:C23) -> 5513 | D24: =SUM(D21:D23) -> 4234 | E24: =SUM(E21:E23) -> 6325 | F24: =SUM(F21:F23) -> 5313 | G24: =SUM(G21:G23) -> 6499 | H24: =SUM(H21:H23) -> 5447.4182 | I24: =SUM(I21:I23) -> 5169.5991 | J24: =SUM(J21:J23) -> 5326.3181 | ... Q24: =SUM(Q21:Q23) -> 0
B25: Non-Current Liabilities
B26: =Assumptions!B314 -> Long-Term Debt | C26: =Assumptions!D314 -> 9830 | D26: =Assumptions!E314 -> 11159 | E26: =Assumptions!F314 -> 8649 | F26: =Assumptions!G314 -> 8212 | G26: =Assumptions!H314 -> 7987 | H26: =IF(H$3="",0,G26) -> 7987 | I26: =IF(I$3="",0,H26) -> 7987 | J26: =IF(J$3="",0,I26) -> 7987 | K26: =IF(K$3="",0,J26) -> 7987 | L26: =IF(L$3="",0,K26) -> 7987 | M26: =IF(M$3="",0,L26) -> 0 | N26: =IF(N$3="",0,M26) -> 0 | O26: =IF(O$3="",0,N26) -> 0 | ... Q26: =IF(Q$3="",0,P26) -> 0
B27: =Assumptions!B317 -> Other Long-Term Liabilities | C27: =Assumptions!D317 -> 3528 | D27: =Assumptions!E317 -> 3677 | E27: =Assumptions!F317 -> 3481 | F27: =Assumptions!G317 -> 3485 | G27: =Assumptions!H317 -> 3510 | H27: =IF(H$3="",0,G27) -> 3510 | I27: =IF(I$3="",0,H27) -> 3510 | J27: =IF(J$3="",0,I27) -> 3510 | K27: =IF(K$3="",0,J27) -> 3510 | L27: =IF(L$3="",0,K27) -> 3510 | M27: =IF(M$3="",0,L27) -> 0 | N27: =IF(N$3="",0,M27) -> 0 | O27: =IF(O$3="",0,N27) -> 0 | ... Q27: =IF(Q$3="",0,P27) -> 0
B28: ="Total "&B25 -> Total Non-Current Liabilities | C28: =SUM(C26:C27) -> 13358 | D28: =SUM(D26:D27) -> 14836 | E28: =SUM(E26:E27) -> 12130 | F28: =SUM(F26:F27) -> 11697 | G28: =SUM(G26:G27) -> 11497 | H28: =SUM(H26:H27) -> 11497 | I28: =SUM(I26:I27) -> 11497 | J28: =SUM(J26:J27) -> 11497 | ... Q28: =SUM(Q26:Q27) -> 0
B29: ="Total "&B19 -> Total Liabilities | C29: =SUM(C24,C28) -> 18871 | D29: =SUM(D24,D28) -> 19070 | E29: =SUM(E24,E28) -> 18455 | F29: =SUM(F24,F28) -> 17010 | G29: =SUM(G24,G28) -> 17996 | H29: =SUM(H24,H28) -> 16944.418 | I29: =SUM(I24,I28) -> 16666.599 | J29: =SUM(J24,J28) -> 16823.318 | ... Q29: =SUM(Q24,Q28) -> 0
B32: Equity
B33: =Assumptions!B326 -> Retained Earnings | C33: =Assumptions!D326 -> 13787 | D33: =Assumptions!E326 -> 15100 | E33: =Assumptions!F326 -> 17502 | F33: =Assumptions!G326 -> 20084 | G33: =Assumptions!H326 -> 18760 | H33: =IF(H$3="",0,G33+H56+H57) -> 21191.484 | I33: =IF(I$3="",0,H33+I56+I57) -> 23717.684 | J33: =IF(J$3="",0,I33+J56+J57) -> 26327.278 | K33: =IF(K$3="",0,J33+K56+K57) -> 29013.866 | L33: =IF(L$3="",0,K33+L56+L57) -> 31784.262 | M33: =IF(M$3="",0,L33+M56+M57) -> 0 | N33: =IF(N$3="",0,M33+N56+N57) -> 0 | O33: =IF(O$3="",0,N33+O56+O57) -> 0 | ... Q33: =IF(Q$3="",0,P33+Q56+Q57) -> 0
B34: =Assumptions!B320 -> Preferred and Hybrid Capital | C34: =Assumptions!D320 -> 0 | D34: =Assumptions!E320 -> 0 | E34: =Assumptions!F320 -> 0 | F34: =Assumptions!G320 -> 0 | G34: =Assumptions!H320 -> 0 | H34: =IF(H$3="",0,G34) -> 0 | I34: =IF(I$3="",0,H34) -> 0 | J34: =IF(J$3="",0,I34) -> 0 | K34: =IF(K$3="",0,J34) -> 0 | L34: =IF(L$3="",0,K34) -> 0 | M34: =IF(M$3="",0,L34) -> 0 | N34: =IF(N$3="",0,M34) -> 0 | O34: =IF(O$3="",0,N34) -> 0 | ... Q34: =IF(Q$3="",0,P34) -> 0
B35: =Assumptions!B323 -> Share Capital and Additional Paid in Capital | C35: =Assumptions!D323 -> 4423 | D35: =Assumptions!E323 -> 4478 | E35: =Assumptions!F323 -> 4531 | F35: =Assumptions!G323 -> 4598 | G35: =Assumptions!H323 -> 4605 | H35: =IF(H$3="",0,G35) -> 4605 | I35: =IF(I$3="",0,H35) -> 4605 | J35: =IF(J$3="",0,I35) -> 4605 | K35: =IF(K$3="",0,J35) -> 4605 | L35: =IF(L$3="",0,K35) -> 4605 | M35: =IF(M$3="",0,L35) -> 0 | N35: =IF(N$3="",0,M35) -> 0 | O35: =IF(O$3="",0,N35) -> 0 | ... Q35: =IF(Q$3="",0,P35) -> 0
B36: =Assumptions!B329 -> Other Equity | C36: =Assumptions!D329 -> -117 | D36: =Assumptions!E329 -> -179 | E36: =Assumptions!F329 -> -172 | F36: =Assumptions!G329 -> -297 | G36: =Assumptions!H329 -> -260 | H36: =IF(H$3="",0,G36) -> -260 | I36: =IF(I$3="",0,H36) -> -260 | J36: =IF(J$3="",0,I36) -> -260 | K36: =IF(K$3="",0,J36) -> -260 | L36: =IF(L$3="",0,K36) -> -260 | M36: =IF(M$3="",0,L36) -> 0 | N36: =IF(N$3="",0,M36) -> 0 | O36: =IF(O$3="",0,N36) -> 0 | ... Q36: =IF(Q$3="",0,P36) -> 0
B37: =Assumptions!B332 -> Minority and Non-Controlling Interest | C37: =Assumptions!D332 -> 144 | D37: =Assumptions!E332 -> 132 | E37: =Assumptions!F332 -> 131 | F37: =Assumptions!G332 -> 109 | G37: =Assumptions!H332 -> 122 | H37: =IF(H$3="",0,G37) -> 122 | I37: =IF(I$3="",0,H37) -> 122 | J37: =IF(J$3="",0,I37) -> 122 | K37: =IF(K$3="",0,J37) -> 122 | L37: =IF(L$3="",0,K37) -> 122 | M37: =IF(M$3="",0,L37) -> 0 | N37: =IF(N$3="",0,M37) -> 0 | O37: =IF(O$3="",0,N37) -> 0 | ... Q37: =IF(Q$3="",0,P37) -> 0
B38: =Assumptions!B335 -> Treasury Stock | C38: =Assumptions!D335 -> 4011 | D38: =Assumptions!E335 -> 4145 | E38: =Assumptions!F335 -> 4138 | F38: =Assumptions!G335 -> 4683 | G38: =Assumptions!H335 -> 4972 | H38: =IF(H$3="",0,G38) -> 4972 | I38: =IF(I$3="",0,H38) -> 4972 | J38: =IF(J$3="",0,I38) -> 4972 | K38: =IF(K$3="",0,J38) -> 4972 | L38: =IF(L$3="",0,K38) -> 4972 | M38: =IF(M$3="",0,L38) -> 0 | N38: =IF(N$3="",0,M38) -> 0 | O38: =IF(O$3="",0,N38) -> 0 | ... Q38: =IF(Q$3="",0,P38) -> 0
B39: Balancing Figure
B40: ="Total "&B32 -> Total Equity | C40: =SUM(C33:C37)-C38+C39 -> 14226 | D40: =SUM(D33:D37)-D38+D39 -> 15386 | E40: =SUM(E33:E37)-E38+E39 -> 17854 | F40: =SUM(F33:F37)-F38+F39 -> 19811 | G40: =SUM(G33:G37)-G38+G39 -> 18255 | H40: =SUM(H33:H37)-H38+H39 -> 20686.484 | I40: =SUM(I33:I37)-I38+I39 -> 23212.684 | J40: =SUM(J33:J37)-J38+J39 -> 25822.278 | ... Q40: =SUM(Q33:Q37)-Q38+Q39 -> 0
B42: ="Total "&B19&" and "&B32 -> Total Liabilities and Equity | C42: =C29+C40 -> 33097 | D42: =D29+D40 -> 34456 | E42: =E29+E40 -> 36309 | F42: =F29+F40 -> 36821 | G42: =G29+G40 -> 36251 | H42: =H29+H40 -> 37630.903 | I42: =I29+I40 -> 39879.283 | J42: =J29+J40 -> 42645.596 | ... Q42: =Q29+Q40 -> 0
B43: A = L + E Check, A > L + E = Positive, A < L + E = Negative | C43: =C16-C42 -> -167 | D43: =D16-D42 -> -1272 | E43: =E16-E42 -> -279 | F43: =F16-F42 -> -871 | G43: =G16-G42 -> -587 | H43: =H16-H42 -> -783.63118 | I43: =I16-I42 -> -1359.6784 | J43: =J16-J42 -> -2280.0299 | ... Q43: =Q16-Q42 -> 0
B46: Ratios
